Workbook
Name A: 'Cost Until 07-26'!$F$7
Name B: 'Cost Until 07-26'!$C:$D

Sheet Sum_detailed
B2: EPC | C2: 100 | D2: =SUM(Budget!F2:F22) -> 0 | E2: =SUM(Budget!G2:G22) -> 509.6 | F2: =SUM(Budget!H2:H22) -> 30509.6 | G2: =SUM(Budget!I2:I22) -> 25742.817 | H2: =SUM(Budget!J2:J22) -> 509.6 | I2: =SUM(Budget!K2:K22) -> 36384.257 | J2: =SUM(Budget!L2:L22) -> 20767.896 | K2: =SUM(Budget!M2:M22) -> 9937.2194 | ... KI2: =SUM(Budget!KK2:KK22) -> 0
B3: Advance Payment | C3: 101
B4: PID | C4: 102
B5: ITS | C5: 103
B6: Contruction Toll Plaza | C6: 104
B7: EPC Others | C7: 105
B8: Expropriation & Land Acquisition | C8: 106
B9: Utility Relocation | C9: 107
B10: Citizen & Enviromental Studies | C10: 108
B11: EPC Works | C11: 109
B12: Construction Department Others | C12: 110
B13: MAINTENANCE | C13: 200 | D13: =SUM(Budget!F23:F35) -> 2301.1395 | E13: =SUM(Budget!G23:G35) -> 11526.102 | F13: =SUM(Budget!H23:H35) -> 11749.198 | G13: =SUM(Budget!I23:I35) -> 12556.52 | H13: =SUM(Budget!J23:J35) -> 16696.956 | I13: =SUM(Budget!K23:K35) -> 14984.371 | J13: =SUM(Budget!L23:L35) -> 11818.264 | K13: =SUM(Budget!M23:M35) -> 11633.837 | ... KI13: =SUM(Budget!KK23:KK35) -> 0
B14: Routine Maintenance | C14: 201
B15: Major Maintenances | C15: 202
B16: RM-MM | C16: 203
B17: Maintenance Studies | C17: 204
B18: Maintenance Others Works | C18: 205
B19: Maintenance ASG-Toll Plaza | C19: 206
B20: OPERATIONS | C20: 300 | D20: =SUM(Budget!F36:F42) -> 47139 | E20: =SUM(Budget!G36:G42) -> 17169.422 | F20: =SUM(Budget!H36:H42) -> 17890.711 | G20: =SUM(Budget!I36:I42) -> 16737.939 | H20: =SUM(Budget!J36:J42) -> 19869.528 | I20: =SUM(Budget!K36:K42) -> 20009.026 | J20: =SUM(Budget!L36:L42) -> 23938.713 | K20: =SUM(Budget!M36:M42) -> 19341.088 | ... KI20: =SUM(Budget!KK36:KK42) -> 0
B21: Operations | C21: 301
B22: Backoffice | C22: 302
B23: SPV | C23: 400 | D23: =SUM(Budget!F43:F48) -> 3639.9695 | E23: =SUM(Budget!G43:G48) -> 5932.2995 | F23: =SUM(Budget!H43:H48) -> 6093.9695 | G23: =SUM(Budget!I43:I48) -> 5479.2895 | H23: =SUM(Budget!J43:J48) -> 26444.96 | I23: =SUM(Budget!K43:K48) -> 9851.4395 | J23: =SUM(Budget!L43:L48) -> 10184.46 | K23: =SUM(Budget!M43:M48) -> 10989.8 | ... KI23: =SUM(Budget!KK43:KK48) -> 0
B24: Administration Department | C24: 401
B25: Others | C25: 402
B26: Legal Department | C26: 403
B27: HR Department | C27: 404
B28: Finance Department | C28: 405
B29: Economic Department | C29: 406
B30: Utilities | C30: 407
B31: IGYC Costs | C31: 408
B32: MOP | C32: 500
B33: Revenue Sharing | C33: 501
B34: Contract Management Fees | C34: 502
B35: Franchise Fees | C35: 503
... B41: Other Financing Fees | C41: 603
B42: INSURANCE & GUARANTEE | C42: 700 | D42: =SUM(Budget!F49:F50) -> 3242.5833 | E42: =SUM(Budget!G49:G50) -> 3242.5833 | F42: =SUM(Budget!H49:H50) -> 3242.5833 | G42: =SUM(Budget!I49:I50) -> 3242.5833 | H42: =SUM(Budget!J49:J50) -> 3242.5833 | I42: =SUM(Budget!K49:K50) -> 3242.5833 | J42: =SUM(Budget!L49:L50) -> 3242.5833 | K42: =SUM(Budget!M49:M50) -> 3242.5833 | ... KI42: =SUM(Budget!KK49:KK50) -> 0
B43: Insurance | C43: 701
B44: Guarantee | C44: 702
B45: TAX | C45: 800
B46: VAT | C46: 801
B47: Income Tax | C47: 802
B48: Municipal Patent | C48: 803
B49: Other Tax | C49: 804

Sheet Summary
E3: UNTIL JULY 2026
C4: ITEM | D4: CATEGORY | E4: BUDGET | F4: COST
C5: EPC | D5: 100 | E5: =Balance!D2 -> 2748292.4 | F5: =Balance!D10 -> 2655427.5
C6: ROUTINE MAINTENANCE | D6: 201 | E6: =Balance!D3 -> 606587.55 | F6: =Balance!D11 -> 576929
C7: MAJOR MAINTENANCE | D7: 202 | E7: =Balance!D4 -> 1020526.4 | F7: =Balance!D12 -> 1043357.8
C8: OPERATIONS | D8: 300 | E8: =Balance!D5 -> 1858373.1 | F8: =Balance!D13 -> 1808099.6
C9: SPV | D9: 400 | E9: =Balance!D6 -> 862102.27 | F9: =Balance!D14 -> 625741.07
C10: MOP | D10: 500 | E10: =Balance!D7 -> 8357719.8 | F10: =Balance!D15+Balance!D16+Balance!D17 -> 6377940
C11: INSURANCE & GUARANTEE | D11: 700 | E11: =Balance!D8 -> 206091.06 | F11: =Balance!D18 -> 202513
C12: TAX | D12: 800 | E12: =Balance!D9 -> 129962.5 | F12: =Balance!D19 -> 54110.842
D13: TOTAL | E13: =SUM(E5:E12) -> 15789655 | F13: =SUM(F5:F12) -> 13344119
C15: * June 2026 cost is based on estimates

Sheet Balance
B1: ITEM | C1: CATEGORY | D1: JULY 2026 | E1: =Budget!F1 -> 44287 | F1: =Budget!G1 -> 44317 | G1: =Budget!H1 -> 44348 | H1: =Budget!I1 -> 44378 | I1: =Budget!J1 -> 44409 | J1: =Budget!K1 -> 44440 | K1: =Budget!L1 -> 44470 | L1: =Budget!M1 -> 44501 | ... KG1: =Budget!KH1 -> 53053
A2: BUDGET | B2: EPC | C2: 100 | D2: =SUM(E2:BP2) -> 2748292.4 | E2: =SUM(Budget!F2:F22) -> 0 | F2: =SUM(Budget!G2:G22) -> 509.6 | G2: =SUM(Budget!H2:H22) -> 30509.6 | H2: =SUM(Budget!I2:I22) -> 25742.817 | I2: =SUM(Budget!J2:J22) -> 509.6 | J2: =SUM(Budget!K2:K22) -> 36384.257 | K2: =SUM(Budget!L2:L22) -> 20767.896 | L2: =SUM(Budget!M2:M22) -> 9937.2194 | ... KG2: =SUM(Budget!KH2:KH22) -> 0
B3: ROUTINE MAINTENANCE | C3: 200 | D3: =SUM(E3:BP3) -> 606587.55 | E3: =SUM(Budget!F29:F34) -> 0 | F3: =SUM(Budget!G29:G34) -> 8500 | G3: =SUM(Budget!H29:H34) -> 8500 | H3: =SUM(Budget!I29:I34) -> 8500 | I3: =SUM(Budget!J29:J34) -> 8500 | J3: =SUM(Budget!K29:K34) -> 10751.164 | K3: =SUM(Budget!L29:L34) -> 8500 | L3: =SUM(Budget!M29:M34) -> 8500 | ... KG3: =SUM(Budget!KH29:KH34) -> 10000
B4: MAJOR MAINTENANCE | C4: 200 | D4: =SUM(E4:BP4) -> 1020526.4 | E4: =SUM(Budget!F23:F28) -> 0 | F4: =SUM(Budget!G23:G28) -> 0 | G4: =SUM(Budget!H23:H28) -> 0 | H4: =SUM(Budget!I23:I28) -> 0 | I4: =SUM(Budget!J23:J28) -> 0 | J4: =SUM(Budget!K23:K28) -> 0 | K4: =SUM(Budget!L23:L28) -> 0 | L4: =SUM(Budget!M23:M28) -> 0 | ... KG4: =SUM(Budget!KH23:KH28) -> 10000
B5: OPERATIONS | C5: 300 | D5: =SUM(E5:BP5) -> 1858373.1 | E5: =SUM(Budget!F35:F42) -> 49440.14 | F5: =SUM(Budget!G35:G42) -> 20195.524 | G5: =SUM(Budget!H35:H42) -> 21139.909 | H5: =SUM(Budget!I35:I42) -> 20794.459 | I5: =SUM(Budget!J35:J42) -> 28066.484 | J5: =SUM(Budget!K35:K42) -> 24242.233 | K5: =SUM(Budget!L35:L42) -> 27256.977 | L5: =SUM(Budget!M35:M42) -> 22474.925 | ... KG5: =SUM(Budget!KH35:KH42) -> 24152.58
B6: SPV | C6: 400 | D6: =SUM(E6:BP6) -> 862102.27 | E6: =SUM(Budget!F43:F48)+Budget!F53 -> 4435.7627 | F6: =SUM(Budget!G43:G48)+Budget!G53 -> 6728.0927 | G6: =SUM(Budget!H43:H48)+Budget!H53 -> 6889.7627 | H6: =SUM(Budget!I43:I48)+Budget!I53 -> 6275.0827 | I6: =SUM(Budget!J43:J48)+Budget!J53 -> 27240.753 | J6: =SUM(Budget!K43:K48)+Budget!K53 -> 10647.233 | K6: =SUM(Budget!L43:L48)+Budget!L53 -> 10980.253 | L6: =SUM(Budget!M43:M48)+Budget!M53 -> 11785.593 | ... KG6: =SUM(Budget!KH43:KH48)+Budget!KH53 -> 0
B7: MOP | C7: 500 | D7: =SUM(E7:BP7) -> 8357719.8 | E7: =Budget!F51 -> 18947.456 | F7: =Budget!G51 -> 18947.456 | G7: =Budget!H51 -> 18947.456 | H7: =Budget!I51 -> 18947.456 | I7: =Budget!J51 -> 18947.456 | J7: =Budget!K51 -> 18947.456 | K7: =Budget!L51 -> 18947.456 | L7: =Budget!M51 -> 18947.456 | ... KG7: =Budget!KH51 -> 0
B8: INSURANCE & GUARANTEE | C8: 700 | D8: =SUM(E8:BP8) -> 206091.06 | E8: =SUM(Budget!F49:F50) -> 3242.5833 | F8: =SUM(Budget!G49:G50) -> 3242.5833 | G8: =SUM(Budget!H49:H50) -> 3242.5833 | H8: =SUM(Budget!I49:I50) -> 3242.5833 | I8: =SUM(Budget!J49:J50) -> 3242.5833 | J8: =SUM(Budget!K49:K50) -> 3242.5833 | K8: =SUM(Budget!L49:L50) -> 3242.5833 | L8: =SUM(Budget!M49:M50) -> 3242.5833 | ... KG8: =SUM(Budget!KH49:KH50) -> 0
B9: TAX | C9: 800 | D9: =SUM(E9:BP9) -> 129962.5 | E9: =Budget!F52 -> 5981.9924 | F9: =Budget!G52 -> 0 | G9: =Budget!H52 -> 0 | H9: =Budget!I52 -> 0 | I9: =Budget!J52 -> 0 | J9: =Budget!K52 -> 0 | K9: =Budget!L52 -> 0 | L9: =Budget!M52 -> 0 | ... KG9: =Budget!KH52 -> 0
A10: COST | B10: EPC | C10: 100 | D10: =SUM(E10:BP10) -> 2655427.5 | E10: ='Cost Until 07-26'!G2+'Cost Until 07-26'!G31 -> 0 | F10: ='Cost Until 07-26'!H2+'Cost Until 07-26'!H31 -> 34620 | G10: ='Cost Until 07-26'!I2+'Cost Until 07-26'!I31 -> 1801 | H10: ='Cost Until 07-26'!J2+'Cost Until 07-26'!J31 -> 10517 | I10: ='Cost Until 07-26'!K2+'Cost Until 07-26'!K31 -> 27584 | J10: ='Cost Until 07-26'!L2+'Cost Until 07-26'!L31 -> 19328 | K10: ='Cost Until 07-26'!M2+'Cost Until 07-26'!M31 -> 13171 | L10: ='Cost Until 07-26'!N2+'Cost Until 07-26'!N31 -> 6523 | ... KG10: ='Cost Until 07-26'!KI2+'Cost Until 07-26'!KI31 -> 0
B11: ROUTINE MAINTENANCE | C11: 200 | D11: =SUM(E11:BP11) -> 576929 | E11: =SUM('Cost Until 07-26'!G48:G50) -> 0 | F11: =SUM('Cost Until 07-26'!H48:H50) -> 1498 | G11: =SUM('Cost Until 07-26'!I48:I50) -> 261 | H11: =SUM('Cost Until 07-26'!J48:J50) -> 105 | I11: =SUM('Cost Until 07-26'!K48:K50) -> 69 | J11: =SUM('Cost Until 07-26'!L48:L50) -> 492 | K11: =SUM('Cost Until 07-26'!M48:M50) -> 45901 | L11: =SUM('Cost Until 07-26'!N48:N50) -> 25500 | ... KG11: =SUM('Cost Until 07-26'!KI48:KI50) -> 0
B12: MAJOR MAINTENANCE | C12: 200 | D12: =SUM(E12:BP12) -> 1043357.8 | E12: =SUM('Cost Until 07-26'!G51:G61) -> 0 | F12: =SUM('Cost Until 07-26'!H51:H61) -> 0 | G12: =SUM('Cost Until 07-26'!I51:I61) -> 0 | H12: =SUM('Cost Until 07-26'!J51:J61) -> 0 | I12: =SUM('Cost Until 07-26'!K51:K61) -> 0 | J12: =SUM('Cost Until 07-26'!L51:L61) -> 1106 | K12: =SUM('Cost Until 07-26'!M51:M61) -> 1156 | L12: =SUM('Cost Until 07-26'!N51:N61) -> 0 | ... AZ12: =SUM('Cost Until 07-26'!BB51:BB61) -> 88747 | BA12: =SUM('Cost Until 07-26'!BC51:BC58)+SUM('Cost Until 07-26'!BC60:BC61) -> 15299 | BB12: =SUM('Cost Until 07-26'!BD51:BD58)+SUM('Cost Until 07-26'!BD60:BD61) -> 10998 | BC12: =SUM('Cost Until 07-26'!BE51:BE58)+SUM('Cost Until 07-26'!BE60:BE61) -> 22188.525 | BD12: =SUM('Cost Until 07-26'!BF51:BF58)+SUM('Cost Until 07-26'!BF60:BF61) -> 105.45456 | BE12: =SUM('Cost Until 07-26'!BG51:BG58)+SUM('Cost Until 07-26'!BG60:BG61) -> 49768.974 | BF12: =SUM('Cost Until 07-26'!BH51:BH58)+SUM('Cost Until 07-26'!BH60:BH61) -> 115.97354 | BG12: =SUM('Cost Until 07-26'!BI51:BI58)+SUM('Cost Until 07-26'!BI60:BI61) -> 48428.974 | BH12: =SUM('Cost Until 07-26'!BJ51:BJ58)+SUM('Cost Until 07-26'!BJ60:BJ61) -> 49131.67 | ... BM12: =SUM('Cost Until 07-26'!BO51:BO58)+SUM('Cost Until 07-26'!BO60:BO61) -> 106.94995 | BN12: =SUM('Cost Until 07-26'!BP51:BP61) -> 106.90117 | BO12: =SUM('Cost Until 07-26'!BQ51:BQ61) -> 1120.5312 | BP12: =SUM('Cost Until 07-26'!BR51:BR61) -> 14837.194 | BQ12: =SUM('Cost Until 07-26'!BS51:BS61) -> 0 | BR12: =SUM('Cost Until 07-26'!BT51:BT61) -> 0 | BS12: =SUM('Cost Until 07-26'!BU51:BU61) -> 0 | BT12: =SUM('Cost Until 07-26'!BV51:BV61) -> 0 | BU12: =SUM('Cost Until 07-26'!BW51:BW61) -> 0 | ... KG12: =SUM('Cost Until 07-26'!KI51:KI61) -> 0
B13: OPERATIONS | C13: 300 | D13: =SUM(E13:BP13) -> 1808099.6 | E13: ='Cost Until 07-26'!G62 -> 31312 | F13: ='Cost Until 07-26'!H62 -> 17724 | G13: ='Cost Until 07-26'!I62 -> 16577 | H13: ='Cost Until 07-26'!J62 -> 17453 | I13: ='Cost Until 07-26'!K62 -> 21441 | J13: ='Cost Until 07-26'!L62 -> 32810 | K13: ='Cost Until 07-26'!M62 -> 21600 | L13: ='Cost Until 07-26'!N62 -> 20279 | ... KG13: ='Cost Until 07-26'!KI62 -> 0
B14: SPV | C14: 400 | D14: =SUM(E14:BP14) -> 625741.07 | E14: ='Cost Until 07-26'!G129 -> 760 | F14: ='Cost Until 07-26'!H129 -> 5027 | G14: ='Cost Until 07-26'!I129 -> 4700 | H14: ='Cost Until 07-26'!J129 -> 3416 | I14: ='Cost Until 07-26'!K129 -> 15672 | J14: ='Cost Until 07-26'!L129 -> 3729 | K14: ='Cost Until 07-26'!M129 -> 11017 | L14: ='Cost Until 07-26'!N129 -> 7959 | ... KG14: ='Cost Until 07-26'!KI129 -> 0
B15: MOP - GOODS & RIGHTS | C15: 501 | D15: =SUM(E15:BP15) -> 2232000 | E15: ='Cost Until 07-26'!G44 -> 0 | F15: ='Cost Until 07-26'!H44 -> 0 | G15: ='Cost Until 07-26'!I44 -> 0 | H15: ='Cost Until 07-26'!J44 -> 0 | I15: ='Cost Until 07-26'!K44 -> 0 | J15: ='Cost Until 07-26'!L44 -> 0 | K15: ='Cost Until 07-26'!M44 -> 0 | L15: ='Cost Until 07-26'!N44 -> 0 | ... BP15: ='Cost Until 07-26'!BR44 -> 0
B16: MOP - PRE-EXISTING INFRASTRUCTURE | C16: 502 | D16: =SUM(E16:BP16) -> 3001047 | E16: ='Cost Until 07-26'!G45 -> 0 | F16: ='Cost Until 07-26'!H45 -> 0 | G16: ='Cost Until 07-26'!I45 -> 0 | H16: ='Cost Until 07-26'!J45 -> 0 | I16: ='Cost Until 07-26'!K45 -> 0 | J16: ='Cost Until 07-26'!L45 -> 0 | K16: ='Cost Until 07-26'!M45 -> 0 | L16: ='Cost Until 07-26'!N45 -> 0 | ... BP16: ='Cost Until 07-26'!BR45 -> 0
B17: MOP - TOLL REVENUE SHARING | C17: 503 | D17: =SUM(E17:BP17) -> 1144893 | E17: ='Cost Until 07-26'!G46 -> 0 | F17: ='Cost Until 07-26'!H46 -> 16284.864 | G17: ='Cost Until 07-26'!I46 -> 18467.727 | H17: ='Cost Until 07-26'!J46 -> 18410.304 | I17: ='Cost Until 07-26'!K46 -> 23018.454 | J17: ='Cost Until 07-26'!L46 -> 21517.786 | K17: ='Cost Until 07-26'!M46 -> 21810.214 | L17: ='Cost Until 07-26'!N46 -> 21749.376 | ... BP17: ='Cost Until 07-26'!BR46 -> 17486.47 | BQ17: ='Cost Until 07-26'!BS43 -> 0 | BR17: ='Cost Until 07-26'!BT43 -> 0 | BS17: ='Cost Until 07-26'!BU43 -> 0 | BT17: ='Cost Until 07-26'!BV43 -> 0 | BU17: ='Cost Until 07-26'!BW43 -> 0 | BV17: ='Cost Until 07-26'!BX43 -> 0 | BW17: ='Cost Until 07-26'!BY43 -> 0 | BX17: ='Cost Until 07-26'!BZ43 -> 0 | ... KG17: ='Cost Until 07-26'!KI43 -> 0
B18: INSURANCE & GUARANTEE | C18: 700 | D18: =SUM(E18:BP18) -> 202513 | E18: ='Cost Until 07-26'!G35 -> 948 | F18: ='Cost Until 07-26'!H35 -> 25300 | G18: ='Cost Until 07-26'!I35 -> 7582 | H18: ='Cost Until 07-26'!J35 -> 2 | I18: ='Cost Until 07-26'!K35 -> 0 | J18: ='Cost Until 07-26'!L35 -> 0 | K18: ='Cost Until 07-26'!M35 -> 0 | L18: ='Cost Until 07-26'!N35 -> 0 | ... KG18: ='Cost Until 07-26'!KI35 -> 0
B19: TAX | C19: 800 | D19: =SUM(E19:BP19) -> 54110.842 | E19: ='Cost Until 07-26'!G597 -> 0 | F19: ='Cost Until 07-26'!H597 -> 84 | G19: ='Cost Until 07-26'!I597 -> 1439 | H19: ='Cost Until 07-26'!J597 -> 589 | I19: ='Cost Until 07-26'!K597 -> 7463 | J19: ='Cost Until 07-26'!L597 -> 7620 | K19: ='Cost Until 07-26'!M597 -> 4802 | L19: ='Cost Until 07-26'!N597 -> 732 | ... KG19: ='Cost Until 07-26'!KI597 -> 0
D21: JULY 2026 | E21: =E1 -> 44287 | F21: =F1 -> 44317 | G21: =G1 -> 44348 | H21: =H1 -> 44378 | I21: =I1 -> 44409 | J21: =J1 -> 44440 | K21: =K1 -> 44470 | L21: =L1 -> 44501 | ... KG21: =KG1 -> 53053
B22: BUDGET | C22: Partial | D22: =BP22 -> 126542.62 | E22: =SUM(E2:E9) -> 82047.934 | F22: =SUM(F2:F9) -> 58123.256 | G22: =SUM(G2:G9) -> 89229.311 | H22: =SUM(H2:H9) -> 83502.398 | I22: =SUM(I2:I9) -> 86506.876 | J22: =SUM(J2:J9) -> 104214.93 | K22: =SUM(K2:K9) -> 89695.165 | L22: =SUM(L2:L9) -> 74887.776 | ... KG22: =SUM(KG2:KG9) -> 44152.58
C23: Cumulative | D23: =BP23 -> 15789655 | E23: =E22 -> 82047.934 | F23: =E23+F22 -> 140171.19 | G23: =F23+G22 -> 229400.5 | H23: =G23+H22 -> 312902.9 | I23: =H23+I22 -> 399409.77 | J23: =I23+J22 -> 503624.7 | K23: =J23+K22 -> 593319.87 | L23: =K23+L22 -> 668207.64 | M23: =L23+M22 -> 742719.93 | ... KG23: =KF23+KG22 -> 52463876
B24: COST | C24: Partial | D24: =BP24 -> 75144.169 | E24: =SUM(E10:E19) -> 33020 | F24: =SUM(F10:F19) -> 100537.86 | G24: =SUM(G10:G19) -> 50827.727 | H24: =SUM(H10:H19) -> 50492.304 | I24: =SUM(I10:I19) -> 95247.454 | J24: =SUM(J10:J19) -> 86602.786 | K24: =SUM(K10:K19) -> 119457.21 | L24: =SUM(L10:L19) -> 82742.376 | ... KG24: =SUM(KG10:KG19) -> 0
C25: Cumulative | D25: =BP25 -> 13344119 | E25: =E24 -> 33020 | F25: =E25+F24 -> 133557.86 | G25: =F25+G24 -> 184385.59 | H25: =G25+H24 -> 234877.89 | I25: =H25+I24 -> 330125.35 | J25: =I25+J24 -> 416728.13 | K25: =J25+K24 -> 536185.35 | L25: =K25+L24 -> 618927.72 | M25: =L25+M24 -> 692450.57 | ... KG25: =KF25+KG24 -> 13344119
B26: BALANCE | C26: Partial | D26: =BP26 -> 51398.452 | E26: =E22-E24 -> 49027.934 | F26: =F22-F24 -> -42414.608 | G26: =G22-G24 -> 38401.584 | H26: =H22-H24 -> 33010.094 | I26: =I22-I24 -> -8740.5779 | J26: =J22-J24 -> 17612.14 | K26: =K22-K24 -> -29762.049 | L26: =L22-L24 -> -7854.6 | ... KG26: =KG22-KG24 -> 44152.58
C27: Cumulative | D27: =BP27 -> 2445536.3 | E27: =E26 -> 49027.934 | F27: =E27+F26 -> 6613.3264 | G27: =F27+G26 -> 45014.91 | H27: =G27+H26 -> 78025.004 | I27: =H27+I26 -> 69284.426 | J27: =I27+J26 -> 86896.566 | K27: =J27+K26 -> 57134.518 | L27: =K27+L26 -> 49279.918 | M27: =L27+M26 -> 50269.364 | ... KG27: =KF27+KG26 -> 39119758
B28: DEVIATION | D28: =BP28 -> 0.15488219 | E28: =E27/E23 -> 0.59755233 | F28: =F27/F23 -> 0.047180354 | G28: =G27/G23 -> 0.19622847 | H28: =H27/H23 -> 0.24935852 | I28: =I27/I23 -> 0.17346703 | J28: =J27/J23 -> 0.1725423 | K28: =K27/K23 -> 0.096296316 | L28: =L27/L23 -> 0.073749407 | ... KG28: =KG27/KG23 -> 0.7456513
D31: JUNE 2026 | E31: =E1 -> 44287 | F31: =F1 -> 44317 | G31: =G1 -> 44348 | H31: =H1 -> 44378 | I31: =I1 -> 44409 | J31: =J1 -> 44440 | K31: =K1 -> 44470 | L31: =L1 -> 44501 | ... BP31: =BP1 -> 46204
B32: INCOME | C32: Received | D32: =BO32 -> 175424 | E32: 163558.79 | F32: 185438.13 | G32: 184615.19 | H32: 231026.67 | I32: 216777.15 | J32: 219744.71 | K32: 220482.32 | L32: 217543.05 | M32: 234143.65 | N32: 259569.13 | O32: 229642.98 | P32: 227604.62 | Q32: 189227.97 | R32: 189968.23 | S32: 174106.41 | T32: 179970.33 | U32: 159287.35 | V32: 114801.05 | W32: 76615.087 | X32: 69817.746 | Y32: 95516.665 | Z32: 120058.77 | AA32: 125043.68 | AB32: 141794.14 | AC32: 187292.87 | AD32: 215588.01 | AE32: 191701.88 | AF32: 170835.27 | AG32: 181884.68 | AH32: 153320.58 | AI32: 174106.31 | AJ32: 204519.07 | AK32: 157652.45 | AL32: 207530.94 | AM32: 175053.42 | AN32: 204465.23 | AO32: 179821.93 | AP32: 191142.78 | AQ32: 170358.49 | AR32: 173996.35 | AS32: 175200.01 | AT32: 157573.15 | AU32: 193730.41 | AV32: 173103.52 | AW32: 195374.77 | AX32: 207026.61 | AY32: 197134.22 | AZ32: 236458.64 | BA32: 184024.81 | BB32: 194580.53 | BC32: 193264.71 | BD32: 167365.69 | BE32: 163120.77 | BF32: 173416.98 | BG32: 189320.7 | BH32: 192997.53 | BI32: 194370.89 | BJ32: 204609.58 | BK32: 197419.78 | BL32: 210056 | BM32: 185303 | BN32: 187799 | BO32: 175424 | BP32: TBD
C33: Accrued | D33: =BO33 -> 190119 | E33: 163694.08 | F33: 185779.82 | G33: 185012.69 | H33: 231257.96 | I33: 217019.03 | J33: 219954.14 | K33: 220714.87 | L33: 218702.4 | M33: 234384.26 | N33: 262400.83 | O33: 236326.29 | P33: 229613.1 | Q33: 191383.74 | R33: 194401.83 | S33: 180662.55 | T33: 185844.67 | U33: 168379.5 | V33: 177424.06 | W33: 188972.25 | X33: 184693.93 | Y33: 203815.52 | Z33: 223035.07 | AA33: 224547.5 | AB33: 197586.93 | AC33: 190470.88 | AD33: 179123.85 | AE33: 161412.97 | AF33: 190755.9 | AG33: 177541.59 | AH33: 209113.2 | AI33: 199950.2 | AJ33: 189698.24 | AK33: 210783.72 | AL33: 252213.39 | AM33: 263820.77 | AN33: 216738.08 | AO33: 207453.71 | AP33: 188914.22 | AQ33: 173379.93 | AR33: 206634.13 | AS33: 193707.23 | AT33: 207593.55 | AU33: 206640.35 | AV33: 203051.57 | AW33: 222615.6 | AX33: 259350.97 | AY33: 267386.56 | AZ33: 231402.25 | BA33: 217040.84 | BB33: 198514.09 | BC33: 197471.86 | BD33: 202730.79 | BE33: 197425.27 | BF33: 205123.42 | BG33: 207446.85 | BH33: 204496.26 | BI33: 228809.91 | BJ33: 259658.4 | BK33: 267614.29 | BL33: 228145 | BM33: 209097 | BN33: 193543 | BO33: 190119 | BP33: TBD
D35: JUNE 2026
B36: ADDITIONAL WORKS | C36: Partial | D36: =BO36 -> 0 | AX36: ='Cost Until 07-26'!AZ59 -> 20000 | AY36: ='Cost Until 07-26'!BA59 -> 0 | AZ36: ='Cost Until 07-26'!BB59 -> 0 | BA36: ='Cost Until 07-26'!BC59 -> 0 | BB36: ='Cost Until 07-26'!BD59 -> 5989 | BC36: ='Cost Until 07-26'!BE59 -> 0 | BD36: ='Cost Until 07-26'!BF59 -> 0 | BE36: ='Cost Until 07-26'!BG59 -> 0 | ... BP36: ='Cost Until 07-26'!BR59 -> 0
C37: Cumulative | D37: =BN37 -> 128716.88 | AX37: =AX36 -> 20000 | AY37: =AX37+AY36 -> 20000 | AZ37: =AY37+AZ36 -> 20000 | BA37: =AZ37+BA36 -> 20000 | BB37: =BA37+BB36 -> 25989 | BC37: =BB37+BC36 -> 25989 | BD37: =BC37+BD36 -> 25989 | BE37: =BD37+BE36 -> 25989 | BF37: =BE37+BF36 -> 25989 | ... BP37: =BO37+BP36 -> 128716.88
A43: MAJOR MAINTENANCE | B43: BUDGET | C43: Partial | E43: =SUM(E4) -> 0 | F43: =SUM(F4) -> 0 | G43: =SUM(G4) -> 0 | H43: =SUM(H4) -> 0 | I43: =SUM(I4) -> 0 | J43: =SUM(J4) -> 0 | K43: =SUM(K4) -> 0 | L43: =SUM(L4) -> 0 | ... BM43: =SUM(BM4) -> 47370
C44: Cumulative | E44: =D44+E43 -> 0 | F44: =E44+F43 -> 0 | G44: =F44+G43 -> 0 | H44: =G44+H43 -> 0 | I44: =H44+I43 -> 0 | J44: =I44+J43 -> 0 | K44: =J44+K43 -> 0 | L44: =K44+L43 -> 0 | ... BM44: =BL44+BM43 -> 1006420.4
B45: COST | C45: Partial | E45: =SUM(E12) -> 0 | F45: =SUM(F12) -> 0 | G45: =SUM(G12) -> 0 | H45: =SUM(H12) -> 0 | I45: =SUM(I12) -> 0 | J45: =SUM(J12) -> 1106 | K45: =SUM(K12) -> 1156 | L45: =SUM(L12) -> 0 | ... BM45: =SUM(BM12) -> 106.94995
C46: Cumulative | E46: =D46+E45 -> 0 | F46: =E46+F45 -> 0 | G46: =F46+G45 -> 0 | H46: =G46+H45 -> 0 | I46: =H46+I45 -> 0 | J46: =I46+J45 -> 1106 | K46: =J46+K45 -> 2262 | L46: =K46+L45 -> 2262 | ... BM46: =BL46+BM45 -> 1027293.2
B47: BALANCE | C47: Partial | E47: =E43-E45 -> 0 | F47: =F43-F45 -> 0 | G47: =G43-G45 -> 0 | H47: =H43-H45 -> 0 | I47: =I43-I45 -> 0 | J47: =J43-J45 -> -1106 | K47: =K43-K45 -> -1156 | L47: =L43-L45 -> 0 | ... BM47: =BM43-BM45 -> 47263.05
C48: Cumulative | E48: =E47 -> 0 | F48: =F47+E48 -> 0 | G48: =G47+F48 -> 0 | H48: =H47+G48 -> 0 | I48: =I47+H48 -> 0 | J48: =J47+I48 -> -1106 | K48: =K47+J48 -> -2262 | L48: =L47+K48 -> -2262 | M48: =M47+L48 -> -2262 | ... BM48: =BM47+BL48 -> -20872.733
B49: DEVIATION | E49: =E48/E44 -> #DIV/0! | F49: =F48/F44 -> #DIV/0! | G49: =G48/G44 -> #DIV/0! | H49: =H48/H44 -> #DIV/0! | I49: =I48/I44 -> #DIV/0! | J49: =J48/J44 -> #DIV/0! | K49: =K48/K44 -> #DIV/0! | L49: =L48/L44 -> #DIV/0! | ... BM49: =BM48/BM44 -> -0.020739576

Sheet Sofia's Query
B1: ITEM | C1: CATEGORY | D1: APR 2026 | E1: =Budget!F1 -> 44287 | F1: =Budget!G1 -> 44317 | G1: =Budget!H1 -> 44348 | H1: =Budget!I1 -> 44378 | I1: =Budget!J1 -> 44409 | J1: =Budget!K1 -> 44440 | K1: =Budget!L1 -> 44470 | L1: =Budget!M1 -> 44501 | ... KG1: =Budget!KH1 -> 53053
A2: BUDGET | B2: EPC | C2: 100 | D2: =SUM(E2:BM2) -> 2646507 | E2: =Balance!E2 -> 0 | F2: =Balance!F2 -> 509.6 | G2: =Balance!G2 -> 30509.6 | H2: =Balance!H2 -> 25742.817 | I2: =Balance!I2 -> 509.6 | J2: =Balance!J2 -> 36384.257 | K2: =Balance!K2 -> 20767.896 | L2: =Balance!L2 -> 9937.2194 | ... KG2: =Balance!KG2 -> 0
B3: ROUTINE MAINTENANCE | C3: 200 | D3: =SUM(E3:BM3) -> 576587.55 | E3: =Balance!E3 -> 0 | F3: =Balance!F3 -> 8500 | G3: =Balance!G3 -> 8500 | H3: =Balance!H3 -> 8500 | I3: =Balance!I3 -> 8500 | J3: =Balance!J3 -> 10751.164 | K3: =Balance!K3 -> 8500 | L3: =Balance!L3 -> 8500 | ... KG3: =Balance!KG3 -> 10000
B4: MAJOR MAINTENANCE | C4: 200 | D4: =SUM(E4:BM4) -> 1006420.4 | E4: =Balance!E4 -> 0 | F4: =Balance!F4 -> 0 | G4: =Balance!G4 -> 0 | H4: =Balance!H4 -> 0 | I4: =Balance!I4 -> 0 | J4: =Balance!J4 -> 0 | K4: =Balance!K4 -> 0 | L4: =Balance!L4 -> 0 | ... KG4: =Balance!KG4 -> 10000
B5: OPERATIONS | C5: 300 | D5: =SUM(E5:BM5) -> 1775113.5 | E5: =Balance!E5 -> 49440.14 | F5: =Balance!F5 -> 20195.524 | G5: =Balance!G5 -> 21139.909 | H5: =Balance!H5 -> 20794.459 | I5: =Balance!I5 -> 28066.484 | J5: =Balance!J5 -> 24242.233 | K5: =Balance!K5 -> 27256.977 | L5: =Balance!L5 -> 22474.925 | ... KG5: =Balance!KG5 -> 24152.58
B6: SPV | C6: 400 | D6: =SUM(E6:BM6) -> 839125.93 | E6: =Balance!E6 -> 4435.7627 | F6: =Balance!F6 -> 6728.0927 | G6: =Balance!G6 -> 6889.7627 | H6: =Balance!H6 -> 6275.0827 | I6: =Balance!I6 -> 27240.753 | J6: =Balance!J6 -> 10647.233 | K6: =Balance!K6 -> 10980.253 | L6: =Balance!L6 -> 11785.593 | ... KG6: =Balance!KG6 -> 0
B7: MOP | C7: 500 | D7: =SUM(E7:BM7) -> 8284097.5 | E7: =Balance!E7 -> 18947.456 | F7: =Balance!F7 -> 18947.456 | G7: =Balance!G7 -> 18947.456 | H7: =Balance!H7 -> 18947.456 | I7: =Balance!I7 -> 18947.456 | J7: =Balance!J7 -> 18947.456 | K7: =Balance!K7 -> 18947.456 | L7: =Balance!L7 -> 18947.456 | ... KG7: =Balance!KG7 -> 0
B8: INSURANCE & GUARANTEE | C8: 700 | D8: =SUM(E8:BM8) -> 205443.6 | E8: =Balance!E8 -> 3242.5833 | F8: =Balance!F8 -> 3242.5833 | G8: =Balance!G8 -> 3242.5833 | H8: =Balance!H8 -> 3242.5833 | I8: =Balance!I8 -> 3242.5833 | J8: =Balance!J8 -> 3242.5833 | K8: =Balance!K8 -> 3242.5833 | L8: =Balance!L8 -> 3242.5833 | ... KG8: =Balance!KG8 -> 0
B9: TAX | C9: 800 | D9: =SUM(E9:BM9) -> 129962.5 | E9: =Balance!E9 -> 5981.9924 | F9: =Balance!F9 -> 0 | G9: =Balance!G9 -> 0 | H9: =Balance!H9 -> 0 | I9: =Balance!I9 -> 0 | J9: =Balance!J9 -> 0 | K9: =Balance!K9 -> 0 | L9: =Balance!L9 -> 0 | ... KG9: =Balance!KG9 -> 0
A10: COST | B10: EPC | C10: 100 | D10: =SUM(E10:BM10) -> 2651925.9 | E10: =Balance!E10 -> 0 | F10: =Balance!F10 -> 34620 | G10: =Balance!G10 -> 1801 | H10: =Balance!H10 -> 10517 | I10: =Balance!I10 -> 27584 | J10: =Balance!J10 -> 19328 | K10: =Balance!K10 -> 13171 | L10: =Balance!L10 -> 6523 | ... KG10: =Balance!KG10 -> 0
B11: ROUTINE MAINTENANCE | C11: 200 | D11: =SUM(E11:BM11) -> 546929 | E11: =Balance!E11 -> 0 | F11: =Balance!F11 -> 1498 | G11: =Balance!G11 -> 261 | H11: =Balance!H11 -> 105 | I11: =Balance!I11 -> 69 | J11: =Balance!J11 -> 492 | K11: =Balance!K11 -> 45901 | L11: =Balance!L11 -> 25500 | ... KG11: =Balance!KG11 -> 0
B12: MAJOR MAINTENANCE | C12: 200 | D12: =SUM(E12:BM12) -> 1027293.2 | E12: =Balance!E12 -> 0 | F12: =Balance!F12 -> 0 | G12: =Balance!G12 -> 0 | H12: =Balance!H12 -> 0 | I12: =Balance!I12 -> 0 | J12: =Balance!J12 -> 1106 | K12: =Balance!K12 -> 1156 | L12: =Balance!L12 -> 0 | ... KG12: =Balance!KG12 -> 0
B13: OPERATIONS | C13: 300 | D13: =SUM(E13:BM13) -> 1734892.5 | E13: =Balance!E13 -> 31312 | F13: =Balance!F13 -> 17724 | G13: =Balance!G13 -> 16577 | H13: =Balance!H13 -> 17453 | I13: =Balance!I13 -> 21441 | J13: =Balance!J13 -> 32810 | K13: =Balance!K13 -> 21600 | L13: =Balance!L13 -> 20279 | ... KG13: =Balance!KG13 -> 0
B14: SPV | C14: 400 | D14: =SUM(E14:BM14) -> 608343.95 | E14: =Balance!E14 -> 760 | F14: =Balance!F14 -> 5027 | G14: =Balance!G14 -> 4700 | H14: =Balance!H14 -> 3416 | I14: =Balance!I14 -> 15672 | J14: =Balance!J14 -> 3729 | K14: =Balance!K14 -> 11017 | L14: =Balance!L14 -> 7959 | ... KG14: =Balance!KG14 -> 0
B15: MOP | C15: 500 | D15: =SUM(E15:BM15) -> 1090422.9 | E15: =Balance!E17 -> 0 | F15: =Balance!F17 -> 16284.864 | G15: =Balance!G17 -> 18467.727 | H15: =Balance!H17 -> 18410.304 | I15: =Balance!I17 -> 23018.454 | J15: =Balance!J17 -> 21517.786 | K15: =Balance!K17 -> 21810.214 | L15: =Balance!L17 -> 21749.376 | ... KG15: =Balance!KG17 -> 0
B16: INSURANCE & GUARANTEE | C16: 700 | D16: =SUM(E16:BM16) -> 202513 | E16: =Balance!E18 -> 948 | F16: =Balance!F18 -> 25300 | G16: =Balance!G18 -> 7582 | H16: =Balance!H18 -> 2 | I16: =Balance!I18 -> 0 | J16: =Balance!J18 -> 0 | K16: =Balance!K18 -> 0 | L16: =Balance!L18 -> 0 | ... KG16: =Balance!KG18 -> 0
B17: TAX | C17: 800 | D17: =SUM(E17:BM17) -> 52531.842 | E17: =Balance!E19 -> 0 | F17: =Balance!F19 -> 84 | G17: =Balance!G19 -> 1439 | H17: =Balance!H19 -> 589 | I17: =Balance!I19 -> 7463 | J17: =Balance!J19 -> 7620 | K17: =Balance!K19 -> 4802 | L17: =Balance!L19 -> 732 | ... KG17: =Balance!KG19 -> 0
B19: EPC | D19: MAY 2026 | E19: =E1 -> 44287 | F19: =F1 -> 44317 | G19: =G1 -> 44348 | H19: =H1 -> 44378 | I19: =I1 -> 44409 | J19: =J1 -> 44440 | K19: =K1 -> 44470 | L19: =L1 -> 44501 | ... KG19: =KG1 -> 53053
B20: BUDGET | C20: Partial | D20: =BN20 -> 38201.27 | E20: =E2 -> 0 | F20: =F2 -> 509.6 | G20: =G2 -> 30509.6 | H20: =H2 -> 25742.817 | I20: =I2 -> 509.6 | J20: =J2 -> 36384.257 | K20: =K2 -> 20767.896 | L20: =L2 -> 9937.2194 | ... KG20: =KG2 -> 0
C21: Cumulative | D21: =BN21 -> 2684708.3 | E21: =E20 -> 0 | F21: =E21+F20 -> 509.6 | G21: =F21+G20 -> 31019.2 | H21: =G21+H20 -> 56762.017 | I21: =H21+I20 -> 57271.617 | J21: =I21+J20 -> 93655.874 | K21: =J21+K20 -> 114423.77 | L21: =K21+L20 -> 124360.99 | M21: =L21+M20 -> 129483.15 | ... KG21: =KF21+KG20 -> 14860182
B22: COST | C22: Partial | D22: =BN22 -> 978 | E22: =E10 -> 0 | F22: =F10 -> 34620 | G22: =G10 -> 1801 | H22: =H10 -> 10517 | I22: =I10 -> 27584 | J22: =J10 -> 19328 | K22: =K10 -> 13171 | L22: =L10 -> 6523 | ... KG22: =KG10 -> 0
C23: Cumulative | D23: =BN23 -> 2652903.9 | E23: =E22 -> 0 | F23: =E23+F22 -> 34620 | G23: =F23+G22 -> 36421 | H23: =G23+H22 -> 46938 | I23: =H23+I22 -> 74522 | J23: =I23+J22 -> 93850 | K23: =J23+K22 -> 107021 | L23: =K23+L22 -> 113544 | M23: =L23+M22 -> 118915 | ... KG23: =KF23+KG22 -> 2655427.5
B24: BALANCE | C24: Partial | D24: =BN24 -> 37223.27 | E24: =E20-E22 -> 0 | F24: =F20-F22 -> -34110.4 | G24: =G20-G22 -> 28708.6 | H24: =H20-H22 -> 15225.817 | I24: =I20-I22 -> -27074.4 | J24: =J20-J22 -> 17056.257 | K24: =K20-K22 -> 7596.8964 | L24: =L20-L22 -> 3414.2194 | ... KG24: =KG20-KG22 -> 0
C25: Cumulative | D25: =BN25 -> 31804.444 | E25: =E24 -> 0 | F25: =E25+F24 -> -34110.4 | G25: =F25+G24 -> -5401.8 | H25: =G25+H24 -> 9824.0168 | I25: =H25+I24 -> -17250.383 | J25: =I25+J24 -> -194.12573 | K25: =J25+K24 -> 7402.7706 | L25: =K25+L24 -> 10816.99 | M25: =L25+M24 -> 10568.149 | ... KG25: =KF25+KG24 -> 12204755
B26: DEVIATION | D26: =BN26 -> 0.011846518 | E26: =E25/E21 -> #DIV/0! | F26: =F25/F21 -> -66.935636 | G26: =G25/G21 -> -0.17414376 | H26: =H25/H21 -> 0.17307378 | I26: =I25/I21 -> -0.30120301 | J26: =J25/J21 -> -0.0020727555 | K26: =K25/K21 -> 0.064696091 | L26: =L25/L21 -> 0.086980572 | ... KG26: =KG25/KG21 -> 0.82130586
B29: ROUTINE MAINTENANCE | D29: MAY 2026 | E29: =E19 -> 44287 | F29: =F19 -> 44317 | G29: =G19 -> 44348 | H29: =H19 -> 44378 | I29: =I19 -> 44409 | J29: =J19 -> 44440 | K29: =K19 -> 44470 | L29: =L19 -> 44501 | ... KG29: =KG19 -> 53053
B30: BUDGET | C30: Partial | D30: =BN30 -> 10000 | E30: =E3 -> 0 | F30: =F3 -> 8500 | G30: =G3 -> 8500 | H30: =H3 -> 8500 | I30: =I3 -> 8500 | J30: =J3 -> 10751.164 | K30: =K3 -> 8500 | L30: =L3 -> 8500 | ... KG30: =KG3 -> 10000
C31: Cumulative | D31: =BN31 -> 586587.55 | E31: =E30 -> 0 | F31: =E31+F30 -> 8500 | G31: =F31+G30 -> 17000 | H31: =G31+H30 -> 25500 | I31: =H31+I30 -> 34000 | J31: =I31+J30 -> 44751.164 | K31: =J31+K30 -> 53251.164 | L31: =K31+L30 -> 61751.164 | M31: =L31+M30 -> 70251.164 | ... KG31: =KF31+KG30 -> 3022769.5
B32: COST | C32: Partial | D32: =BN32 -> 10000 | E32: =E11 -> 0 | F32: =F11 -> 1498 | G32: =G11 -> 261 | H32: =H11 -> 105 | I32: =I11 -> 69 | J32: =J11 -> 492 | K32: =K11 -> 45901 | L32: =L11 -> 25500 | ... KG32: =KG11 -> 0
C33: Cumulative | D33: =BN33 -> 556929 | E33: =E32 -> 0 | F33: =E33+F32 -> 1498 | G33: =F33+G32 -> 1759 | H33: =G33+H32 -> 1864 | I33: =H33+I32 -> 1933 | J33: =I33+J32 -> 2425 | K33: =J33+K32 -> 48326 | L33: =K33+L32 -> 73826 | M33: =L33+M32 -> 90819 | ... KG33: =KF33+KG32 -> 576929
B34: BALANCE | C34: Partial | D34: =BN34 -> 0 | E34: =E30-E32 -> 0 | F34: =F30-F32 -> 7002 | G34: =G30-G32 -> 8239 | H34: =H30-H32 -> 8395 | I34: =I30-I32 -> 8431 | J34: =J30-J32 -> 10259.164 | K34: =K30-K32 -> -37401 | L34: =L30-L32 -> -17000 | ... KG34: =KG30-KG32 -> 10000
C35: Cumulative | D35: =BN35 -> 29658.545 | E35: =E34 -> 0 | F35: =E35+F34 -> 7002 | G35: =F35+G34 -> 15241 | H35: =G35+H34 -> 23636 | I35: =H35+I34 -> 32067 | J35: =I35+J34 -> 42326.164 | K35: =J35+K34 -> 4925.1639 | L35: =K35+L34 -> -12074.836 | M35: =L35+M34 -> -20567.836 | ... KG35: =KF35+KG34 -> 2445840.5
B36: DEVIATION | D36: =BN36 -> 0.050561158 | E36: =E35/E31 -> #DIV/0! | F36: =F35/F31 -> 0.82376471 | G36: =G35/G31 -> 0.89652941 | H36: =H35/H31 -> 0.92690196 | I36: =I35/I31 -> 0.94314706 | J36: =J35/J31 -> 0.94581147 | K36: =K35/K31 -> 0.092489319 | L36: =L35/L31 -> -0.19554022 | ... KG36: =KG35/KG31 -> 0.80913894
B39: MAJOR MAINTENANCE | D39: MAY 2026 | E39: =E29 -> 44287 | F39: =F29 -> 44317 | G39: =G29 -> 44348 | H39: =H29 -> 44378 | I39: =I29 -> 44409 | J39: =J29 -> 44440 | K39: =K29 -> 44470 | L39: =L29 -> 44501 | ... KG39: =KG29 -> 53053
B40: BUDGET | C40: Partial | D40: =BN40 -> 0 | E40: =E4 -> 0 | F40: =F4 -> 0 | G40: =G4 -> 0 | H40: =H4 -> 0 | I40: =I4 -> 0 | J40: =J4 -> 0 | K40: =K4 -> 0 | L40: =L4 -> 0 | ... KG40: =KG4 -> 10000
C41: Cumulative | D41: =BN41 -> 1006420.4 | E41: =E40 -> 0 | F41: =E41+F40 -> 0 | G41: =F41+G40 -> 0 | H41: =G41+H40 -> 0 | I41: =H41+I40 -> 0 | J41: =I41+J40 -> 0 | K41: =J41+K40 -> 0 | L41: =K41+L40 -> 0 | M41: =L41+M40 -> 0 | ... KG41: =KF41+KG40 -> 3612929.9
B42: COST | C42: Partial | D42: =BN42 -> 106.90117 | E42: =E12 -> 0 | F42: =F12 -> 0 | G42: =G12 -> 0 | H42: =H12 -> 0 | I42: =I12 -> 0 | J42: =J12 -> 1106 | K42: =K12 -> 1156 | L42: =L12 -> 0 | ... KG42: =KG12 -> 0
C43: Cumulative | D43: =BN43 -> 1027400.1 | E43: =E42 -> 0 | F43: =E43+F42 -> 0 | G43: =F43+G42 -> 0 | H43: =G43+H42 -> 0 | I43: =H43+I42 -> 0 | J43: =I43+J42 -> 1106 | K43: =J43+K42 -> 2262 | L43: =K43+L42 -> 2262 | M43: =L43+M42 -> 2262 | ... KG43: =KF43+KG42 -> 1043357.8
B44: BALANCE | C44: Partial | D44: =BN44 -> -106.90117 | E44: =E40-E42 -> 0 | F44: =F40-F42 -> 0 | G44: =G40-G42 -> 0 | H44: =H40-H42 -> 0 | I44: =I40-I42 -> 0 | J44: =J40-J42 -> -1106 | K44: =K40-K42 -> -1156 | L44: =L40-L42 -> 0 | ... KG44: =KG40-KG42 -> 10000
C45: Cumulative | D45: =BN45 -> -20979.634 | E45: =E44 -> 0 | F45: =E45+F44 -> 0 | G45: =F45+G44 -> 0 | H45: =G45+H44 -> 0 | I45: =H45+I44 -> 0 | J45: =I45+J44 -> -1106 | K45: =J45+K44 -> -2262 | L45: =K45+L44 -> -2262 | M45: =L45+M44 -> -2262 | ... KG45: =KF45+KG44 -> 2569572.2
B46: DEVIATION | D46: =BN46 -> -0.020845795 | E46: =E45/E41 -> #DIV/0! | F46: =F45/F41 -> #DIV/0! | G46: =G45/G41 -> #DIV/0! | H46: =H45/H41 -> #DIV/0! | I46: =I45/I41 -> #DIV/0! | J46: =J45/J41 -> #DIV/0! | K46: =K45/K41 -> #DIV/0! | L46: =L45/L41 -> #DIV/0! | ... KG46: =KG45/KG41 -> 0.71121561
B49: OPERATIONS | D49: MAY 2026 | E49: =E39 -> 44287 | F49: =F39 -> 44317 | G49: =G39 -> 44348 | H49: =H39 -> 44378 | I49: =I39 -> 44409 | J49: =J39 -> 44440 | K49: =K39 -> 44470 | L49: =L39 -> 44501 | ... KG49: =KG39 -> 53053
B50: BUDGET | C50: Partial | D50: =BN50 -> 27753.2 | E50: =E5 -> 49440.14 | F50: =F5 -> 20195.524 | G50: =G5 -> 21139.909 | H50: =H5 -> 20794.459 | I50: =I5 -> 28066.484 | J50: =J5 -> 24242.233 | K50: =K5 -> 27256.977 | L50: =L5 -> 22474.925 | ... KG50: =KG5 -> 24152.58
C51: Cumulative | D51: =BN51 -> 1802866.7 | E51: =E50 -> 49440.14 | F51: =E51+F50 -> 69635.663 | G51: =F51+G50 -> 90775.572 | H51: =G51+H50 -> 111570.03 | I51: =H51+I50 -> 139636.52 | J51: =I51+J50 -> 163878.75 | K51: =J51+K50 -> 191135.72 | L51: =K51+L50 -> 213610.65 | M51: =L51+M50 -> 241379.35 | ... KG51: =KF51+KG50 -> 7230601.4
B52: COST | C52: Partial | D52: =BN52 -> 24200.003 | E52: =E13 -> 31312 | F52: =F13 -> 17724 | G52: =G13 -> 16577 | H52: =H13 -> 17453 | I52: =I13 -> 21441 | J52: =J13 -> 32810 | K52: =K13 -> 21600 | L52: =L13 -> 20279 | ... KG52: =KG13 -> 0
C53: Cumulative | D53: =BN53 -> 1759092.5 | E53: =E52 -> 31312 | F53: =E53+F52 -> 49036 | G53: =F53+G52 -> 65613 | H53: =G53+H52 -> 83066 | I53: =H53+I52 -> 104507 | J53: =I53+J52 -> 137317 | K53: =J53+K52 -> 158917 | L53: =K53+L52 -> 179196 | M53: =L53+M52 -> 199869 | ... KG53: =KF53+KG52 -> 1808099.6
B54: BALANCE | C54: Partial | D54: =BN54 -> 3553.1975 | E54: =E50-E52 -> 18128.14 | F54: =F50-F52 -> 2471.5239 | G54: =G50-G52 -> 4562.9089 | H54: =H50-H52 -> 3341.4588 | I54: =I50-I52 -> 6625.4839 | J54: =J50-J52 -> -8567.7671 | K54: =K50-K52 -> 5656.9765 | L54: =L50-L52 -> 2195.9246 | ... KG54: =KG50-KG52 -> 24152.58
C55: Cumulative | D55: =BN55 -> 43774.203 | E55: =E54 -> 18128.14 | F55: =E55+F54 -> 20599.663 | G55: =F55+G54 -> 25162.572 | H55: =G55+H54 -> 28504.031 | I55: =H55+I54 -> 35129.515 | J55: =I55+J54 -> 26561.748 | K55: =J55+K54 -> 32218.724 | L55: =K55+L54 -> 34414.649 | M55: =L55+M54 -> 41510.348 | ... KG55: =KF55+KG54 -> 5422501.8
B56: DEVIATION | D56: =BN56 -> 0.024280332 | E56: =E55/E51 -> 0.36666845 | F56: =F55/F51 -> 0.2958206 | G56: =G55/G51 -> 0.27719541 | H56: =H55/H51 -> 0.25548107 | I56: =I55/I51 -> 0.25157829 | J56: =J55/J51 -> 0.16208171 | K56: =K55/K51 -> 0.16856464 | L56: =L55/L51 -> 0.16110924 | ... KG56: =KG55/KG51 -> 0.74993787
B59: SPV | D59: MAY 2026 | E59: =E49 -> 44287 | F59: =F49 -> 44317 | G59: =G49 -> 44348 | H59: =H49 -> 44378 | I59: =I49 -> 44409 | J59: =J49 -> 44440 | K59: =K49 -> 44470 | L59: =L49 -> 44501 | ... KG59: =KG49 -> 53053
B60: BUDGET | C60: Partial | D60: =BN60 -> 8435.4474 | E60: =E6 -> 4435.7627 | F60: =F6 -> 6728.0927 | G60: =G6 -> 6889.7627 | H60: =H6 -> 6275.0827 | I60: =I6 -> 27240.753 | J60: =J6 -> 10647.233 | K60: =K6 -> 10980.253 | L60: =L6 -> 11785.593 | ... KG60: =KG6 -> 0
C61: Cumulative | D61: =BN61 -> 847561.38 | E61: =E60 -> 4435.7627 | F61: =E61+F60 -> 11163.855 | G61: =F61+G60 -> 18053.618 | H61: =G61+H60 -> 24328.701 | I61: =H61+I60 -> 51569.453 | J61: =I61+J60 -> 62216.686 | K61: =J61+K60 -> 73196.939 | L61: =K61+L60 -> 84982.531 | M61: =L61+M60 -> 95913.924 | ... KG61: =KF61+KG60 -> 2004957.6
B62: COST | C62: Partial | D62: =BM62 -> 4870.14 | E62: =E14 -> 760 | F62: =F14 -> 5027 | G62: =G14 -> 4700 | H62: =H14 -> 3416 | I62: =I14 -> 15672 | J62: =J14 -> 3729 | K62: =K14 -> 11017 | L62: =L14 -> 7959 | ... KG62: =KG14 -> 0
C63: Cumulative | D63: =BM63 -> 608343.95 | E63: =E62 -> 760 | F63: =E63+F62 -> 5787 | G63: =F63+G62 -> 10487 | H63: =G63+H62 -> 13903 | I63: =H63+I62 -> 29575 | J63: =I63+J62 -> 33304 | K63: =J63+K62 -> 44321 | L63: =K63+L62 -> 52280 | M63: =L63+M62 -> 60576 | ... KG63: =KF63+KG62 -> 625741.07
B64: BALANCE | C64: Partial | D64: =BM64 -> 4005.3074 | E64: =E60-E62 -> 3675.7627 | F64: =F60-F62 -> 1701.0927 | G64: =G60-G62 -> 2189.7627 | H64: =H60-H62 -> 2859.0827 | I64: =I60-I62 -> 11568.753 | J64: =J60-J62 -> 6918.2327 | K64: =K60-K62 -> -36.747313 | L64: =L60-L62 -> 3826.5927 | ... KG64: =KG60-KG62 -> 0
C65: Cumulative | D65: =BM65 -> 230781.98 | E65: =E64 -> 3675.7627 | F65: =E65+F64 -> 5376.8554 | G65: =F65+G64 -> 7566.6181 | H65: =G65+H64 -> 10425.701 | I65: =H65+I64 -> 21994.453 | J65: =I65+J64 -> 28912.686 | K65: =J65+K64 -> 28875.939 | L65: =K65+L64 -> 32702.531 | M65: =L65+M64 -> 35337.924 | ... KG65: =KF65+KG64 -> 1379216.6
B66: DEVIATION | D66: =BM66 -> 0.27502663 | E66: =E65/E61 -> 0.82866532 | F66: =F65/F61 -> 0.48163069 | G66: =G65/G61 -> 0.41911921 | H66: =H65/H61 -> 0.42853504 | I66: =I65/I61 -> 0.42650158 | J66: =J65/J61 -> 0.46470952 | K66: =K65/K61 -> 0.39449654 | L66: =L65/L61 -> 0.38481475 | ... KG66: =KG65/KG61 -> 0.68790309
B69: MOP | D69: MAY 2026 | E69: =E59 -> 44287 | F69: =F59 -> 44317 | G69: =G59 -> 44348 | H69: =H59 -> 44378 | I69: =I59 -> 44409 | J69: =J59 -> 44440 | K69: =K59 -> 44470 | L69: =L59 -> 44501 | ... KG69: =KG59 -> 53053
B70: BUDGET | C70: Partial | D70: =BN70 -> 24540.772 | E70: =E7 -> 18947.456 | F70: =F7 -> 18947.456 | G70: =G7 -> 18947.456 | H70: =H7 -> 18947.456 | I70: =I7 -> 18947.456 | J70: =J7 -> 18947.456 | K70: =K7 -> 18947.456 | L70: =L7 -> 18947.456 | ... KG70: =KG7 -> 0
C71: Cumulative | D71: =BN71 -> 8308638.2 | E71: =E70 -> 18947.456 | F71: =E71+F70 -> 37894.912 | G71: =F71+G70 -> 56842.368 | H71: =G71+H70 -> 75789.824 | I71: =H71+I70 -> 94737.281 | J71: =I71+J70 -> 113684.74 | K71: =J71+K70 -> 132632.19 | L71: =K71+L70 -> 151579.65 | M71: =L71+M70 -> 170527.1 | ... KG71: =KF71+KG70 -> 20917687
B72: COST | C72: Partial | D72: =BN72 -> 18424.028 | E72: =E15 -> 0 | F72: =F15 -> 16284.864 | G72: =G15 -> 18467.727 | H72: =H15 -> 18410.304 | I72: =I15 -> 23018.454 | J72: =J15 -> 21517.786 | K72: =K15 -> 21810.214 | L72: =L15 -> 21749.376 | ... KG72: =KG15 -> 0
C73: Cumulative | D73: =BN73 -> 1108846.9 | E73: =E72 -> 0 | F73: =E73+F72 -> 16284.864 | G73: =F73+G72 -> 34752.591 | H73: =G73+H72 -> 53162.895 | I73: =H73+I72 -> 76181.349 | J73: =I73+J72 -> 97699.135 | K73: =J73+K72 -> 119509.35 | L73: =K73+L72 -> 141258.72 | M73: =L73+M72 -> 162756.57 | ... KG73: =KF73+KG72 -> 1144893
B74: BALANCE | C74: Partial | D74: =BN74 -> 6116.7437 | E74: =E70-E72 -> 18947.456 | F74: =F70-F72 -> 2662.5925 | G74: =G70-G72 -> 479.72882 | H74: =H70-H72 -> 537.15211 | I74: =I70-I72 -> -4070.9978 | J74: =J70-J72 -> -2570.3299 | K74: =K70-K72 -> -2862.7578 | L74: =L70-L72 -> -2801.92 | ... KG74: =KG70-KG72 -> 0
C75: Cumulative | D75: =BN75 -> 7199791.3 | E75: =E74 -> 18947.456 | F75: =E75+F74 -> 21610.049 | G75: =F75+G74 -> 22089.777 | H75: =G75+H74 -> 22626.929 | I75: =H75+I74 -> 18555.932 | J75: =I75+J74 -> 15985.602 | K75: =J75+K74 -> 13122.844 | L75: =K75+L74 -> 10320.924 | M75: =L75+M74 -> 7770.5355 | ... KG75: =KF75+KG74 -> 19772794
B76: DEVIATION | D76: =BN76 -> 0.86654288 | E76: =E75/E71 -> 1 | F76: =F75/F71 -> 0.57026253 | G76: =G75/G71 -> 0.38861466 | H76: =H75/H71 -> 0.29854838 | I76: =I75/I71 -> 0.19586726 | J76: =J75/J71 -> 0.14061344 | K76: =K75/K71 -> 0.09894162 | L76: =L75/L71 -> 0.068089114 | ... KG76: =KG75/KG71 -> 0.94526675
B79: INSURANCE & GUARANTEE | D79: MAY 2026 | E79: =E69 -> 44287 | F79: =F69 -> 44317 | G79: =G69 -> 44348 | H79: =H69 -> 44378 | I79: =I69 -> 44409 | J79: =J69 -> 44440 | K79: =K69 -> 44470 | L79: =L69 -> 44501 | ... KG79: =KG69 -> 53053
B80: BUDGET | C80: Partial | D80: =BN80 -> 230.40525 | E80: =E8 -> 3242.5833 | F80: =F8 -> 3242.5833 | G80: =G8 -> 3242.5833 | H80: =H8 -> 3242.5833 | I80: =I8 -> 3242.5833 | J80: =J8 -> 3242.5833 | K80: =K8 -> 3242.5833 | L80: =L8 -> 3242.5833 | ... KG80: =KG8 -> 0
C81: Cumulative | D81: =BN81 -> 205674 | E81: =E80 -> 3242.5833 | F81: =E81+F80 -> 6485.1667 | G81: =F81+G80 -> 9727.75 | H81: =G81+H80 -> 12970.333 | I81: =H81+I80 -> 16212.917 | J81: =I81+J80 -> 19455.5 | K81: =J81+K80 -> 22698.083 | L81: =K81+L80 -> 25940.667 | M81: =L81+M80 -> 29183.25 | ... KG81: =KF81+KG80 -> 637306.26
B82: COST | C82: Partial | D82: =BN82 -> 0 | E82: =E16 -> 948 | F82: =F16 -> 25300 | G82: =G16 -> 7582 | H82: =H16 -> 2 | I82: =I16 -> 0 | J82: =J16 -> 0 | K82: =K16 -> 0 | L82: =L16 -> 0 | ... KG82: =KG16 -> 0
C83: Cumulative | D83: =BN83 -> 202513 | E83: =E82 -> 948 | F83: =E83+F82 -> 26248 | G83: =F83+G82 -> 33830 | H83: =G83+H82 -> 33832 | I83: =H83+I82 -> 33832 | J83: =I83+J82 -> 33832 | K83: =J83+K82 -> 33832 | L83: =K83+L82 -> 33832 | M83: =L83+M82 -> 33832 | ... KG83: =KF83+KG82 -> 202513
B84: BALANCE | C84: Partial | D84: =BN84 -> 230.40525 | E84: =E80-E82 -> 2294.5833 | F84: =F80-F82 -> -22057.417 | G84: =G80-G82 -> -4339.4167 | H84: =H80-H82 -> 3240.5833 | I84: =I80-I82 -> 3242.5833 | J84: =J80-J82 -> 3242.5833 | K84: =K80-K82 -> 3242.5833 | L84: =L80-L82 -> 3242.5833 | ... KG84: =KG80-KG82 -> 0
C85: Cumulative | D85: =BN85 -> 3161.0043 | E85: =E84 -> 2294.5833 | F85: =E85+F84 -> -19762.833 | G85: =F85+G84 -> -24102.25 | H85: =G85+H84 -> -20861.667 | I85: =H85+I84 -> -17619.083 | J85: =I85+J84 -> -14376.5 | K85: =J85+K84 -> -11133.917 | L85: =K85+L84 -> -7891.3333 | M85: =L85+M84 -> -4648.75 | ... KG85: =KF85+KG84 -> 434793.26
B86: DEVIATION | D86: =BN86 -> 0.015369003 | E86: =E85/E81 -> 0.70764051 | F86: =F85/F81 -> -3.0473902 | G86: =G85/G81 -> -2.4776798 | H86: =H85/H81 -> -1.6084141 | I86: =I85/I81 -> -1.0867313 | J86: =J85/J81 -> -0.73894272 | K86: =K85/K81 -> -0.49052233 | L86: =L85/L81 -> -0.30420704 | ... KG86: =KG85/KG81 -> 0.68223598
B89: TAX | D89: MAY 2026 | E89: =E79 -> 44287 | F89: =F79 -> 44317 | G89: =G79 -> 44348 | H89: =H79 -> 44378 | I89: =I79 -> 44409 | J89: =J79 -> 44440 | K89: =K79 -> 44470 | L89: =L79 -> 44501 | ... KG89: =KG79 -> 53053
B90: BUDGET | C90: Partial | D90: =BN90 -> 0 | E90: =E9 -> 5981.9924 | F90: =F9 -> 0 | G90: =G9 -> 0 | H90: =H9 -> 0 | I90: =I9 -> 0 | J90: =J9 -> 0 | K90: =K9 -> 0 | L90: =L9 -> 0 | ... KG90: =KG9 -> 0
C91: Cumulative | D91: =BN91 -> 129962.5 | E91: =E90 -> 5981.9924 | F91: =E91+F90 -> 5981.9924 | G91: =F91+G90 -> 5981.9924 | H91: =G91+H90 -> 5981.9924 | I91: =H91+I90 -> 5981.9924 | J91: =I91+J90 -> 5981.9924 | K91: =J91+K90 -> 5981.9924 | L91: =K91+L90 -> 5981.9924 | M91: =L91+M90 -> 5981.9924 | ... KG91: =KF91+KG90 -> 177442.61
B92: COST | C92: Partial | D92: =BN92 -> 142 | E92: =E17 -> 0 | F92: =F17 -> 84 | G92: =G17 -> 1439 | H92: =H17 -> 589 | I92: =I17 -> 7463 | J92: =J17 -> 7620 | K92: =K17 -> 4802 | L92: =L17 -> 732 | ... KG92: =KG17 -> 0
C93: Cumulative | D93: =BN93 -> 52673.842 | E93: =E92 -> 0 | F93: =E93+F92 -> 84 | G93: =F93+G92 -> 1523 | H93: =G93+H92 -> 2112 | I93: =H93+I92 -> 9575 | J93: =I93+J92 -> 17195 | K93: =J93+K92 -> 21997 | L93: =K93+L92 -> 22729 | M93: =L93+M92 -> 23421 | ... KG93: =KF93+KG92 -> 54110.842
B94: BALANCE | C94: Partial | D94: =BN94 -> -142 | E94: =E90-E92 -> 5981.9924 | F94: =F90-F92 -> -84 | G94: =G90-G92 -> -1439 | H94: =H90-H92 -> -589 | I94: =I90-I92 -> -7463 | J94: =J90-J92 -> -7620 | K94: =K90-K92 -> -4802 | L94: =L90-L92 -> -732 | ... KG94: =KG90-KG92 -> 0
C95: Cumulative | D95: =BN95 -> 77288.661 | E95: =E94 -> 5981.9924 | F95: =E95+F94 -> 5897.9924 | G95: =F95+G94 -> 4458.9924 | H95: =G95+H94 -> 3869.9924 | I95: =H95+I94 -> -3593.0076 | J95: =I95+J94 -> -11213.008 | K95: =J95+K94 -> -16015.008 | L95: =K95+L94 -> -16747.008 | M95: =L95+M94 -> -17439.008 | ... KG95: =KF95+KG94 -> 123331.77
B96: DEVIATION | D96: =BN96 -> 0.59469969 | E96: =E95/E91 -> 1 | F96: =F95/F91 -> 0.98595786 | G96: =G95/G91 -> 0.74540255 | H96: =H95/H91 -> 0.64694037 | I96: =I95/I91 -> -0.60063727 | J96: =J95/J91 -> -1.8744604 | K96: =K95/K91 -> -2.6772029 | L96: =L95/L91 -> -2.7995702 | ... KG96: =KG95/KG91 -> 0.69505158

Sheet Balance by Area
B1: ITEM | C1: CATEGORY | D1: APR 2026 | E1: =Budget!F1 -> 44287 | F1: =Budget!G1 -> 44317 | G1: =Budget!H1 -> 44348 | H1: =Budget!I1 -> 44378 | I1: =Budget!J1 -> 44409 | J1: =Budget!K1 -> 44440 | K1: =Budget!L1 -> 44470 | L1: =Budget!M1 -> 44501 | ... KG1: =Budget!KH1 -> 53053
A2: BUDGET | B2: EPC | C2: 100 | D2: =SUM(E2:BM2) -> 2646507 | E2: =Balance!E2 -> 0 | F2: =Balance!F2 -> 509.6 | G2: =Balance!G2 -> 30509.6 | H2: =Balance!H2 -> 25742.817 | I2: =Balance!I2 -> 509.6 | J2: =Balance!J2 -> 36384.257 | K2: =Balance!K2 -> 20767.896 | L2: =Balance!L2 -> 9937.2194 | ... KG2: =Balance!KG2 -> 0
B3: ROUTINE MAINTENANCE | C3: 200 | D3: =SUM(E3:BM3) -> 576587.55 | E3: =Balance!E3 -> 0 | F3: =Balance!F3 -> 8500 | G3: =Balance!G3 -> 8500 | H3: =Balance!H3 -> 8500 | I3: =Balance!I3 -> 8500 | J3: =Balance!J3 -> 10751.164 | K3: =Balance!K3 -> 8500 | L3: =Balance!L3 -> 8500 | ... KG3: =Balance!KG3 -> 10000
B4: MAJOR MAINTENANCE | C4: 200 | D4: =SUM(E4:BM4) -> 1006420.4 | E4: =Balance!E4 -> 0 | F4: =Balance!F4 -> 0 | G4: =Balance!G4 -> 0 | H4: =Balance!H4 -> 0 | I4: =Balance!I4 -> 0 | J4: =Balance!J4 -> 0 | K4: =Balance!K4 -> 0 | L4: =Balance!L4 -> 0 | ... KG4: =Balance!KG4 -> 10000
B5: OPERATIONS | C5: 300 | D5: =SUM(E5:BM5) -> 1775113.5 | E5: =Balance!E5 -> 49440.14 | F5: =Balance!F5 -> 20195.524 | G5: =Balance!G5 -> 21139.909 | H5: =Balance!H5 -> 20794.459 | I5: =Balance!I5 -> 28066.484 | J5: =Balance!J5 -> 24242.233 | K5: =Balance!K5 -> 27256.977 | L5: =Balance!L5 -> 22474.925 | ... KG5: =Balance!KG5 -> 24152.58
B6: SPV | C6: 400 | D6: =SUM(E6:BM6) -> 839125.93 | E6: =Balance!E6 -> 4435.7627 | F6: =Balance!F6 -> 6728.0927 | G6: =Balance!G6 -> 6889.7627 | H6: =Balance!H6 -> 6275.0827 | I6: =Balance!I6 -> 27240.753 | J6: =Balance!J6 -> 10647.233 | K6: =Balance!K6 -> 10980.253 | L6: =Balance!L6 -> 11785.593 | ... KG6: =Balance!KG6 -> 0
B7: MOP | C7: 500 | D7: =SUM(E7:BM7) -> 8284097.5 | E7: =Balance!E7 -> 18947.456 | F7: =Balance!F7 -> 18947.456 | G7: =Balance!G7 -> 18947.456 | H7: =Balance!H7 -> 18947.456 | I7: =Balance!I7 -> 18947.456 | J7: =Balance!J7 -> 18947.456 | K7: =Balance!K7 -> 18947.456 | L7: =Balance!L7 -> 18947.456 | ... KG7: =Balance!KG7 -> 0
B8: INSURANCE & GUARANTEE | C8: 700 | D8: =SUM(E8:BM8) -> 205443.6 | E8: =Balance!E8 -> 3242.5833 | F8: =Balance!F8 -> 3242.5833 | G8: =Balance!G8 -> 3242.5833 | H8: =Balance!H8 -> 3242.5833 | I8: =Balance!I8 -> 3242.5833 | J8: =Balance!J8 -> 3242.5833 | K8: =Balance!K8 -> 3242.5833 | L8: =Balance!L8 -> 3242.5833 | ... KG8: =Balance!KG8 -> 0
B9: TAX | C9: 800 | D9: =SUM(E9:BM9) -> 129962.5 | E9: =Balance!E9 -> 5981.9924 | F9: =Balance!F9 -> 0 | G9: =Balance!G9 -> 0 | H9: =Balance!H9 -> 0 | I9: =Balance!I9 -> 0 | J9: =Balance!J9 -> 0 | K9: =Balance!K9 -> 0 | L9: =Balance!L9 -> 0 | ... KG9: =Balance!KG9 -> 0
A10: COST | B10: EPC | C10: 100 | D10: =SUM(E10:BM10) -> 2651925.9 | E10: =Balance!E10 -> 0 | F10: =Balance!F10 -> 34620 | G10: =Balance!G10 -> 1801 | H10: =Balance!H10 -> 10517 | I10: =Balance!I10 -> 27584 | J10: =Balance!J10 -> 19328 | K10: =Balance!K10 -> 13171 | L10: =Balance!L10 -> 6523 | ... KG10: =Balance!KG10 -> 0
B11: ROUTINE MAINTENANCE | C11: 200 | D11: =SUM(E11:BM11) -> 546929 | E11: =Balance!E11 -> 0 | F11: =Balance!F11 -> 1498 | G11: =Balance!G11 -> 261 | H11: =Balance!H11 -> 105 | I11: =Balance!I11 -> 69 | J11: =Balance!J11 -> 492 | K11: =Balance!K11 -> 45901 | L11: =Balance!L11 -> 25500 | ... KG11: =Balance!KG11 -> 0
B12: MAJOR MAINTENANCE | C12: 200 | D12: =SUM(E12:BM12) -> 1027293.2 | E12: =Balance!E12 -> 0 | F12: =Balance!F12 -> 0 | G12: =Balance!G12 -> 0 | H12: =Balance!H12 -> 0 | I12: =Balance!I12 -> 0 | J12: =Balance!J12 -> 1106 | K12: =Balance!K12 -> 1156 | L12: =Balance!L12 -> 0 | ... KG12: =Balance!KG12 -> 0
B13: OPERATIONS | C13: 300 | D13: =SUM(E13:BM13) -> 1734892.5 | E13: =Balance!E13 -> 31312 | F13: =Balance!F13 -> 17724 | G13: =Balance!G13 -> 16577 | H13: =Balance!H13 -> 17453 | I13: =Balance!I13 -> 21441 | J13: =Balance!J13 -> 32810 | K13: =Balance!K13 -> 21600 | L13: =Balance!L13 -> 20279 | ... KG13: =Balance!KG13 -> 0
B14: SPV | C14: 400 | D14: =SUM(E14:BM14) -> 608343.95 | E14: =Balance!E14 -> 760 | F14: =Balance!F14 -> 5027 | G14: =Balance!G14 -> 4700 | H14: =Balance!H14 -> 3416 | I14: =Balance!I14 -> 15672 | J14: =Balance!J14 -> 3729 | K14: =Balance!K14 -> 11017 | L14: =Balance!L14 -> 7959 | ... KG14: =Balance!KG14 -> 0
B15: MOP | C15: 500 | D15: =SUM(E15:BM15) -> 1090422.9 | E15: =Balance!E17 -> 0 | F15: =Balance!F17 -> 16284.864 | G15: =Balance!G17 -> 18467.727 | H15: =Balance!H17 -> 18410.304 | I15: =Balance!I17 -> 23018.454 | J15: =Balance!J17 -> 21517.786 | K15: =Balance!K17 -> 21810.214 | L15: =Balance!L17 -> 21749.376 | ... KG15: =Balance!KG17 -> 0
B16: INSURANCE & GUARANTEE | C16: 700 | D16: =SUM(E16:BM16) -> 202513 | E16: =Balance!E18 -> 948 | F16: =Balance!F18 -> 25300 | G16: =Balance!G18 -> 7582 | H16: =Balance!H18 -> 2 | I16: =Balance!I18 -> 0 | J16: =Balance!J18 -> 0 | K16: =Balance!K18 -> 0 | L16: =Balance!L18 -> 0 | ... KG16: =Balance!KG18 -> 0
B17: TAX | C17: 800 | D17: =SUM(E17:BM17) -> 52531.842 | E17: =Balance!E19 -> 0 | F17: =Balance!F19 -> 84 | G17: =Balance!G19 -> 1439 | H17: =Balance!H19 -> 589 | I17: =Balance!I19 -> 7463 | J17: =Balance!J19 -> 7620 | K17: =Balance!K19 -> 4802 | L17: =Balance!L19 -> 732 | ... KG17: =Balance!KG19 -> 0
B19: EPC | D19: JULY 2026 | E19: =E1 -> 44287 | F19: =F1 -> 44317 | G19: =G1 -> 44348 | H19: =H1 -> 44378 | I19: =I1 -> 44409 | J19: =J1 -> 44440 | K19: =K1 -> 44470 | L19: =L1 -> 44501 | ... KG19: =KG1 -> 53053
B20: BUDGET | C20: Partial | D20: =BP20 -> 43790.547 | E20: =E2 -> 0 | F20: =F2 -> 509.6 | G20: =G2 -> 30509.6 | H20: =H2 -> 25742.817 | I20: =I2 -> 509.6 | J20: =J2 -> 36384.257 | K20: =K2 -> 20767.896 | L20: =L2 -> 9937.2194 | ... KG20: =KG2 -> 0
C21: Cumulative | D21: =BP21 -> 2748292.4 | E21: =E20 -> 0 | F21: =E21+F20 -> 509.6 | G21: =F21+G20 -> 31019.2 | H21: =G21+H20 -> 56762.017 | I21: =H21+I20 -> 57271.617 | J21: =I21+J20 -> 93655.874 | K21: =J21+K20 -> 114423.77 | L21: =K21+L20 -> 124360.99 | M21: =L21+M20 -> 129483.15 | ... KG21: =KF21+KG20 -> 14860182
B22: COST | C22: Partial | D22: =BP22 -> 978 | E22: =E10 -> 0 | F22: =F10 -> 34620 | G22: =G10 -> 1801 | H22: =H10 -> 10517 | I22: =I10 -> 27584 | J22: =J10 -> 19328 | K22: =K10 -> 13171 | L22: =L10 -> 6523 | ... KG22: =KG10 -> 0
C23: Cumulative | D23: =BP23 -> 2655427.5 | E23: =E22 -> 0 | F23: =E23+F22 -> 34620 | G23: =F23+G22 -> 36421 | H23: =G23+H22 -> 46938 | I23: =H23+I22 -> 74522 | J23: =I23+J22 -> 93850 | K23: =J23+K22 -> 107021 | L23: =K23+L22 -> 113544 | M23: =L23+M22 -> 118915 | ... KG23: =KF23+KG22 -> 2655427.5
B24: BALANCE | C24: Partial | D24: =BO24 -> 18247.933 | E24: =E20-E22 -> 0 | F24: =F20-F22 -> -34110.4 | G24: =G20-G22 -> 28708.6 | H24: =H20-H22 -> 15225.817 | I24: =I20-I22 -> -27074.4 | J24: =J20-J22 -> 17056.257 | K24: =K20-K22 -> 7596.8964 | L24: =L20-L22 -> 3414.2194 | ... KG24: =KG20-KG22 -> 0
C25: Cumulative | D25: =BO25 -> 50052.378 | E25: =E24 -> 0 | F25: =E25+F24 -> -34110.4 | G25: =F25+G24 -> -5401.8 | H25: =G25+H24 -> 9824.0168 | I25: =H25+I24 -> -17250.383 | J25: =I25+J24 -> -194.12573 | K25: =J25+K24 -> 7402.7706 | L25: =K25+L24 -> 10816.99 | M25: =L25+M24 -> 10568.149 | ... KG25: =KF25+KG24 -> 12204755
B26: DEVIATION | D26: =BO26 -> 0.01850706 | E26: =E25/E21 -> #DIV/0! | F26: =F25/F21 -> -66.935636 | G26: =G25/G21 -> -0.17414376 | H26: =H25/H21 -> 0.17307378 | I26: =I25/I21 -> -0.30120301 | J26: =J25/J21 -> -0.0020727555 | K26: =K25/K21 -> 0.064696091 | L26: =L25/L21 -> 0.086980572 | ... KG26: =KG25/KG21 -> 0.82130586
B29: ROUTINE MAINTENANCE | D29: JULY 2026 | E29: =E19 -> 44287 | F29: =F19 -> 44317 | G29: =G19 -> 44348 | H29: =H19 -> 44378 | I29: =I19 -> 44409 | J29: =J19 -> 44440 | K29: =K19 -> 44470 | L29: =L19 -> 44501 | ... KG29: =KG19 -> 53053
B30: BUDGET | C30: Partial | D30: =BP30 -> 10000 | E30: =E3 -> 0 | F30: =F3 -> 8500 | G30: =G3 -> 8500 | H30: =H3 -> 8500 | I30: =I3 -> 8500 | J30: =J3 -> 10751.164 | K30: =K3 -> 8500 | L30: =L3 -> 8500 | ... KG30: =KG3 -> 10000
C31: Cumulative | D31: =BP31 -> 606587.55 | E31: =E30 -> 0 | F31: =E31+F30 -> 8500 | G31: =F31+G30 -> 17000 | H31: =G31+H30 -> 25500 | I31: =H31+I30 -> 34000 | J31: =I31+J30 -> 44751.164 | K31: =J31+K30 -> 53251.164 | L31: =K31+L30 -> 61751.164 | M31: =L31+M30 -> 70251.164 | ... KG31: =KF31+KG30 -> 3022769.5
B32: COST | C32: Partial | D32: =BP32 -> 10000 | E32: =E11 -> 0 | F32: =F11 -> 1498 | G32: =G11 -> 261 | H32: =H11 -> 105 | I32: =I11 -> 69 | J32: =J11 -> 492 | K32: =K11 -> 45901 | L32: =L11 -> 25500 | ... KG32: =KG11 -> 0
C33: Cumulative | D33: =BP33 -> 576929 | E33: =E32 -> 0 | F33: =E33+F32 -> 1498 | G33: =F33+G32 -> 1759 | H33: =G33+H32 -> 1864 | I33: =H33+I32 -> 1933 | J33: =I33+J32 -> 2425 | K33: =J33+K32 -> 48326 | L33: =K33+L32 -> 73826 | M33: =L33+M32 -> 90819 | ... KG33: =KF33+KG32 -> 576929
B34: BALANCE | C34: Partial | D34: =BP34 -> 0 | E34: =E30-E32 -> 0 | F34: =F30-F32 -> 7002 | G34: =G30-G32 -> 8239 | H34: =H30-H32 -> 8395 | I34: =I30-I32 -> 8431 | J34: =J30-J32 -> 10259.164 | K34: =K30-K32 -> -37401 | L34: =L30-L32 -> -17000 | ... KG34: =KG30-KG32 -> 10000
C35: Cumulative | D35: =BP35 -> 29658.545 | E35: =E34 -> 0 | F35: =E35+F34 -> 7002 | G35: =F35+G34 -> 15241 | H35: =G35+H34 -> 23636 | I35: =H35+I34 -> 32067 | J35: =I35+J34 -> 42326.164 | K35: =J35+K34 -> 4925.1639 | L35: =K35+L34 -> -12074.836 | M35: =L35+M34 -> -20567.836 | ... KG35: =KF35+KG34 -> 2445840.5
B36: DEVIATION | D36: =BP36 -> 0.048894089 | E36: =E35/E31 -> #DIV/0! | F36: =F35/F31 -> 0.82376471 | G36: =G35/G31 -> 0.89652941 | H36: =H35/H31 -> 0.92690196 | I36: =I35/I31 -> 0.94314706 | J36: =J35/J31 -> 0.94581147 | K36: =K35/K31 -> 0.092489319 | L36: =L35/L31 -> -0.19554022 | ... KG36: =KG35/KG31 -> 0.80913894
B39: MAJOR MAINTENANCE | D39: JULY 2026 | E39: =E29 -> 44287 | F39: =F29 -> 44317 | G39: =G29 -> 44348 | H39: =H29 -> 44378 | I39: =I29 -> 44409 | J39: =J29 -> 44440 | K39: =K29 -> 44470 | L39: =L29 -> 44501 | ... KG39: =KG29 -> 53053
B40: BUDGET | C40: Partial | D40: =BP40 -> 14106 | E40: =E4 -> 0 | F40: =F4 -> 0 | G40: =G4 -> 0 | H40: =H4 -> 0 | I40: =I4 -> 0 | J40: =J4 -> 0 | K40: =K4 -> 0 | L40: =L4 -> 0 | ... KG40: =KG4 -> 10000
C41: Cumulative | D41: =BP41 -> 1020526.4 | E41: =E40 -> 0 | F41: =E41+F40 -> 0 | G41: =F41+G40 -> 0 | H41: =G41+H40 -> 0 | I41: =H41+I40 -> 0 | J41: =I41+J40 -> 0 | K41: =J41+K40 -> 0 | L41: =K41+L40 -> 0 | M41: =L41+M40 -> 0 | ... KG41: =KF41+KG40 -> 3612929.9
B42: COST | C42: Partial | D42: =BP42 -> 14837.194 | E42: =E12 -> 0 | F42: =F12 -> 0 | G42: =G12 -> 0 | H42: =H12 -> 0 | I42: =I12 -> 0 | J42: =J12 -> 1106 | K42: =K12 -> 1156 | L42: =L12 -> 0 | ... KG42: =KG12 -> 0
C43: Cumulative | D43: =BP43 -> 1043357.8 | E43: =E42 -> 0 | F43: =E43+F42 -> 0 | G43: =F43+G42 -> 0 | H43: =G43+H42 -> 0 | I43: =H43+I42 -> 0 | J43: =I43+J42 -> 1106 | K43: =J43+K42 -> 2262 | L43: =K43+L42 -> 2262 | M43: =L43+M42 -> 2262 | ... KG43: =KF43+KG42 -> 1043357.8
B44: BALANCE | C44: Partial | D44: =BP44 -> -731.19431 | E44: =E40-E42 -> 0 | F44: =F40-F42 -> 0 | G44: =G40-G42 -> 0 | H44: =H40-H42 -> 0 | I44: =I40-I42 -> 0 | J44: =J40-J42 -> -1106 | K44: =K40-K42 -> -1156 | L44: =L40-L42 -> 0 | ... KG44: =KG40-KG42 -> 10000
C45: Cumulative | D45: =BP45 -> -22831.36 | E45: =E44 -> 0 | F45: =E45+F44 -> 0 | G45: =F45+G44 -> 0 | H45: =G45+H44 -> 0 | I45: =H45+I44 -> 0 | J45: =I45+J44 -> -1106 | K45: =J45+K44 -> -2262 | L45: =K45+L44 -> -2262 | M45: =L45+M44 -> -2262 | ... KG45: =KF45+KG44 -> 2569572.2
B46: DEVIATION | D46: =BP46 -> -0.02237214 | E46: =E45/E41 -> #DIV/0! | F46: =F45/F41 -> #DIV/0! | G46: =G45/G41 -> #DIV/0! | H46: =H45/H41 -> #DIV/0! | I46: =I45/I41 -> #DIV/0! | J46: =J45/J41 -> #DIV/0! | K46: =K45/K41 -> #DIV/0! | L46: =L45/L41 -> #DIV/0! | ... KG46: =KG45/KG41 -> 0.71121561
B49: OPERATIONS | D49: JULY 2026 | E49: =E39 -> 44287 | F49: =F39 -> 44317 | G49: =G39 -> 44348 | H49: =H39 -> 44378 | I49: =I39 -> 44409 | J49: =J39 -> 44440 | K49: =K39 -> 44470 | L49: =L39 -> 44501 | ... KG49: =KG39 -> 53053
B50: BUDGET | C50: Partial | D50: =BO50 -> 27753.2 | E50: =E5 -> 49440.14 | F50: =F5 -> 20195.524 | G50: =G5 -> 21139.909 | H50: =H5 -> 20794.459 | I50: =I5 -> 28066.484 | J50: =J5 -> 24242.233 | K50: =K5 -> 27256.977 | L50: =L5 -> 22474.925 | ... KG50: =KG5 -> 24152.58
C51: Cumulative | D51: =BO51 -> 1830619.9 | E51: =E50 -> 49440.14 | F51: =E51+F50 -> 69635.663 | G51: =F51+G50 -> 90775.572 | H51: =G51+H50 -> 111570.03 | I51: =H51+I50 -> 139636.52 | J51: =I51+J50 -> 163878.75 | K51: =J51+K50 -> 191135.72 | L51: =K51+L50 -> 213610.65 | M51: =L51+M50 -> 241379.35 | ... KG51: =KF51+KG50 -> 7230601.4
B52: COST | C52: Partial | D52: =BO52 -> 24085.533 | E52: =E13 -> 31312 | F52: =F13 -> 17724 | G52: =G13 -> 16577 | H52: =H13 -> 17453 | I52: =I13 -> 21441 | J52: =J13 -> 32810 | K52: =K13 -> 21600 | L52: =L13 -> 20279 | ... KG52: =KG13 -> 0
C53: Cumulative | D53: =BO53 -> 1783178 | E53: =E52 -> 31312 | F53: =E53+F52 -> 49036 | G53: =F53+G52 -> 65613 | H53: =G53+H52 -> 83066 | I53: =H53+I52 -> 104507 | J53: =I53+J52 -> 137317 | K53: =J53+K52 -> 158917 | L53: =K53+L52 -> 179196 | M53: =L53+M52 -> 199869 | ... KG53: =KF53+KG52 -> 1808099.6
B54: BALANCE | C54: Partial | D54: =BO54 -> 3667.6675 | E54: =E50-E52 -> 18128.14 | F54: =F50-F52 -> 2471.5239 | G54: =G50-G52 -> 4562.9089 | H54: =H50-H52 -> 3341.4588 | I54: =I50-I52 -> 6625.4839 | J54: =J50-J52 -> -8567.7671 | K54: =K50-K52 -> 5656.9765 | L54: =L50-L52 -> 2195.9246 | ... KG54: =KG50-KG52 -> 24152.58
C55: Cumulative | D55: =BO55 -> 47441.87 | E55: =E54 -> 18128.14 | F55: =E55+F54 -> 20599.663 | G55: =F55+G54 -> 25162.572 | H55: =G55+H54 -> 28504.031 | I55: =H55+I54 -> 35129.515 | J55: =I55+J54 -> 26561.748 | K55: =J55+K54 -> 32218.724 | L55: =K55+L54 -> 34414.649 | M55: =L55+M54 -> 41510.348 | ... KG55: =KF55+KG54 -> 5422501.8
B56: DEVIATION | D56: =BO56 -> 0.02591574 | E56: =E55/E51 -> 0.36666845 | F56: =F55/F51 -> 0.2958206 | G56: =G55/G51 -> 0.27719541 | H56: =H55/H51 -> 0.25548107 | I56: =I55/I51 -> 0.25157829 | J56: =J55/J51 -> 0.16208171 | K56: =K55/K51 -> 0.16856464 | L56: =L55/L51 -> 0.16110924 | ... KG56: =KG55/KG51 -> 0.74993787
B59: SPV | D59: JULY 2026 | E59: =E49 -> 44287 | F59: =F49 -> 44317 | G59: =G49 -> 44348 | H59: =H49 -> 44378 | I59: =I49 -> 44409 | J59: =J49 -> 44440 | K59: =K49 -> 44470 | L59: =L49 -> 44501 | ... KG59: =KG49 -> 53053
B60: BUDGET | C60: Partial | D60: =BO60 -> 8375.4474 | E60: =E6 -> 4435.7627 | F60: =F6 -> 6728.0927 | G60: =G6 -> 6889.7627 | H60: =H6 -> 6275.0827 | I60: =I6 -> 27240.753 | J60: =J6 -> 10647.233 | K60: =K6 -> 10980.253 | L60: =L6 -> 11785.593 | ... KG60: =KG6 -> 0
C61: Cumulative | D61: =BO61 -> 855936.82 | E61: =E60 -> 4435.7627 | F61: =E61+F60 -> 11163.855 | G61: =F61+G60 -> 18053.618 | H61: =G61+H60 -> 24328.701 | I61: =H61+I60 -> 51569.453 | J61: =I61+J60 -> 62216.686 | K61: =J61+K60 -> 73196.939 | L61: =K61+L60 -> 84982.531 | M61: =L61+M60 -> 95913.924 | ... KG61: =KF61+KG60 -> 2004957.6
B62: COST | C62: Partial | D62: =BO62 -> 7161.9218 | E62: =E14 -> 760 | F62: =F14 -> 5027 | G62: =G14 -> 4700 | H62: =H14 -> 3416 | I62: =I14 -> 15672 | J62: =J14 -> 3729 | K62: =K14 -> 11017 | L62: =L14 -> 7959 | ... KG62: =KG14 -> 0
C63: Cumulative | D63: =BO63 -> 620057.16 | E63: =E62 -> 760 | F63: =E63+F62 -> 5787 | G63: =F63+G62 -> 10487 | H63: =G63+H62 -> 13903 | I63: =H63+I62 -> 29575 | J63: =I63+J62 -> 33304 | K63: =J63+K62 -> 44321 | L63: =K63+L62 -> 52280 | M63: =L63+M62 -> 60576 | ... KG63: =KF63+KG62 -> 625741.07
B64: BALANCE | C64: Partial | D64: =BO64 -> 1213.5256 | E64: =E60-E62 -> 3675.7627 | F64: =F60-F62 -> 1701.0927 | G64: =G60-G62 -> 2189.7627 | H64: =H60-H62 -> 2859.0827 | I64: =I60-I62 -> 11568.753 | J64: =J60-J62 -> 6918.2327 | K64: =K60-K62 -> -36.747313 | L64: =L60-L62 -> 3826.5927 | ... KG64: =KG60-KG62 -> 0
C65: Cumulative | D65: =BO65 -> 235879.66 | E65: =E64 -> 3675.7627 | F65: =E65+F64 -> 5376.8554 | G65: =F65+G64 -> 7566.6181 | H65: =G65+H64 -> 10425.701 | I65: =H65+I64 -> 21994.453 | J65: =I65+J64 -> 28912.686 | K65: =J65+K64 -> 28875.939 | L65: =K65+L64 -> 32702.531 | M65: =L65+M64 -> 35337.924 | ... KG65: =KF65+KG64 -> 1379216.6
B66: DEVIATION | D66: =BO66 -> 0.27558069 | E66: =E65/E61 -> 0.82866532 | F66: =F65/F61 -> 0.48163069 | G66: =G65/G61 -> 0.41911921 | H66: =H65/H61 -> 0.42853504 | I66: =I65/I61 -> 0.42650158 | J66: =J65/J61 -> 0.46470952 | K66: =K65/K61 -> 0.39449654 | L66: =L65/L61 -> 0.38481475 | ... KG66: =KG65/KG61 -> 0.68790309
B69: MOP | D69: JULY 2026 | E69: =E59 -> 44287 | F69: =F59 -> 44317 | G69: =G59 -> 44348 | H69: =H59 -> 44378 | I69: =I59 -> 44409 | J69: =J59 -> 44440 | K69: =K59 -> 44470 | L69: =L59 -> 44501 | ... KG69: =KG59 -> 53053
B70: BUDGET | C70: Partial | D70: =BO70 -> 24540.772 | E70: =E7 -> 18947.456 | F70: =F7 -> 18947.456 | G70: =G7 -> 18947.456 | H70: =H7 -> 18947.456 | I70: =I7 -> 18947.456 | J70: =J7 -> 18947.456 | K70: =K7 -> 18947.456 | L70: =L7 -> 18947.456 | ... KG70: =KG7 -> 0
C71: Cumulative | D71: =BO71 -> 8333179 | E71: =E70 -> 18947.456 | F71: =E71+F70 -> 37894.912 | G71: =F71+G70 -> 56842.368 | H71: =G71+H70 -> 75789.824 | I71: =H71+I70 -> 94737.281 | J71: =I71+J70 -> 113684.74 | K71: =J71+K70 -> 132632.19 | L71: =K71+L70 -> 151579.65 | M71: =L71+M70 -> 170527.1 | ... KG71: =KF71+KG70 -> 20917687
B72: COST | C72: Partial | D72: =BO72 -> 18559.576 | E72: =E15 -> 0 | F72: =F15 -> 16284.864 | G72: =G15 -> 18467.727 | H72: =H15 -> 18410.304 | I72: =I15 -> 23018.454 | J72: =J15 -> 21517.786 | K72: =K15 -> 21810.214 | L72: =L15 -> 21749.376 | ... KG72: =KG15 -> 0
C73: Cumulative | D73: =BO73 -> 1127406.5 | E73: =E72 -> 0 | F73: =E73+F72 -> 16284.864 | G73: =F73+G72 -> 34752.591 | H73: =G73+H72 -> 53162.895 | I73: =H73+I72 -> 76181.349 | J73: =I73+J72 -> 97699.135 | K73: =J73+K72 -> 119509.35 | L73: =K73+L72 -> 141258.72 | M73: =L73+M72 -> 162756.57 | ... KG73: =KF73+KG72 -> 1144893
B74: BALANCE | C74: Partial | D74: =BO74 -> 5981.1955 | E74: =E70-E72 -> 18947.456 | F74: =F70-F72 -> 2662.5925 | G74: =G70-G72 -> 479.72882 | H74: =H70-H72 -> 537.15211 | I74: =I70-I72 -> -4070.9978 | J74: =J70-J72 -> -2570.3299 | K74: =K70-K72 -> -2862.7578 | L74: =L70-L72 -> -2801.92 | ... KG74: =KG70-KG72 -> 0
C75: Cumulative | D75: =BO75 -> 7205772.5 | E75: =E74 -> 18947.456 | F75: =E75+F74 -> 21610.049 | G75: =F75+G74 -> 22089.777 | H75: =G75+H74 -> 22626.929 | I75: =H75+I74 -> 18555.932 | J75: =I75+J74 -> 15985.602 | K75: =J75+K74 -> 13122.844 | L75: =K75+L74 -> 10320.924 | M75: =L75+M74 -> 7770.5355 | ... KG75: =KF75+KG74 -> 19772794
B76: DEVIATION | D76: =BO76 -> 0.86470871 | E76: =E75/E71 -> 1 | F76: =F75/F71 -> 0.57026253 | G76: =G75/G71 -> 0.38861466 | H76: =H75/H71 -> 0.29854838 | I76: =I75/I71 -> 0.19586726 | J76: =J75/J71 -> 0.14061344 | K76: =K75/K71 -> 0.09894162 | L76: =L75/L71 -> 0.068089114 | ... KG76: =KG75/KG71 -> 0.94526675
B79: INSURANCE & GUARANTEE | D79: JULY 2026 | E79: =E69 -> 44287 | F79: =F69 -> 44317 | G79: =G69 -> 44348 | H79: =H69 -> 44378 | I79: =I69 -> 44409 | J79: =J69 -> 44440 | K79: =K69 -> 44470 | L79: =L69 -> 44501 | ... KG79: =KG69 -> 53053
B80: BUDGET | C80: Partial | D80: =BO80 -> 230.40525 | E80: =E8 -> 3242.5833 | F80: =F8 -> 3242.5833 | G80: =G8 -> 3242.5833 | H80: =H8 -> 3242.5833 | I80: =I8 -> 3242.5833 | J80: =J8 -> 3242.5833 | K80: =K8 -> 3242.5833 | L80: =L8 -> 3242.5833 | ... KG80: =KG8 -> 0
C81: Cumulative | D81: =BO81 -> 205904.41 | E81: =E80 -> 3242.5833 | F81: =E81+F80 -> 6485.1667 | G81: =F81+G80 -> 9727.75 | H81: =G81+H80 -> 12970.333 | I81: =H81+I80 -> 16212.917 | J81: =I81+J80 -> 19455.5 | K81: =J81+K80 -> 22698.083 | L81: =K81+L80 -> 25940.667 | M81: =L81+M80 -> 29183.25 | ... KG81: =KF81+KG80 -> 637306.26
B82: COST | C82: Partial | D82: =BO82 -> 0 | E82: =E16 -> 948 | F82: =F16 -> 25300 | G82: =G16 -> 7582 | H82: =H16 -> 2 | I82: =I16 -> 0 | J82: =J16 -> 0 | K82: =K16 -> 0 | L82: =L16 -> 0 | ... KG82: =KG16 -> 0
C83: Cumulative | D83: =BO83 -> 202513 | E83: =E82 -> 948 | F83: =E83+F82 -> 26248 | G83: =F83+G82 -> 33830 | H83: =G83+H82 -> 33832 | I83: =H83+I82 -> 33832 | J83: =I83+J82 -> 33832 | K83: =J83+K82 -> 33832 | L83: =K83+L82 -> 33832 | M83: =L83+M82 -> 33832 | ... KG83: =KF83+KG82 -> 202513
B84: BALANCE | C84: Partial | D84: =BO84 -> 230.40525 | E84: =E80-E82 -> 2294.5833 | F84: =F80-F82 -> -22057.417 | G84: =G80-G82 -> -4339.4167 | H84: =H80-H82 -> 3240.5833 | I84: =I80-I82 -> 3242.5833 | J84: =J80-J82 -> 3242.5833 | K84: =K80-K82 -> 3242.5833 | L84: =L80-L82 -> 3242.5833 | ... KG84: =KG80-KG82 -> 0
C85: Cumulative | D85: =BO85 -> 3391.4096 | E85: =E84 -> 2294.5833 | F85: =E85+F84 -> -19762.833 | G85: =F85+G84 -> -24102.25 | H85: =G85+H84 -> -20861.667 | I85: =H85+I84 -> -17619.083 | J85: =I85+J84 -> -14376.5 | K85: =J85+K84 -> -11133.917 | L85: =K85+L84 -> -7891.3333 | M85: =L85+M84 -> -4648.75 | ... KG85: =KF85+KG84 -> 434793.26
B86: DEVIATION | D86: =BO86 -> 0.016470796 | E86: =E85/E81 -> 0.70764051 | F86: =F85/F81 -> -3.0473902 | G86: =G85/G81 -> -2.4776798 | H86: =H85/H81 -> -1.6084141 | I86: =I85/I81 -> -1.0867313 | J86: =J85/J81 -> -0.73894272 | K86: =K85/K81 -> -0.49052233 | L86: =L85/L81 -> -0.30420704 | ... KG86: =KG85/KG81 -> 0.68223598
B89: TAX | D89: JULY 2026 | E89: =E79 -> 44287 | F89: =F79 -> 44317 | G89: =G79 -> 44348 | H89: =H79 -> 44378 | I89: =I79 -> 44409 | J89: =J79 -> 44440 | K89: =K79 -> 44470 | L89: =L79 -> 44501 | ... KG89: =KG79 -> 53053
B90: BUDGET | C90: Partial | D90: =BO90 -> 0 | E90: =E9 -> 5981.9924 | F90: =F9 -> 0 | G90: =G9 -> 0 | H90: =H9 -> 0 | I90: =I9 -> 0 | J90: =J9 -> 0 | K90: =K9 -> 0 | L90: =L9 -> 0 | ... KG90: =KG9 -> 0
C91: Cumulative | D91: =BO91 -> 129962.5 | E91: =E90 -> 5981.9924 | F91: =E91+F90 -> 5981.9924 | G91: =F91+G90 -> 5981.9924 | H91: =G91+H90 -> 5981.9924 | I91: =H91+I90 -> 5981.9924 | J91: =I91+J90 -> 5981.9924 | K91: =J91+K90 -> 5981.9924 | L91: =K91+L90 -> 5981.9924 | M91: =L91+M90 -> 5981.9924 | ... KG91: =KF91+KG90 -> 177442.61
B92: COST | C92: Partial | D92: =BO92 -> 200 | E92: =E17 -> 0 | F92: =F17 -> 84 | G92: =G17 -> 1439 | H92: =H17 -> 589 | I92: =I17 -> 7463 | J92: =J17 -> 7620 | K92: =K17 -> 4802 | L92: =L17 -> 732 | ... KG92: =KG17 -> 0
C93: Cumulative | D93: =BO93 -> 52873.842 | E93: =E92 -> 0 | F93: =E93+F92 -> 84 | G93: =F93+G92 -> 1523 | H93: =G93+H92 -> 2112 | I93: =H93+I92 -> 9575 | J93: =I93+J92 -> 17195 | K93: =J93+K92 -> 21997 | L93: =K93+L92 -> 22729 | M93: =L93+M92 -> 23421 | ... KG93: =KF93+KG92 -> 54110.842
B94: BALANCE | C94: Partial | D94: =BO94 -> -200 | E94: =E90-E92 -> 5981.9924 | F94: =F90-F92 -> -84 | G94: =G90-G92 -> -1439 | H94: =H90-H92 -> -589 | I94: =I90-I92 -> -7463 | J94: =J90-J92 -> -7620 | K94: =K90-K92 -> -4802 | L94: =L90-L92 -> -732 | ... KG94: =KG90-KG92 -> 0
C95: Cumulative | D95: =BO95 -> 77088.661 | E95: =E94 -> 5981.9924 | F95: =E95+F94 -> 5897.9924 | G95: =F95+G94 -> 4458.9924 | H95: =G95+H94 -> 3869.9924 | I95: =H95+I94 -> -3593.0076 | J95: =I95+J94 -> -11213.008 | K95: =J95+K94 -> -16015.008 | L95: =K95+L94 -> -16747.008 | M95: =L95+M94 -> -17439.008 | ... KG95: =KF95+KG94 -> 123331.77
B96: DEVIATION | D96: =BO96 -> 0.59316079 | E96: =E95/E91 -> 1 | F96: =F95/F91 -> 0.98595786 | G96: =G95/G91 -> 0.74540255 | H96: =H95/H91 -> 0.64694037 | I96: =I95/I91 -> -0.60063727 | J96: =J95/J91 -> -1.8744604 | K96: =K95/K91 -> -2.6772029 | L96: =L95/L91 -> -2.7995702 | ... KG96: =KG95/KG91 -> 0.69505158

Sheet Budget
A1: ITEM_ID | B1: CAT-CN | C1: MAIN_ITEM-CN | D1: CAT-CC | E1: SUBCAT-CC | F1: 44287 | G1: 44317 | H1: 44348 | I1: 44378 | J1: 44409 | K1: 44440 | L1: 44470 | M1: 44501 | N1: 44531 | O1: 44562 | P1: 44593 | Q1: 44621 | R1: 44652 | S1: 44682 | T1: 44713 | U1: 44743 | V1: 44774 | W1: 44805 | X1: 44835 | Y1: 44866 | Z1: 44896 | AA1: 44927 | AB1: 44958 | AC1: 44986 | AD1: 45017 | AE1: 45047 | AF1: 45078 | AG1: 45108 | AH1: 45139 | AI1: 45170 | AJ1: 45200 | AK1: 45231 | AL1: 45261 | AM1: 45292 | AN1: 45323 | AO1: 45352 | AP1: 45383 | AQ1: 45413 | AR1: 45444 | AS1: 45474 | AT1: 45505 | AU1: 45536 | AV1: 45566 | AW1: 45597 | AX1: 45627 | AY1: 45658 | AZ1: 45689 | BA1: 45717 | BB1: 45748 | BC1: 45778 | BD1: 45809 | BE1: 45839 | BF1: 45870 | BG1: 45901 | BH1: 45931 | BI1: 45962 | BJ1: 45992 | BK1: 46023 | BL1: 46054 | BM1: 46082 | BN1: 46113 | BO1: 46143 | BP1: 46174 | BQ1: 46204 | BR1: 46235 | BS1: 46266 | BT1: 46296 | BU1: 46327 | BV1: 46357 | BW1: 46388 | BX1: 46419 | BY1: 46447 | BZ1: 46478 | CA1: 46508 | CB1: 46539 | CC1: 46569 | CD1: 46600 | CE1: 46631 | CF1: 46661 | CG1: 46692 | CH1: 46722 | CI1: 46753 | CJ1: 46784 | CK1: 46813 | CL1: 46844 | CM1: 46874 | CN1: 46905 | CO1: 46935 | CP1: 46966 | CQ1: 46997 | CR1: 47027 | CS1: 47058 | CT1: 47088 | CU1: 47119 | CV1: 47150 | CW1: 47178 | CX1: 47209 | CY1: 47239 | CZ1: 47270 | DA1: 47300 | DB1: 47331 | DC1: 47362 | DD1: 47392 | DE1: 47423 | DF1: 47453 | DG1: 47484 | DH1: 47515 | DI1: 47543 | DJ1: 47574 | DK1: 47604 | DL1: 47635 | DM1: 47665 | DN1: 47696 | DO1: 47727 | DP1: 47757 | DQ1: 47788 | DR1: 47818 | DS1: 47849 | DT1: 47880 | DU1: 47908 | DV1: 47939 | DW1: 47969 | DX1: 48000 | DY1: 48030 | DZ1: 48061 | EA1: 48092 | EB1: 48122 | EC1: 48153 | ED1: 48183 | EE1: 48214 | EF1: 48245 | EG1: 48274 | EH1: 48305 | EI1: 48335 | EJ1: 48366 | EK1: 48396 | EL1: 48427 | EM1: 48458 | EN1: 48488 | EO1: 48519 | EP1: 48549 | EQ1: 48580 | ER1: 48611 | ES1: 48639 | ET1: 48670 | EU1: 48700 | EV1: 48731 | EW1: 48761 | EX1: 48792 | EY1: 48823 | EZ1: 48853 | FA1: 48884 | FB1: 48914 | FC1: 48945 | FD1: 48976 | FE1: 49004 | FF1: 49035 | FG1: 49065 | FH1: 49096 | FI1: 49126 | FJ1: 49157 | FK1: 49188 | FL1: 49218 | FM1: 49249 | FN1: 49279 | FO1: 49310 | FP1: 49341 | FQ1: 49369 | FR1: 49400 | FS1: 49430 | FT1: 49461 | FU1: 49491 | FV1: 49522 | FW1: 49553 | FX1: 49583 | FY1: 49614 | FZ1: 49644 | GA1: 49675 | GB1: 49706 | GC1: 49735 | GD1: 49766 | GE1: 49796 | GF1: 49827 | GG1: 49857 | GH1: 49888 | GI1: 49919 | GJ1: 49949 | GK1: 49980 | GL1: 50010 | GM1: 50041 | GN1: 50072 | GO1: 50100 | GP1: 50131 | GQ1: 50161 | GR1: 50192 | GS1: 50222 | GT1: 50253 | GU1: 50284 | GV1: 50314 | GW1: 50345 | GX1: 50375 | GY1: 50406 | GZ1: 50437 | HA1: 50465 | HB1: 50496 | HC1: 50526 | HD1: 50557 | HE1: 50587 | HF1: 50618 | HG1: 50649 | HH1: 50679 | HI1: 50710 | HJ1: 50740 | HK1: 50771 | HL1: 50802 | HM1: 50830 | HN1: 50861 | HO1: 50891 | HP1: 50922 | HQ1: 50952 | HR1: 50983 | HS1: 51014 | HT1: 51044 | HU1: 51075 | HV1: 51105 | HW1: 51136 | HX1: 51167 | HY1: 51196 | HZ1: 51227 | IA1: 51257 | IB1: 51288 | IC1: 51318 | ID1: 51349 | IE1: 51380 | IF1: 51410 | IG1: 51441 | IH1: 51471 | II1: 51502 | IJ1: 51533 | IK1: 51561 | IL1: 51592 | IM1: 51622 | IN1: 51653 | IO1: 51683 | IP1: 51714 | IQ1: 51745 | IR1: 51775 | IS1: 51806 | IT1: 51836 | IU1: 51867 | IV1: 51898 | IW1: 51926 | IX1: 51957 | IY1: 51987 | IZ1: 52018 | JA1: 52048 | JB1: 52079 | JC1: 52110 | JD1: 52140 | JE1: 52171 | JF1: 52201 | JG1: 52232 | JH1: 52263 | JI1: 52291 | JJ1: 52322 | JK1: 52352 | JL1: 52383 | JM1: 52413 | JN1: 52444 | JO1: 52475 | JP1: 52505 | JQ1: 52536 | JR1: 52566 | JS1: 52597 | JT1: 52628 | JU1: 52657 | JV1: 52688 | JW1: 52718 | JX1: 52749 | JY1: 52779 | JZ1: 52810 | KA1: 52841 | KB1: 52871 | KC1: 52902 | KD1: 52932 | KE1: 52963 | KF1: 52994 | KG1: 53022 | KH1: 53053
A2: 3.1 | B2: SPV | C2: Delegate administration Environmental Assessment, citizen participation and territorial. (ILUFFI) | D2: 100 | E2: 108 | F2: 0 | G2: 509.6 | H2: 509.6 | I2: 532.81685 | J2: 509.6 | K2: 961.57445 | L2: 913.57895 | M2: 913.49071 | N2: 905.35 | O2: 1121.1844 | P2: 914.25056 | Q2: 905.35 | R2: 1013.0527 | S2: 958.17487 | T2: 936.18073 | U2: 906.12821 | V2: 895.82 | W2: 928.74208 | X2: 760.79696 | Y2: 1098.6929 | Z2: 837.08858 | AA2: 837.05346 | AB2: 838.59773 | AC2: 848.96324 | AD2: 850.65423 | AE2: 856.35935 | AF2: 858.6044 | AG2: 850.77064 | AH2: 848.09679 | AI2: 848.95367 | AJ2: 860.13843 | AK2: 719.4013 | AL2: 732.78932 | AM2: 736.04182 | AN2: 738.09819 | AO2: 725.59672 | AP2: 717.72216 | AQ2: 724.67879 | AR2: 721.72327 | AS2: 730.51855 | AT2: 747.97 | AU2: 720.37 | AV2: 718.96 | AW2: 722.28 | AX2: 389 | AY2: 711 | AZ2: 711 | BA2: 711 | BB2: 711 | BC2: 711 | BD2: 711 | BE2: 711 | BF2: 711 | BG2: 711 | BH2: 711 | BI2: 711 | BJ2: 711 | BK2: 711 | BL2: 711 | BM2: 711 | BN2: 711 | BO2: 711 | BP2: 711 | BQ2: 711 | BR2: 711 | BS2: 711 | BT2: 711 | BU2: 711 | BV2: 711 | BW2: 500 | BX2: 500 | BY2: 500 | BZ2: 500 | CA2: 500 | CB2: 500 | CC2: 500 | CD2: 500 | CE2: 500 | CF2: 500 | CG2: 500 | CH2: 500 | CI2: 500 | CJ2: 500 | CK2: 500 | CL2: 500 | CM2: 500 | CN2: 500 | CO2: 500 | CP2: 500 | CQ2: 500 | CR2: 500 | CS2: 500 | CT2: 500 | CU2: 500 | CV2: 500 | CW2: 500 | CX2: 500 | CY2: 500 | CZ2: 500 | DA2: 500 | DB2: 500 | DC2: 500 | DD2: 500 | DE2: 500 | DF2: 500 | DG2: 500 | DH2: 500 | DI2: 500 | DJ2: 500 | DK2: 500 | DL2: 500 | DM2: 500 | DN2: 500 | DO2: 500 | DP2: 500 | DQ2: 500 | DR2: 500 | DS2: 500 | DT2: 500 | DU2: 500 | DV2: 500 | DW2: 500 | DX2: 500 | DY2: 500 | DZ2: 500 | EA2: 500 | EB2: 500 | EC2: 500 | ED2: 500 | EE2: 500 | EF2: 500 | EG2: 500 | EH2: 500 | EI2: 500 | EJ2: 500 | EK2: 500 | EL2: 500 | EM2: 500 | EN2: 500 | EO2: 500 | EP2: 500 | EQ2: 500 | ER2: 500 | ES2: 500 | ET2: 500 | EU2: 500 | EV2: 500 | EW2: 500 | EX2: 500 | EY2: 500 | EZ2: 500 | FA2: 500 | FB2: 500 | FC2: 500 | FD2: 500 | FE2: 500 | FF2: 500 | FG2: 500 | FH2: 500 | FI2: 500 | FJ2: 500 | FK2: 500 | FL2: 500 | FM2: 500 | FN2: 500 | FO2: 500 | FP2: 500 | FQ2: 500 | FR2: 500 | FS2: 500 | FT2: 500 | FU2: 500 | FV2: 500 | FW2: 500 | FX2: 500 | FY2: 500 | FZ2: 500 | GA2: 500 | GB2: 500 | GC2: 500 | GD2: 500 | GE2: 500 | GF2: 500 | GG2: 500 | GH2: 500 | GI2: 500 | GJ2: 500 | GK2: 500 | GL2: 500 | GM2: 500 | GN2: 500 | GO2: 500 | GP2: 500 | GQ2: 500 | GR2: 500 | GS2: 500 | GT2: 500 | GU2: 500 | GV2: 500 | GW2: 500 | GX2: 500 | GY2: 500 | GZ2: 500 | HA2: 500 | HB2: 500 | HC2: 500 | HD2: 500 | HE2: 500 | HF2: 500 | HG2: 500 | HH2: 500 | HI2: 500 | HJ2: 500 | HK2: 500 | HL2: 500 | HM2: 500 | HN2: 500 | HO2: 500 | HP2: 500 | HQ2: 500 | HR2: 500 | HS2: 500 | HT2: 500 | HU2: 500 | HV2: 500 | HW2: 500 | HX2: 500 | HY2: 500 | HZ2: 500 | IA2: 500 | IB2: 500 | IC2: 500 | ID2: 500 | IE2: 500 | IF2: 500 | IG2: 500 | IH2: 500 | II2: 500 | IJ2: 500 | IK2: 500 | IL2: 500 | IM2: 500 | IN2: 500 | IO2: 500 | IP2: 500 | IQ2: 500 | IR2: 500 | IS2: 500 | IT2: 500 | IU2: 500 | IV2: 500 | IW2: 500 | IX2: 500 | IY2: 500 | IZ2: 500 | JA2: 500 | JB2: 500 | JC2: 500 | JD2: 500 | JE2: 500 | JF2: 500 | JG2: 500 | JH2: 500 | JI2: 500 | JJ2: 500 | JK2: 500 | JL2: 500 | JM2: 500 | JN2: 500 | JO2: 500 | JP2: 500 | JQ2: 500 | JR2: 500 | JS2: 500 | JT2: 500 | JU2: 500 | JV2: 500 | JW2: 500 | JX2: 500 | JY2: 500 | JZ2: 500 | KA2: 500 | KB2: 500 | KC2: 500 | KD2: 500 | KE2: 500 | KF2: 500 | KG2: 500 | KH2: 0
A3: 3.2 | B3: SPV | C3: Advice on crossings, parallelism, access and the like. (ROBLE) | D3: 100 | E3: 110 | F3: 0 | G3: 0 | H3: 0 | I3: 0 | J3: 0 | K3: 116.91968 | L3: 116.32401 | M3: 115.20536 | N3: 113.77378 | O3: 112.93332 | P3: 112.13402 | Q3: 110.97301 | R3: 110.31356 | S3: 108.77507 | T3: 107.10065 | U3: 105.78227 | V3: 104.73629 | W3: 103.43856 | X3: 102.16523 | Y3: 101.15505 | Z3: 100.54062 | AA3: 99.683917 | AB3: 99.185264 | AC3: 98.564673 | AD3: 98.382369 | AE3: 97.660201 | AF3: 97.13348 | AG3: 96.98117 | AH3: 97.089937 | AI3: 0 | AJ3: 0 | AK3: 265.29 | AL3: 0 | AM3: 0 | AN3: 176.86 | AO3: 0 | AP3: 0 | AQ3: 176.86 | AR3: 176.86 | AS3: 88.43 | AT3: 0 | AU3: 0 | AV3: 0 | AW3: 0 | AX3: 7.8894958 | AY3: 743.72727 | AZ3: 265.68508 | BA3: 265.68508 | BB3: 265.68508 | BC3: 88.3 | BD3: 88.3 | BE3: 88.3 | BF3: 88.3 | BG3: 88.3 | BH3: 88.3 | BI3: 88.3 | BJ3: 88.3 | BK3: 88.3 | BL3: 88.3 | BM3: 88.3 | BN3: 88.3 | BO3: 88.3 | BP3: 88.3 | BQ3: 88.3 | BR3: 88.3 | BS3: 88.3 | BT3: 88.3 | BU3: 88.3 | BV3: 88.3 | BW3: 88.3 | BX3: 88.3 | BY3: 88.3 | BZ3: 88.3 | CA3: 88.3 | CB3: 88.3 | CC3: 88.3 | CD3: 8088.3 | CE3: 88.3 | CF3: 88.3 | CG3: 88.3 | CH3: 2288.3 | CI3: 88.3 | CJ3: 88.3 | CK3: 88.3 | CL3: 88.3 | CM3: 88.3 | CN3: 88.3 | CO3: 88.3 | CP3: 88.3 | CQ3: 88.3 | CR3: 88.3 | CS3: 88.3 | CT3: 88.3 | CU3: 88.225 | CV3: 88.225 | CW3: 88.225 | CX3: 88.225 | CY3: 88.225 | CZ3: 88.225 | DA3: 88.225 | DB3: 88.225 | DC3: 88.225 | DD3: 88.225 | DE3: 88.225 | DF3: 88.225 | DG3: 88.225 | DH3: 88.225 | DI3: 88.225 | DJ3: 88.225 | DK3: 88.225 | DL3: 88.225 | DM3: 88.225 | DN3: 8088.225 | DO3: 88.225 | DP3: 88.225 | DQ3: 88.225 | DR3: 2288.225 | DS3: 88.225 | DT3: 88.225 | DU3: 88.225 | DV3: 88.225 | DW3: 88.225 | DX3: 88.225 | DY3: 88.225 | DZ3: 88.225 | EA3: 88.225 | EB3: 88.225 | EC3: 88.225 | ED3: 88.225 | EE3: 88.225 | EF3: 88.225 | EG3: 88.225 | EH3: 88.225 | EI3: 88.225 | EJ3: 88.225 | EK3: 88.225 | EL3: 88.225 | EM3: 88.225 | EN3: 88.225 | EO3: 88.225 | EP3: 88.225 | EQ3: 88.225 | ER3: 88.225 | ES3: 88.225 | ET3: 88.225 | EU3: 88.225 | EV3: 88.225 | EW3: 88.225 | EX3: 8088.225 | EY3: 88.225 | EZ3: 88.225 | FA3: 88.225 | FB3: 2288.225 | FC3: 88.225 | FD3: 88.225 | FE3: 88.225 | FF3: 88.225 | FG3: 88.225 | FH3: 88.225 | FI3: 88.225 | FJ3: 88.225 | FK3: 88.225 | FL3: 88.225 | FM3: 88.225 | FN3: 88.225 | FO3: 88.225 | FP3: 88.225 | FQ3: 88.225 | FR3: 88.225 | FS3: 88.225 | FT3: 88.225 | FU3: 88.225 | FV3: 88.225 | FW3: 88.225 | FX3: 88.225 | FY3: 88.225 | FZ3: 88.225 | GA3: 88.225 | GB3: 88.225 | GC3: 88.225 | GD3: 88.225 | GE3: 88.225 | GF3: 88.225 | GG3: 88.225 | GH3: 88.225 | GI3: 88.225 | GJ3: 88.225 | GK3: 88.225 | GL3: 88.225 | GM3: 88.225 | GN3: 88.225 | GO3: 88.225 | GP3: 88.225 | GQ3: 88.225 | GR3: 88.225 | GS3: 88.225 | GT3: 88.225 | GU3: 88.225 | GV3: 88.225 | GW3: 88.225 | GX3: 88.225 | GY3: 88.225 | GZ3: 88.225 | HA3: 88.225 | HB3: 88.225 | HC3: 88.225 | HD3: 88.225 | HE3: 88.225 | HF3: 88.225 | HG3: 88.225 | HH3: 88.225 | HI3: 88.225 | HJ3: 88.225 | HK3: 88.225 | HL3: 88.225 | HM3: 88.225 | HN3: 88.225 | HO3: 88.225 | HP3: 88.225 | HQ3: 88.225 | HR3: 88.225 | HS3: 88.225 | HT3: 88.225 | HU3: 88.225 | HV3: 88.225 | HW3: 88.225 | HX3: 88.225 | HY3: 88.225 | HZ3: 88.225 | IA3: 88.225 | IB3: 88.225 | IC3: 88.225 | ID3: 88.225 | IE3: 88.225 | IF3: 88.225 | IG3: 88.225 | IH3: 88.225 | II3: 88.225 | IJ3: 88.225 | IK3: 88.225 | IL3: 88.225 | IM3: 88.225 | IN3: 88.225 | IO3: 88.225 | IP3: 88.225 | IQ3: 88.225 | IR3: 88.225 | IS3: 88.225 | IT3: 88.225 | IU3: 88.225 | IV3: 88.225 | IW3: 88.225 | IX3: 88.225 | IY3: 88.225 | IZ3: 88.225 | JA3: 88.225 | JB3: 88.225 | JC3: 88.225 | JD3: 88.225 | JE3: 88.225 | JF3: 88.225 | JG3: 88.225 | JH3: 88.225 | JI3: 88.225 | JJ3: 88.225 | JK3: 88.225 | JL3: 88.225 | JM3: 88.225 | JN3: 88.225 | JO3: 88.225 | JP3: 88.225 | JQ3: 88.225 | JR3: 88.225 | JS3: 88.225 | JT3: 88.225 | JU3: 88.225 | JV3: 88.225 | JW3: 88.225 | JX3: 88.225 | JY3: 88.225 | JZ3: 88.225 | KA3: 88.225 | KB3: 88.225 | KC3: 88.225 | KD3: 88.225 | KE3: 88.225 | KF3: 88.225 | KG3: 88.225 | KH3: 0
A4: 3.3 | B4: SPV | C4: Pertinence and EIA Lircay Link, Ñuble Bridge and Nebuco Local Road. (AP ECOLOGY) | D4: 100 | E4: 108 | F4: 0 | G4: 0 | H4: 0 | I4: 0 | J4: 0 | K4: 0 | L4: 0 | M4: 0 | N4: 0 | O4: 0 | P4: 0 | Q4: 0 | R4: 0 | S4: 0 | T4: 0 | U4: 0 | V4: 0 | W4: 733.26359 | X4: 0 | Y4: 0 | Z4: 0 | AA4: 351.59106 | AB4: 0 | AC4: 0 | AD4: 0 | AE4: 0 | AF4: 0 | AG4: 0 | AH4: 0 | AI4: 0 | AJ4: 0 | AK4: 0 | AL4: 0 | AM4: 0 | AN4: 0 | AO4: 0 | AP4: 0 | AQ4: 0 | AR4: 0 | AS4: 0 | AT4: 969.60536 | AU4: 0 | AV4: 0 | AW4: 844.04208 | AX4: 0 | AY4: 0 | AZ4: 0 | BA4: 0 | BB4: 0 | BC4: 0 | BD4: 0 | BE4: 0 | BF4: 0 | BG4: 0 | BH4: 0 | BI4: 0 | BJ4: 0 | BK4: 0 | BL4: 0 | BM4: 0 | BN4: 0 | BO4: 0 | BP4: 0 | BQ4: 0 | BR4: 1217.4 | BS4: 0 | BT4: 0 | BU4: 0 | BV4: 0 | BW4: 0 | BX4: 0 | BY4: 0 | BZ4: 0 | CA4: 0 | CB4: 0 | CC4: 0 | CD4: 0 | CE4: 0 | CF4: 0 | CG4: 0 | CH4: 0 | CI4: 0 | CJ4: 0 | CK4: 0 | CL4: 0 | CM4: 0 | CN4: 0 | CO4: 0 | CP4: 0 | CQ4: 0 | CR4: 0 | CS4: 0 | CT4: 0 | CU4: 0 | CV4: 0 | CW4: 0 | CX4: 0 | CY4: 0 | CZ4: 0 | DA4: 0 | DB4: 0 | DC4: 0 | DD4: 0 | DE4: 0 | DF4: 0 | DG4: 0 | DH4: 0 | DI4: 0 | DJ4: 0 | DK4: 0 | DL4: 0 | DM4: 0 | DN4: 0 | DO4: 0 | DP4: 0 | DQ4: 0 | DR4: 0 | DS4: 0 | DT4: 0 | DU4: 0 | DV4: 0 | DW4: 0 | DX4: 0 | DY4: 0 | DZ4: 0 | EA4: 0 | EB4: 0 | EC4: 0 | ED4: 0 | EE4: 0 | EF4: 0 | EG4: 0 | EH4: 0 | EI4: 0 | EJ4: 0 | EK4: 0 | EL4: 0 | EM4: 0 | EN4: 0 | EO4: 0 | EP4: 0 | EQ4: 0 | ER4: 0 | ES4: 0 | ET4: 0 | EU4: 0 | EV4: 0 | EW4: 0 | EX4: 0 | EY4: 0 | EZ4: 0 | FA4: 0 | FB4: 0 | FC4: 0 | FD4: 0 | FE4: 0 | FF4: 0 | FG4: 0 | FH4: 0 | FI4: 0 | FJ4: 0 | FK4: 0 | FL4: 0 | FM4: 0 | FN4: 0 | FO4: 0 | FP4: 0 | FQ4: 0 | FR4: 0 | FS4: 0 | FT4: 0 | FU4: 0 | FV4: 0 | FW4: 0 | FX4: 0 | FY4: 0 | FZ4: 0 | GA4: 0 | GB4: 0 | GC4: 0 | GD4: 0 | GE4: 0 | GF4: 0 | GG4: 0 | GH4: 0 | GI4: 0 | GJ4: 0 | GK4: 0 | GL4: 0 | GM4: 0 | GN4: 0 | GO4: 0 | GP4: 0 | GQ4: 0 | GR4: 0 | GS4: 0 | GT4: 0 | GU4: 0 | GV4: 0 | GW4: 0 | GX4: 0 | GY4: 0 | GZ4: 0 | HA4: 0 | HB4: 0 | HC4: 0 | HD4: 0 | HE4: 0 | HF4: 0 | HG4: 0 | HH4: 0 | HI4: 0 | HJ4: 0 | HK4: 0 | HL4: 0 | HM4: 0 | HN4: 0 | HO4: 0 | HP4: 0 | HQ4: 0 | HR4: 0 | HS4: 0 | HT4: 0 | HU4: 0 | HV4: 0 | HW4: 0 | HX4: 0 | HY4: 0 | HZ4: 0 | IA4: 0 | IB4: 0 | IC4: 0 | ID4: 0 | IE4: 0 | IF4: 0 | IG4: 0 | IH4: 0 | II4: 0 | IJ4: 0 | IK4: 0 | IL4: 0 | IM4: 0 | IN4: 0 | IO4: 0 | IP4: 0 | IQ4: 0 | IR4: 0 | IS4: 0 | IT4: 0 | IU4: 0 | IV4: 0 | IW4: 0 | IX4: 0 | IY4: 0 | IZ4: 0 | JA4: 0 | JB4: 0 | JC4: 0 | JD4: 0 | JE4: 0 | JF4: 0 | JG4: 0 | JH4: 0 | JI4: 0 | JJ4: 0 | JK4: 0 | JL4: 0 | JM4: 0 | JN4: 0 | JO4: 0 | JP4: 0 | JQ4: 0 | JR4: 0 | JS4: 0 | JT4: 0 | JU4: 0 | JV4: 0 | JW4: 0 | JX4: 0 | JY4: 0 | JZ4: 0 | KA4: 0 | KB4: 0 | KC4: 0 | KD4: 0 | KE4: 0 | KF4: 0 | KG4: 0 | KH4: 0
A5: 3.4 | B5: SPV | C5: EIA Bypass Talca. (AP ECOLOGY) | D5: 100 | E5: 108 | F5: 0 | G5: 0 | H5: 0 | I5: 0 | J5: 0 | K5: 0 | L5: 0 | M5: 0 | N5: 0 | O5: 0 | P5: 0 | Q5: 0 | R5: 0 | S5: 0 | T5: 0 | U5: 0 | V5: 0 | W5: 0 | X5: 0 | Y5: 992.07541 | Z5: 0 | AA5: 0 | AB5: 651.88771 | AC5: 0 | AD5: 0 | AE5: 0 | AF5: 0 | AG5: 0 | AH5: 0 | AI5: 0 | AJ5: 0 | AK5: 0 | AL5: 0 | AM5: 0 | AN5: 0 | AO5: 0 | AP5: 0 | AQ5: 0 | AR5: 0 | AS5: 0 | AT5: 992.07541 | AU5: 857 | AV5: 992.07541 | AW5: 0 | AX5: 0 | AY5: 0 | AZ5: 0 | BA5: 0 | BB5: 0 | BC5: 0 | BD5: 0 | BE5: 0 | BF5: 0 | BG5: 0 | BH5: 0 | BI5: 0 | BJ5: 0 | BK5: 0 | BL5: 0 | BM5: 0 | BN5: 0 | BO5: 0 | BP5: 0 | BQ5: 1287.6631 | BR5: 0 | BS5: 0 | BT5: 0 | BU5: 0 | BV5: 0 | BW5: 0 | BX5: 0 | BY5: 0 | BZ5: 0 | CA5: 0 | CB5: 0 | CC5: 0 | CD5: 0 | CE5: 0 | CF5: 0 | CG5: 0 | CH5: 0 | CI5: 0 | CJ5: 0 | CK5: 0 | CL5: 0 | CM5: 0 | CN5: 0 | CO5: 0 | CP5: 0 | CQ5: 0 | CR5: 0 | CS5: 0 | CT5: 0 | CU5: 0 | CV5: 0 | CW5: 0 | CX5: 0 | CY5: 0 | CZ5: 0 | DA5: 0 | DB5: 0 | DC5: 0 | DD5: 0 | DE5: 0 | DF5: 0 | DG5: 0 | DH5: 0 | DI5: 0 | DJ5: 0 | DK5: 0 | DL5: 0 | DM5: 0 | DN5: 0 | DO5: 0 | DP5: 0 | DQ5: 0 | DR5: 0 | DS5: 0 | DT5: 0 | DU5: 0 | DV5: 0 | DW5: 0 | DX5: 0 | DY5: 0 | DZ5: 0 | EA5: 0 | EB5: 0 | EC5: 0 | ED5: 0 | EE5: 0 | EF5: 0 | EG5: 0 | EH5: 0 | EI5: 0 | EJ5: 0 | EK5: 0 | EL5: 0 | EM5: 0 | EN5: 0 | EO5: 0 | EP5: 0 | EQ5: 0 | ER5: 0 | ES5: 0 | ET5: 0 | EU5: 0 | EV5: 0 | EW5: 0 | EX5: 0 | EY5: 0 | EZ5: 0 | FA5: 0 | FB5: 0 | FC5: 0 | FD5: 0 | FE5: 0 | FF5: 0 | FG5: 0 | FH5: 0 | FI5: 0 | FJ5: 0 | FK5: 0 | FL5: 0 | FM5: 0 | FN5: 0 | FO5: 0 | FP5: 0 | FQ5: 0 | FR5: 0 | FS5: 0 | FT5: 0 | FU5: 0 | FV5: 0 | FW5: 0 | FX5: 0 | FY5: 0 | FZ5: 0 | GA5: 0 | GB5: 0 | GC5: 0 | GD5: 0 | GE5: 0 | GF5: 0 | GG5: 0 | GH5: 0 | GI5: 0 | GJ5: 0 | GK5: 0 | GL5: 0 | GM5: 0 | GN5: 0 | GO5: 0 | GP5: 0 | GQ5: 0 | GR5: 0 | GS5: 0 | GT5: 0 | GU5: 0 | GV5: 0 | GW5: 0 | GX5: 0 | GY5: 0 | GZ5: 0 | HA5: 0 | HB5: 0 | HC5: 0 | HD5: 0 | HE5: 0 | HF5: 0 | HG5: 0 | HH5: 0 | HI5: 0 | HJ5: 0 | HK5: 0 | HL5: 0 | HM5: 0 | HN5: 0 | HO5: 0 | HP5: 0 | HQ5: 0 | HR5: 0 | HS5: 0 | HT5: 0 | HU5: 0 | HV5: 0 | HW5: 0 | HX5: 0 | HY5: 0 | HZ5: 0 | IA5: 0 | IB5: 0 | IC5: 0 | ID5: 0 | IE5: 0 | IF5: 0 | IG5: 0 | IH5: 0 | II5: 0 | IJ5: 0 | IK5: 0 | IL5: 0 | IM5: 0 | IN5: 0 | IO5: 0 | IP5: 0 | IQ5: 0 | IR5: 0 | IS5: 0 | IT5: 0 | IU5: 0 | IV5: 0 | IW5: 0 | IX5: 0 | IY5: 0 | IZ5: 0 | JA5: 0 | JB5: 0 | JC5: 0 | JD5: 0 | JE5: 0 | JF5: 0 | JG5: 0 | JH5: 0 | JI5: 0 | JJ5: 0 | JK5: 0 | JL5: 0 | JM5: 0 | JN5: 0 | JO5: 0 | JP5: 0 | JQ5: 0 | JR5: 0 | JS5: 0 | JT5: 0 | JU5: 0 | JV5: 0 | JW5: 0 | JX5: 0 | JY5: 0 | JZ5: 0 | KA5: 0 | KB5: 0 | KC5: 0 | KD5: 0 | KE5: 0 | KF5: 0 | KG5: 0 | KH5: 0
A6: 3.5 | B6: SPV | C6: EIA New Bridges Subsectors C and D. (IDOM) | D6: 100 | E6: 108 | F6: 0 | G6: 0 | H6: 0 | I6: 0 | J6: 0 | K6: 0 | L6: 0 | M6: 0 | N6: 0 | O6: 0 | P6: 0 | Q6: 0 | R6: 0 | S6: 0 | T6: 0 | U6: 0 | V6: 0 | W6: 0 | X6: 0 | Y6: 0 | Z6: 0 | AA6: 0 | AB6: 0 | AC6: 0 | AD6: 0 | AE6: 0 | AF6: 0 | AG6: 4560.3717 | AH6: 0 | AI6: 0 | AJ6: 0 | AK6: 0 | AL6: 2602.7859 | AM6: 0 | AN6: 0 | AO6: 5438.5 | AP6: 0 | AQ6: 0 | AR6: 0 | AS6: 0 | AT6: 0 | AU6: 0 | AV6: 3047 | AW6: 320 | AX6: 320 | AY6: 0 | AZ6: 0 | BA6: 0 | BB6: 0 | BC6: 0 | BD6: 0 | BE6: 0 | BF6: 0 | BG6: 0 | BH6: 0 | BI6: 0 | BJ6: 0 | BK6: 0 | BL6: 0 | BM6: 0 | BN6: 3965.8987 | BO6: 0 | BP6: 0 | BQ6: 0 | BR6: 0 | BS6: 0 | BT6: 0 | BU6: 0 | BV6: 0 | BW6: 0 | BX6: 0 | BY6: 0 | BZ6: 0 | CA6: 0 | CB6: 0 | CC6: 0 | CD6: 0 | CE6: 0 | CF6: 0 | CG6: 0 | CH6: 0 | CI6: 0 | CJ6: 0 | CK6: 0 | CL6: 0 | CM6: 0 | CN6: 0 | CO6: 0 | CP6: 0 | CQ6: 0 | CR6: 0 | CS6: 0 | CT6: 0 | CU6: 0 | CV6: 0 | CW6: 0 | CX6: 0 | CY6: 0 | CZ6: 0 | DA6: 0 | DB6: 0 | DC6: 0 | DD6: 0 | DE6: 0 | DF6: 0 | DG6: 0 | DH6: 0 | DI6: 0 | DJ6: 0 | DK6: 0 | DL6: 0 | DM6: 0 | DN6: 0 | DO6: 0 | DP6: 0 | DQ6: 0 | DR6: 0 | DS6: 0 | DT6: 0 | DU6: 0 | DV6: 0 | DW6: 0 | DX6: 0 | DY6: 0 | DZ6: 0 | EA6: 0 | EB6: 0 | EC6: 0 | ED6: 0 | EE6: 0 | EF6: 0 | EG6: 0 | EH6: 0 | EI6: 0 | EJ6: 0 | EK6: 0 | EL6: 0 | EM6: 0 | EN6: 0 | EO6: 0 | EP6: 0 | EQ6: 0 | ER6: 0 | ES6: 0 | ET6: 0 | EU6: 0 | EV6: 0 | EW6: 0 | EX6: 0 | EY6: 0 | EZ6: 0 | FA6: 0 | FB6: 0 | FC6: 0 | FD6: 0 | FE6: 0 | FF6: 0 | FG6: 0 | FH6: 0 | FI6: 0 | FJ6: 0 | FK6: 0 | FL6: 0 | FM6: 0 | FN6: 0 | FO6: 0 | FP6: 0 | FQ6: 0 | FR6: 0 | FS6: 0 | FT6: 0 | FU6: 0 | FV6: 0 | FW6: 0 | FX6: 0 | FY6: 0 | FZ6: 0 | GA6: 0 | GB6: 0 | GC6: 0 | GD6: 0 | GE6: 0 | GF6: 0 | GG6: 0 | GH6: 0 | GI6: 0 | GJ6: 0 | GK6: 0 | GL6: 0 | GM6: 0 | GN6: 0 | GO6: 0 | GP6: 0 | GQ6: 0 | GR6: 0 | GS6: 0 | GT6: 0 | GU6: 0 | GV6: 0 | GW6: 0 | GX6: 0 | GY6: 0 | GZ6: 0 | HA6: 0 | HB6: 0 | HC6: 0 | HD6: 0 | HE6: 0 | HF6: 0 | HG6: 0 | HH6: 0 | HI6: 0 | HJ6: 0 | HK6: 0 | HL6: 0 | HM6: 0 | HN6: 0 | HO6: 0 | HP6: 0 | HQ6: 0 | HR6: 0 | HS6: 0 | HT6: 0 | HU6: 0 | HV6: 0 | HW6: 0 | HX6: 0 | HY6: 0 | HZ6: 0 | IA6: 0 | IB6: 0 | IC6: 0 | ID6: 0 | IE6: 0 | IF6: 0 | IG6: 0 | IH6: 0 | II6: 0 | IJ6: 0 | IK6: 0 | IL6: 0 | IM6: 0 | IN6: 0 | IO6: 0 | IP6: 0 | IQ6: 0 | IR6: 0 | IS6: 0 | IT6: 0 | IU6: 0 | IV6: 0 | IW6: 0 | IX6: 0 | IY6: 0 | IZ6: 0 | JA6: 0 | JB6: 0 | JC6: 0 | JD6: 0 | JE6: 0 | JF6: 0 | JG6: 0 | JH6: 0 | JI6: 0 | JJ6: 0 | JK6: 0 | JL6: 0 | JM6: 0 | JN6: 0 | JO6: 0 | JP6: 0 | JQ6: 0 | JR6: 0 | JS6: 0 | JT6: 0 | JU6: 0 | JV6: 0 | JW6: 0 | JX6: 0 | JY6: 0 | JZ6: 0 | KA6: 0 | KB6: 0 | KC6: 0 | KD6: 0 | KE6: 0 | KF6: 0 | KG6: 0 | KH6: 0
A7: 3.6 | B7: SPV | C7: Preliminary citizen participation EIA NewBridges Subsectors C and D. (ILUFFI) | D7: 100 | E7: 108 | F7: 0 | G7: 0 | H7: 0 | I7: 0 | J7: 0 | K7: 0 | L7: 0 | M7: 0 | N7: 0 | O7: 0 | P7: 0 | Q7: 0 | R7: 0 | S7: 0 | T7: 0 | U7: 0 | V7: 0 | W7: 0 | X7: 0 | Y7: 180.5 | Z7: 180.5 | AA7: 180.5 | AB7: 180.5 | AC7: 180.5 | AD7: 180.5 | AE7: 180.5 | AF7: 0 | AG7: 0 | AH7: 0 | AI7: 0 | AJ7: 0 | AK7: 0 | AL7: 0 | AM7: 0 | AN7: 0 | AO7: 0 | AP7: 117 | AQ7: 117 | AR7: 117 | AS7: 117 | AT7: 117 | AU7: 0 | AV7: 0 | AW7: 0 | AX7: 0 | AY7: 0 | AZ7: 0 | BA7: 0 | BB7: 0 | BC7: 0 | BD7: 0 | BE7: 0 | BF7: 0 | BG7: 0 | BH7: 0 | BI7: 0 | BJ7: 0 | BK7: 0 | BL7: 0 | BM7: 0 | BN7: 0 | BO7: 0 | BP7: 0 | BQ7: 0 | BR7: 0 | BS7: 0 | BT7: 0 | BU7: 0 | BV7: 0 | BW7: 0 | BX7: 0 | BY7: 0 | BZ7: 0 | CA7: 0 | CB7: 0 | CC7: 0 | CD7: 0 | CE7: 0 | CF7: 0 | CG7: 0 | CH7: 0 | CI7: 0 | CJ7: 0 | CK7: 0 | CL7: 0 | CM7: 0 | CN7: 0 | CO7: 0 | CP7: 0 | CQ7: 0 | CR7: 0 | CS7: 0 | CT7: 0 | CU7: 0 | CV7: 0 | CW7: 0 | CX7: 0 | CY7: 0 | CZ7: 0 | DA7: 0 | DB7: 0 | DC7: 0 | DD7: 0 | DE7: 0 | DF7: 0 | DG7: 0 | DH7: 0 | DI7: 0 | DJ7: 0 | DK7: 0 | DL7: 0 | DM7: 0 | DN7: 0 | DO7: 0 | DP7: 0 | DQ7: 0 | DR7: 0 | DS7: 0 | DT7: 0 | DU7: 0 | DV7: 0 | DW7: 0 | DX7: 0 | DY7: 0 | DZ7: 0 | EA7: 0 | EB7: 0 | EC7: 0 | ED7: 0 | EE7: 0 | EF7: 0 | EG7: 0 | EH7: 0 | EI7: 0 | EJ7: 0 | EK7: 0 | EL7: 0 | EM7: 0 | EN7: 0 | EO7: 0 | EP7: 0 | EQ7: 0 | ER7: 0 | ES7: 0 | ET7: 0 | EU7: 0 | EV7: 0 | EW7: 0 | EX7: 0 | EY7: 0 | EZ7: 0 | FA7: 0 | FB7: 0 | FC7: 0 | FD7: 0 | FE7: 0 | FF7: 0 | FG7: 0 | FH7: 0 | FI7: 0 | FJ7: 0 | FK7: 0 | FL7: 0 | FM7: 0 | FN7: 0 | FO7: 0 | FP7: 0 | FQ7: 0 | FR7: 0 | FS7: 0 | FT7: 0 | FU7: 0 | FV7: 0 | FW7: 0 | FX7: 0 | FY7: 0 | FZ7: 0 | GA7: 0 | GB7: 0 | GC7: 0 | GD7: 0 | GE7: 0 | GF7: 0 | GG7: 0 | GH7: 0 | GI7: 0 | GJ7: 0 | GK7: 0 | GL7: 0 | GM7: 0 | GN7: 0 | GO7: 0 | GP7: 0 | GQ7: 0 | GR7: 0 | GS7: 0 | GT7: 0 | GU7: 0 | GV7: 0 | GW7: 0 | GX7: 0 | GY7: 0 | GZ7: 0 | HA7: 0 | HB7: 0 | HC7: 0 | HD7: 0 | HE7: 0 | HF7: 0 | HG7: 0 | HH7: 0 | HI7: 0 | HJ7: 0 | HK7: 0 | HL7: 0 | HM7: 0 | HN7: 0 | HO7: 0 | HP7: 0 | HQ7: 0 | HR7: 0 | HS7: 0 | HT7: 0 | HU7: 0 | HV7: 0 | HW7: 0 | HX7: 0 | HY7: 0 | HZ7: 0 | IA7: 0 | IB7: 0 | IC7: 0 | ID7: 0 | IE7: 0 | IF7: 0 | IG7: 0 | IH7: 0 | II7: 0 | IJ7: 0 | IK7: 0 | IL7: 0 | IM7: 0 | IN7: 0 | IO7: 0 | IP7: 0 | IQ7: 0 | IR7: 0 | IS7: 0 | IT7: 0 | IU7: 0 | IV7: 0 | IW7: 0 | IX7: 0 | IY7: 0 | IZ7: 0 | JA7: 0 | JB7: 0 | JC7: 0 | JD7: 0 | JE7: 0 | JF7: 0 | JG7: 0 | JH7: 0 | JI7: 0 | JJ7: 0 | JK7: 0 | JL7: 0 | JM7: 0 | JN7: 0 | JO7: 0 | JP7: 0 | JQ7: 0 | JR7: 0 | JS7: 0 | JT7: 0 | JU7: 0 | JV7: 0 | JW7: 0 | JX7: 0 | JY7: 0 | JZ7: 0 | KA7: 0 | KB7: 0 | KC7: 0 | KD7: 0 | KE7: 0 | KF7: 0 | KG7: 0 | KH7: 0
A8: 3.7 | B8: SPV | C8: Acoustic Studio-SPV Cost. (ILUFFI, ALREDAY FINISHED) | D8: 100 | E8: 108 | F8: 0 | G8: 0 | H8: 0 | I8: 0 | J8: 0 | K8: 0 | L8: 0 | M8: 0 | N8: 0 | O8: 566.2 | P8: 0 | Q8: 0 | R8: 858.8 | S8: 0 | T8: 0 | U8: 0 | V8: 0 | W8: 171 | X8: 0 | Y8: 0 | Z8: 0 | AA8: 0 | AB8: 0 | AC8: 0 | AD8: 0 | AE8: 0 | AF8: 0 | AG8: 291.65 | AH8: 0 | AI8: 0 | AJ8: 0 | AK8: 0 | AL8: 0 | AM8: 0 | AN8: 0 | AO8: 0 | AP8: 0 | AQ8: 0 | AR8: 0 | AS8: 0 | AT8: 0 | AU8: 0 | AV8: 99.35 | AW8: 0 | AX8: 0 | AY8: 0 | AZ8: 0 | BA8: 0 | BB8: 0 | BC8: 0 | BD8: 0 | BE8: 0 | BF8: 0 | BG8: 0 | BH8: 0 | BI8: 0 | BJ8: 0 | BK8: 0 | BL8: 0 | BM8: 0 | BN8: 0 | BO8: 0 | BP8: 0 | BQ8: 0 | BR8: 0 | BS8: 0 | BT8: 0 | BU8: 0 | BV8: 0 | BW8: 0 | BX8: 0 | BY8: 0 | BZ8: 0 | CA8: 0 | CB8: 0 | CC8: 0 | CD8: 0 | CE8: 0 | CF8: 0 | CG8: 0 | CH8: 0 | CI8: 0 | CJ8: 0 | CK8: 0 | CL8: 0 | CM8: 0 | CN8: 0 | CO8: 0 | CP8: 0 | CQ8: 0 | CR8: 0 | CS8: 0 | CT8: 0 | CU8: 0 | CV8: 0 | CW8: 0 | CX8: 0 | CY8: 0 | CZ8: 0 | DA8: 0 | DB8: 0 | DC8: 0 | DD8: 0 | DE8: 0 | DF8: 0 | DG8: 0 | DH8: 0 | DI8: 0 | DJ8: 0 | DK8: 0 | DL8: 0 | DM8: 0 | DN8: 0 | DO8: 0 | DP8: 0 | DQ8: 0 | DR8: 0 | DS8: 0 | DT8: 0 | DU8: 0 | DV8: 0 | DW8: 0 | DX8: 0 | DY8: 0 | DZ8: 0 | EA8: 0 | EB8: 0 | EC8: 0 | ED8: 0 | EE8: 0 | EF8: 0 | EG8: 0 | EH8: 0 | EI8: 0 | EJ8: 0 | EK8: 0 | EL8: 0 | EM8: 0 | EN8: 0 | EO8: 0 | EP8: 0 | EQ8: 0 | ER8: 0 | ES8: 0 | ET8: 0 | EU8: 0 | EV8: 0 | EW8: 0 | EX8: 0 | EY8: 0 | EZ8: 0 | FA8: 0 | FB8: 0 | FC8: 0 | FD8: 0 | FE8: 0 | FF8: 0 | FG8: 0 | FH8: 0 | FI8: 0 | FJ8: 0 | FK8: 0 | FL8: 0 | FM8: 0 | FN8: 0 | FO8: 0 | FP8: 0 | FQ8: 0 | FR8: 0 | FS8: 0 | FT8: 0 | FU8: 0 | FV8: 0 | FW8: 0 | FX8: 0 | FY8: 0 | FZ8: 0 | GA8: 0 | GB8: 0 | GC8: 0 | GD8: 0 | GE8: 0 | GF8: 0 | GG8: 0 | GH8: 0 | GI8: 0 | GJ8: 0 | GK8: 0 | GL8: 0 | GM8: 0 | GN8: 0 | GO8: 0 | GP8: 0 | GQ8: 0 | GR8: 0 | GS8: 0 | GT8: 0 | GU8: 0 | GV8: 0 | GW8: 0 | GX8: 0 | GY8: 0 | GZ8: 0 | HA8: 0 | HB8: 0 | HC8: 0 | HD8: 0 | HE8: 0 | HF8: 0 | HG8: 0 | HH8: 0 | HI8: 0 | HJ8: 0 | HK8: 0 | HL8: 0 | HM8: 0 | HN8: 0 | HO8: 0 | HP8: 0 | HQ8: 0 | HR8: 0 | HS8: 0 | HT8: 0 | HU8: 0 | HV8: 0 | HW8: 0 | HX8: 0 | HY8: 0 | HZ8: 0 | IA8: 0 | IB8: 0 | IC8: 0 | ID8: 0 | IE8: 0 | IF8: 0 | IG8: 0 | IH8: 0 | II8: 0 | IJ8: 0 | IK8: 0 | IL8: 0 | IM8: 0 | IN8: 0 | IO8: 0 | IP8: 0 | IQ8: 0 | IR8: 0 | IS8: 0 | IT8: 0 | IU8: 0 | IV8: 0 | IW8: 0 | IX8: 0 | IY8: 0 | IZ8: 0 | JA8: 0 | JB8: 0 | JC8: 0 | JD8: 0 | JE8: 0 | JF8: 0 | JG8: 0 | JH8: 0 | JI8: 0 | JJ8: 0 | JK8: 0 | JL8: 0 | JM8: 0 | JN8: 0 | JO8: 0 | JP8: 0 | JQ8: 0 | JR8: 0 | JS8: 0 | JT8: 0 | JU8: 0 | JV8: 0 | JW8: 0 | JX8: 0 | JY8: 0 | JZ8: 0 | KA8: 0 | KB8: 0 | KC8: 0 | KD8: 0 | KE8: 0 | KF8: 0 | KG8: 0 | KH8: 0
A9: 3.8 | B9: SPV | C9: Sector 1 IF Offices Leasing, Maintenance and Security. | D9: 100 | E9: 105
A10: 3.9 | B10: SPV | C10: Sector 2 IF Offices Cost. | D10: 100 | E10: 105
A11: 3.10 | B11: SPV | C11: Fiscal Goods Deposit | D11: 100 | E11: 105
A12: 3.11 | B12: SPV | C12: construction BIM | D12: 100 | E12: 105 | BC12: 80 | BD12: 80 | BE12: 80 | BF12: 80 | BG12: 80 | BH12: 80 | BI12: 80 | BJ12: 80 | BK12: 80 | BL12: 80 | BM12: 80 | BN12: 80 | BO12: 80 | BP12: 80 | BQ12: 80 | BR12: 80 | BS12: 80 | BT12: 80 | BU12: 80 | BV12: 80 | BW12: 80 | BX12: 80 | BY12: 80 | BZ12: 80 | CA12: 80 | CB12: 80 | CC12: 80 | CD12: 80 | CE12: 80 | CF12: 80 | CG12: 80 | CH12: 80 | CI12: 80 | CJ12: 80 | CK12: 80 | CL12: 80 | CM12: 80 | CN12: 80 | CO12: 80 | CP12: 80 | CQ12: 80 | CR12: 80 | CS12: 80 | CT12: 80 | CU12: 80 | CV12: 80 | CW12: 80 | CX12: 80 | CY12: 80 | CZ12: 80 | DA12: 80 | DB12: 80 | DC12: 80 | DD12: 80 | DE12: 80 | DF12: 80 | DG12: 80 | DH12: 80 | DI12: 80 | DJ12: 80 | DK12: 80
A13: 4.1 | B13: CAPEX | C13: Sub-sector A | D13: 100 | E13: 109 | F13: 0 | G13: 0 | H13: 0 | I13: 0 | J13: 0 | K13: 0 | L13: 0 | M13: 0 | N13: 0 | O13: 0 | P13: 0 | Q13: 0 | R13: 0 | S13: 0 | T13: 0 | U13: 0 | V13: 0 | W13: 0 | X13: 0 | Y13: 0 | Z13: 0 | AA13: 0 | AB13: 0 | AC13: 0 | AD13: 0 | AE13: 0 | AF13: 0 | AG13: 0 | AH13: 0 | AI13: 0 | AJ13: 0 | AK13: 0 | AL13: 0 | AM13: 0 | AN13: 0 | AO13: 0 | AP13: 0 | AQ13: 0 | AR13: 0 | AS13: 0 | AT13: 0 | AU13: 0 | AV13: 0 | AW13: 0 | AX13: 0 | AY13: 0 | AZ13: 0 | BA13: 0 | BB13: 0 | BC13: 0 | BD13: 0 | BE13: 0 | BF13: 0 | BG13: 0 | BH13: 0 | BI13: 0 | BJ13: 0 | BK13: 0 | BL13: 0 | BM13: 0 | BN13: 0 | BO13: 0 | BP13: 0 | BQ13: 0 | BR13: 0 | BS13: 0 | BT13: 5380.4089 | BU13: 18538.593 | BV13: 24385.716 | BW13: 24420.705 | BX13: 24400.803 | BY13: 24420.705 | BZ13: 23428.143 | CA13: 23393.155 | CB13: 23408.242 | CC13: 23408.242 | CD13: 23373.254 | CE13: 29955.554 | CF13: 30948.115 | CG13: 29441.271 | CH13: 29441.271 | CI13: 23570.844 | CJ13: 23570.844 | CK13: 23570.844 | CL13: 23570.844 | CM13: 11004.044 | CN13: 11004.044 | CO13: 0 | CP13: 0 | CQ13: 0 | CR13: 0 | CS13: 0 | CT13: 0 | CU13: 0 | CV13: 0 | CW13: 0 | CX13: 0 | CY13: 0 | CZ13: 0 | DA13: 0 | DB13: 0 | DC13: 0 | DD13: 0 | DE13: 0 | DF13: 0 | DG13: 0 | DH13: 0 | DI13: 0 | DJ13: 0 | DK13: 0 | DL13: 0 | DM13: 0 | DN13: 0 | DO13: 0 | DP13: 0 | DQ13: 0 | DR13: 0 | DS13: 0 | DT13: 0 | DU13: 0 | DV13: 0 | DW13: 0 | DX13: 0 | DY13: 0 | DZ13: 0 | EA13: 0 | EB13: 0 | EC13: 0 | ED13: 0 | EE13: 0 | EF13: 0 | EG13: 0 | EH13: 0 | EI13: 0 | EJ13: 0 | EK13: 0 | EL13: 0 | EM13: 0 | EN13: 0 | EO13: 0 | EP13: 0 | EQ13: 0 | ER13: 0 | ES13: 0 | ET13: 0 | EU13: 0 | EV13: 0 | EW13: 0 | EX13: 0 | EY13: 0 | EZ13: 0 | FA13: 0 | FB13: 0 | FC13: 0 | FD13: 0 | FE13: 0 | FF13: 0 | FG13: 0 | FH13: 0 | FI13: 0 | FJ13: 0 | FK13: 0 | FL13: 0 | FM13: 0 | FN13: 0 | FO13: 0 | FP13: 0 | FQ13: 0 | FR13: 0 | FS13: 0 | FT13: 0 | FU13: 0 | FV13: 0 | FW13: 0 | FX13: 0 | FY13: 0 | FZ13: 0 | GA13: 0 | GB13: 0 | GC13: 0 | GD13: 0 | GE13: 0 | GF13: 0 | GG13: 0 | GH13: 0 | GI13: 0 | GJ13: 0 | GK13: 0 | GL13: 0 | GM13: 0 | GN13: 0 | GO13: 0 | GP13: 0 | GQ13: 0 | GR13: 0 | GS13: 0 | GT13: 0 | GU13: 0 | GV13: 0 | GW13: 0 | GX13: 0 | GY13: 0 | GZ13: 0 | HA13: 0 | HB13: 0 | HC13: 0 | HD13: 0 | HE13: 0 | HF13: 0 | HG13: 0 | HH13: 0 | HI13: 0 | HJ13: 0 | HK13: 0 | HL13: 0 | HM13: 0 | HN13: 0 | HO13: 0 | HP13: 0 | HQ13: 0 | HR13: 0 | HS13: 0 | HT13: 0 | HU13: 0 | HV13: 0 | HW13: 0 | HX13: 0 | HY13: 0 | HZ13: 0 | IA13: 0 | IB13: 0 | IC13: 0 | ID13: 0 | IE13: 0 | IF13: 0 | IG13: 0 | IH13: 0 | II13: 0 | IJ13: 0 | IK13: 0 | IL13: 0 | IM13: 0 | IN13: 0 | IO13: 0 | IP13: 0
A14: 4.2 | B14: CAPEX | C14: Sub-sector B0 | D14: 100 | E14: 109 | F14: 0 | G14: 0 | H14: 0 | I14: 0 | J14: 0 | K14: 0 | L14: 0 | M14: 0 | N14: 0 | O14: 0 | P14: 0 | Q14: 0 | R14: 0 | S14: 0 | T14: 0 | U14: 0 | V14: 0 | W14: 0 | X14: 0 | Y14: 0 | Z14: 0 | AA14: 0 | AB14: 0 | AC14: 0 | AD14: 0 | AE14: 0 | AF14: 0 | AG14: 0 | AH14: 0 | AI14: 0 | AJ14: 0 | AK14: 0 | AL14: 0 | AM14: 0 | AN14: 0 | AO14: 0 | AP14: 0 | AQ14: 0 | AR14: 0 | AS14: 0 | AT14: 0 | AU14: 0 | AV14: 0 | AW14: 0 | AX14: 0 | AY14: 0 | AZ14: 0 | BA14: 0 | BB14: 0 | BC14: 1043.8308 | BD14: 21173.654 | BE14: 20129.824 | BF14: 26370.31 | BG14: 5102.8638 | BH14: 3048.3847 | BI14: 4791.8905 | BJ14: 2511.1853 | BK14: 1467.3545 | BL14: 23389.929 | BM14: 24676.729 | BN14: 1743.5058 | BO14: 2511.1853 | BP14: 767.67949 | BQ14: 23389.929 | BR14: 24676.729 | BS14: 0 | BT14: 0 | BU14: 0 | BV14: 0 | BW14: 0 | BX14: 0 | BY14: 0 | BZ14: 0 | CA14: 0 | CB14: 0 | CC14: 0 | CD14: 0 | CE14: 0 | CF14: 0 | CG14: 0 | CH14: 0 | CI14: 0 | CJ14: 0 | CK14: 0 | CL14: 0 | CM14: 0 | CN14: 0 | CO14: 0 | CP14: 0 | CQ14: 0 | CR14: 0 | CS14: 0 | CT14: 0 | CU14: 0 | CV14: 0 | CW14: 0 | CX14: 0 | CY14: 0 | CZ14: 0 | DA14: 0 | DB14: 0 | DC14: 0 | DD14: 0 | DE14: 0 | DF14: 0 | DG14: 0 | DH14: 0 | DI14: 0 | DJ14: 0 | DK14: 0 | DL14: 0 | DM14: 0 | DN14: 0 | DO14: 0 | DP14: 0 | DQ14: 0 | DR14: 0 | DS14: 0 | DT14: 0 | DU14: 0 | DV14: 0 | DW14: 0 | DX14: 0 | DY14: 0 | DZ14: 0 | EA14: 0 | EB14: 0 | EC14: 0 | ED14: 0 | EE14: 0 | EF14: 0 | EG14: 0 | EH14: 0 | EI14: 0 | EJ14: 0 | EK14: 0 | EL14: 0 | EM14: 0 | EN14: 0 | EO14: 0 | EP14: 0 | EQ14: 0 | ER14: 0 | ES14: 0 | ET14: 0 | EU14: 0 | EV14: 0 | EW14: 0 | EX14: 0 | EY14: 0 | EZ14: 0 | FA14: 0 | FB14: 0 | FC14: 0 | FD14: 0 | FE14: 0 | FF14: 0 | FG14: 0 | FH14: 0 | FI14: 0 | FJ14: 0 | FK14: 0 | FL14: 0 | FM14: 0 | FN14: 0 | FO14: 0 | FP14: 0 | FQ14: 0 | FR14: 0 | FS14: 0 | FT14: 0 | FU14: 0 | FV14: 0 | FW14: 0 | FX14: 0 | FY14: 0 | FZ14: 0 | GA14: 0 | GB14: 0 | GC14: 0 | GD14: 0 | GE14: 0 | GF14: 0 | GG14: 0 | GH14: 0 | GI14: 0 | GJ14: 0 | GK14: 0 | GL14: 0 | GM14: 0 | GN14: 0 | GO14: 0 | GP14: 0 | GQ14: 0 | GR14: 0 | GS14: 0 | GT14: 0 | GU14: 0 | GV14: 0 | GW14: 0 | GX14: 0 | GY14: 0 | GZ14: 0 | HA14: 0 | HB14: 0 | HC14: 0 | HD14: 0 | HE14: 0 | HF14: 0 | HG14: 0 | HH14: 0 | HI14: 0 | HJ14: 0 | HK14: 0 | HL14: 0 | HM14: 0 | HN14: 0 | HO14: 0 | HP14: 0 | HQ14: 0 | HR14: 0 | HS14: 0 | HT14: 0 | HU14: 0 | HV14: 0 | HW14: 0 | HX14: 0 | HY14: 0 | HZ14: 0 | IA14: 0 | IB14: 0 | IC14: 0 | ID14: 0 | IE14: 0 | IF14: 0 | IG14: 0 | IH14: 0 | II14: 0 | IJ14: 0 | IK14: 0 | IL14: 0 | IM14: 0 | IN14: 0 | IO14: 0 | IP14: 0
A15: 4.3 | B15: CAPEX | C15: Sub-sector B | D15: 100 | E15: 109 | F15: 0 | G15: 0 | H15: 0 | I15: 0 | J15: 0 | K15: 0 | L15: 0 | M15: 0 | N15: 0 | O15: 0 | P15: 0 | Q15: 0 | R15: 0 | S15: 0 | T15: 0 | U15: 0 | V15: 0 | W15: 0 | X15: 0 | Y15: 0 | Z15: 0 | AA15: 0 | AB15: 0 | AC15: 0 | AD15: 0 | AE15: 0 | AF15: 0 | AG15: 0 | AH15: 0 | AI15: 0 | AJ15: 0 | AK15: 0 | AL15: 0 | AM15: 0 | AN15: 0 | AO15: 0 | AP15: 0 | AQ15: 0 | AR15: 0 | AS15: 0 | AT15: 0 | AU15: 0 | AV15: 0 | AW15: 70237.893 | AX15: 0 | AY15: 0 | AZ15: 0 | BA15: 0 | BB15: 0 | BC15: 0 | BD15: 0 | BE15: 0 | BF15: 0 | BG15: 0 | BH15: 0 | BI15: 0 | BJ15: 0 | BK15: 0 | BL15: 0 | BM15: 0 | BN15: 0 | BO15: 0 | BP15: 0 | BQ15: 0 | BR15: 0 | BS15: 0 | BT15: 0 | BU15: 0 | BV15: 0 | BW15: 0 | BX15: 0 | BY15: 0 | BZ15: 4825.2916 | CA15: 5881.5996 | CB15: 15179.119 | CC15: 14711.787 | CD15: 15380.639 | CE15: 24420.515 | CF15: 32851.009 | CG15: 21516.305 | CH15: 26855.484 | CI15: 25000.931 | CJ15: 22269.729 | CK15: 22342.497 | CL15: 25900.204 | CM15: 22342.497 | CN15: 24191.616 | CO15: 25940.142 | CP15: 20608.082 | CQ15: 0 | CR15: 0 | CS15: 0 | CT15: 0 | CU15: 0 | CV15: 0 | CW15: 0 | CX15: 0 | CY15: 0 | CZ15: 0 | DA15: 0 | DB15: 0 | DC15: 0 | DD15: 0 | DE15: 0 | DF15: 0 | DG15: 0 | DH15: 0 | DI15: 0 | DJ15: 0 | DK15: 0 | DL15: 0 | DM15: 0 | DN15: 0 | DO15: 0 | DP15: 0 | DQ15: 0 | DR15: 0 | DS15: 0 | DT15: 0 | DU15: 0 | DV15: 0 | DW15: 0 | DX15: 0 | DY15: 0 | DZ15: 0 | EA15: 0 | EB15: 0 | EC15: 0 | ED15: 0 | EE15: 0 | EF15: 0 | EG15: 0 | EH15: 0 | EI15: 0 | EJ15: 0 | EK15: 0 | EL15: 0 | EM15: 0 | EN15: 0 | EO15: 0 | EP15: 0 | EQ15: 0 | ER15: 0 | ES15: 0 | ET15: 0 | EU15: 0 | EV15: 0 | EW15: 0 | EX15: 0 | EY15: 0 | EZ15: 0 | FA15: 0 | FB15: 0 | FC15: 0 | FD15: 0 | FE15: 0 | FF15: 0 | FG15: 0 | FH15: 0 | FI15: 0 | FJ15: 0 | FK15: 0 | FL15: 0 | FM15: 0 | FN15: 0 | FO15: 0 | FP15: 0 | FQ15: 0 | FR15: 0 | FS15: 0 | FT15: 0 | FU15: 0 | FV15: 0 | FW15: 0 | FX15: 0 | FY15: 0 | FZ15: 0 | GA15: 0 | GB15: 0 | GC15: 0 | GD15: 0 | GE15: 0 | GF15: 0 | GG15: 0 | GH15: 0 | GI15: 0 | GJ15: 0 | GK15: 0 | GL15: 0 | GM15: 0 | GN15: 0 | GO15: 0 | GP15: 0 | GQ15: 0 | GR15: 0 | GS15: 0 | GT15: 0 | GU15: 0 | GV15: 0 | GW15: 0 | GX15: 0 | GY15: 0 | GZ15: 0 | HA15: 0 | HB15: 0 | HC15: 0 | HD15: 0 | HE15: 0 | HF15: 0 | HG15: 0 | HH15: 0 | HI15: 0 | HJ15: 0 | HK15: 0 | HL15: 0 | HM15: 0 | HN15: 0 | HO15: 0 | HP15: 0 | HQ15: 0 | HR15: 0 | HS15: 0 | HT15: 0 | HU15: 0 | HV15: 0 | HW15: 0 | HX15: 0 | HY15: 0 | HZ15: 0 | IA15: 0 | IB15: 0 | IC15: 0 | ID15: 0 | IE15: 0 | IF15: 0 | IG15: 0 | IH15: 0 | II15: 0 | IJ15: 0 | IK15: 0 | IL15: 0 | IM15: 0 | IN15: 0 | IO15: 0 | IP15: 0
A16: 4.4 | B16: CAPEX | C16: Sub-sector C | D16: 100 | E16: 109 | F16: 0 | G16: 0 | H16: 0 | I16: 0 | J16: 0 | K16: 0 | L16: 0 | M16: 0 | N16: 0 | O16: 0 | P16: 0 | Q16: 0 | R16: 0 | S16: 0 | T16: 0 | U16: 0 | V16: 0 | W16: 0 | X16: 0 | Y16: 0 | Z16: 0 | AA16: 0 | AB16: 0 | AC16: 0 | AD16: 0 | AE16: 0 | AF16: 0 | AG16: 0 | AH16: 0 | AI16: 0 | AJ16: 0 | AK16: 0 | AL16: 0 | AM16: 0 | AN16: 0 | AO16: 0 | AP16: 0 | AQ16: 0 | AR16: 0 | AS16: 0 | AT16: 0 | AU16: 0 | AV16: 0 | AW16: 0 | AX16: 42286.657 | AY16: 0 | AZ16: 0 | BA16: 0 | BB16: 18122.853 | BC16: 0 | BD16: 0 | BE16: 0 | BF16: 0 | BG16: 0 | BH16: 0 | BI16: 0 | BJ16: 0 | BK16: 0 | BL16: 0 | BM16: 0 | BN16: 0 | BO16: 0 | BP16: 0 | BQ16: 0 | BR16: 0 | BS16: 0 | BT16: 14452.394 | BU16: 19152.982 | BV16: 21331.071 | BW16: 14452.394 | BX16: 14567.197 | BY16: 121755.5 | BZ16: 82181.041 | CA16: 82181.041 | CB16: 82181.041 | CC16: 83579.849 | CD16: 85678.062 | CE16: 85678.062 | CF16: 82181.041 | CG16: 82181.041 | CH16: 82181.041 | CI16: 82181.041 | CJ16: 84978.658 | CK16: 82181.041 | CL16: 410905.2 | CM16: 82181.041 | CN16: 82181.041 | CO16: 82181.041 | CP16: 82181.041 | CQ16: 157053.53 | CR16: 319388.35 | CS16: 314335.02 | CT16: 134285.68 | CU16: 83558.677 | CV16: 70716.578 | CW16: 70716.578 | CX16: 97469.219 | CY16: 16436.208 | CZ16: 16436.208 | DA16: 16436.208 | DB16: 16436.208 | DC16: 15851.202 | DD16: 20436.988 | DE16: 20436.988 | DF16: 15851.202 | DG16: 20436.988 | DH16: 20436.988 | DI16: 0 | DJ16: 0 | DK16: 0 | DL16: 0 | DM16: 0 | DN16: 0 | DO16: 0 | DP16: 0 | DQ16: 0 | DR16: 0 | DS16: 0 | DT16: 0 | DU16: 0 | DV16: 0 | DW16: 0 | DX16: 0 | DY16: 0 | DZ16: 0 | EA16: 0 | EB16: 0 | EC16: 0 | ED16: 0 | EE16: 0 | EF16: 0 | EG16: 0 | EH16: 0 | EI16: 0 | EJ16: 0 | EK16: 0 | EL16: 0 | EM16: 0 | EN16: 0 | EO16: 0 | EP16: 0 | EQ16: 0 | ER16: 0 | ES16: 0 | ET16: 0 | EU16: 0 | EV16: 0 | EW16: 0 | EX16: 0 | EY16: 0 | EZ16: 0 | FA16: 0 | FB16: 0 | FC16: 0 | FD16: 0 | FE16: 0 | FF16: 0 | FG16: 0 | FH16: 0 | FI16: 0 | FJ16: 0 | FK16: 0 | FL16: 0 | FM16: 0 | FN16: 0 | FO16: 0 | FP16: 0 | FQ16: 0 | FR16: 0 | FS16: 0 | FT16: 0 | FU16: 0 | FV16: 0 | FW16: 0 | FX16: 0 | FY16: 0 | FZ16: 0 | GA16: 0 | GB16: 0 | GC16: 0 | GD16: 0 | GE16: 0 | GF16: 0 | GG16: 0 | GH16: 0 | GI16: 0 | GJ16: 0 | GK16: 0 | GL16: 0 | GM16: 0 | GN16: 0 | GO16: 0 | GP16: 0 | GQ16: 0 | GR16: 0 | GS16: 0 | GT16: 0 | GU16: 0 | GV16: 0 | GW16: 0 | GX16: 0 | GY16: 0 | GZ16: 0 | HA16: 0 | HB16: 0 | HC16: 0 | HD16: 0 | HE16: 0 | HF16: 0 | HG16: 0 | HH16: 0 | HI16: 0 | HJ16: 0 | HK16: 0 | HL16: 0 | HM16: 0 | HN16: 0 | HO16: 0 | HP16: 0 | HQ16: 0 | HR16: 0 | HS16: 0 | HT16: 0 | HU16: 0 | HV16: 0 | HW16: 0 | HX16: 0 | HY16: 0 | HZ16: 0 | IA16: 0 | IB16: 0 | IC16: 0 | ID16: 0 | IE16: 0 | IF16: 0 | IG16: 0 | IH16: 0 | II16: 0 | IJ16: 0 | IK16: 0 | IL16: 0 | IM16: 0 | IN16: 0 | IO16: 0 | IP16: 0
A17: 4.5 | B17: CAPEX | C17: Sub-sector D | D17: 100 | E17: 109 | F17: 0 | G17: 0 | H17: 0 | I17: 0 | J17: 0 | K17: 0 | L17: 0 | M17: 0 | N17: 0 | O17: 0 | P17: 0 | Q17: 0 | R17: 0 | S17: 0 | T17: 0 | U17: 0 | V17: 0 | W17: 0 | X17: 0 | Y17: 0 | Z17: 0 | AA17: 0 | AB17: 0 | AC17: 0 | AD17: 0 | AE17: 0 | AF17: 0 | AG17: 0 | AH17: 0 | AI17: 0 | AJ17: 0 | AK17: 0 | AL17: 0 | AM17: 0 | AN17: 0 | AO17: 0 | AP17: 0 | AQ17: 0 | AR17: 0 | AS17: 0 | AT17: 0 | AU17: 0 | AV17: 0 | AW17: 0 | AX17: 0 | AY17: 0 | AZ17: 0 | BA17: 0 | BB17: 0 | BC17: 0 | BD17: 0 | BE17: 0 | BF17: 0 | BG17: 0 | BH17: 0 | BI17: 0 | BJ17: 0 | BK17: 22366.329 | BL17: 0 | BM17: 0 | BN17: 9585.5694 | BO17: 0 | BP17: 0 | BQ17: 0 | BR17: 0 | BS17: 0 | BT17: 11545.603 | BU17: 15620.508 | BV17: 17657.96 | BW17: 11545.603 | BX17: 11545.603 | BY17: 71068.001 | BZ17: 85451.643 | CA17: 61681.326 | CB17: 59643.873 | CC17: 59643.873 | CD17: 59643.873 | CE17: 59643.873 | CF17: 59643.873 | CG17: 59643.873 | CH17: 59643.873 | CI17: 59643.873 | CJ17: 59643.873 | CK17: 59643.873 | CL17: 63657.022 | CM17: 63657.022 | CN17: 182944.77 | CO17: 242588.64 | CP17: 246420.35 | CQ17: 63657.022 | CR17: 63657.022 | CS17: 63657.022 | CT17: 84031.545 | CU17: 63657.022 | CV17: 59643.873 | CW17: 59643.873 | CX17: 59643.873 | CY17: 59643.873 | CZ17: 54744.64 | DA17: 10793.252 | DB17: 33375.332 | DC17: 11545.603 | DD17: 15620.508 | DE17: 17657.96 | DF17: 11545.603 | DG17: 11545.603 | DH17: 0 | DI17: 0 | DJ17: 0 | DK17: 0 | DL17: 0 | DM17: 0 | DN17: 0 | DO17: 0 | DP17: 0 | DQ17: 0 | DR17: 0 | DS17: 0 | DT17: 0 | DU17: 0 | DV17: 0 | DW17: 0 | DX17: 0 | DY17: 0 | DZ17: 0 | EA17: 0 | EB17: 0 | EC17: 0 | ED17: 0 | EE17: 0 | EF17: 0 | EG17: 0 | EH17: 0 | EI17: 0 | EJ17: 0 | EK17: 0 | EL17: 0 | EM17: 0 | EN17: 0 | EO17: 0 | EP17: 0 | EQ17: 0 | ER17: 0 | ES17: 0 | ET17: 0 | EU17: 0 | EV17: 0 | EW17: 0 | EX17: 0 | EY17: 0 | EZ17: 0 | FA17: 0 | FB17: 0 | FC17: 0 | FD17: 0 | FE17: 0 | FF17: 0 | FG17: 0 | FH17: 0 | FI17: 0 | FJ17: 0 | FK17: 0 | FL17: 0 | FM17: 0 | FN17: 0 | FO17: 0 | FP17: 0 | FQ17: 0 | FR17: 0 | FS17: 0 | FT17: 0 | FU17: 0 | FV17: 0 | FW17: 0 | FX17: 0 | FY17: 0 | FZ17: 0 | GA17: 0 | GB17: 0 | GC17: 0 | GD17: 0 | GE17: 0 | GF17: 0 | GG17: 0 | GH17: 0 | GI17: 0 | GJ17: 0 | GK17: 0 | GL17: 0 | GM17: 0 | GN17: 0 | GO17: 0 | GP17: 0 | GQ17: 0 | GR17: 0 | GS17: 0 | GT17: 0 | GU17: 0 | GV17: 0 | GW17: 0 | GX17: 0 | GY17: 0 | GZ17: 0 | HA17: 0 | HB17: 0 | HC17: 0 | HD17: 0 | HE17: 0 | HF17: 0 | HG17: 0 | HH17: 0 | HI17: 0 | HJ17: 0 | HK17: 0 | HL17: 0 | HM17: 0 | HN17: 0 | HO17: 0 | HP17: 0 | HQ17: 0 | HR17: 0 | HS17: 0 | HT17: 0 | HU17: 0 | HV17: 0 | HW17: 0 | HX17: 0 | HY17: 0 | HZ17: 0 | IA17: 0 | IB17: 0 | IC17: 0 | ID17: 0 | IE17: 0 | IF17: 0 | IG17: 0 | IH17: 0 | II17: 0 | IJ17: 0 | IK17: 0 | IL17: 0 | IM17: 0 | IN17: 0 | IO17: 0 | IP17: 0
A18: 4.6 | B18: CAPEX | C18: Sub-sector E | D18: 100 | E18: 109 | F18: 0 | G18: 0 | H18: 0 | I18: 0 | J18: 0 | K18: 0 | L18: 0 | M18: 0 | N18: 0 | O18: 0 | P18: 0 | Q18: 0 | R18: 0 | S18: 0 | T18: 0 | U18: 0 | V18: 0 | W18: 0 | X18: 0 | Y18: 0 | Z18: 0 | AA18: 0 | AB18: 0 | AC18: 0 | AD18: 0 | AE18: 0 | AF18: 0 | AG18: 0 | AH18: 0 | AI18: 0 | AJ18: 0 | AK18: 0 | AL18: 0 | AM18: 0 | AN18: 0 | AO18: 0 | AP18: 0 | AQ18: 0 | AR18: 0 | AS18: 0 | AT18: 0 | AU18: 0 | AV18: 0 | AW18: 0 | AX18: 0 | AY18: 0 | AZ18: 0 | BA18: 0 | BB18: 0 | BC18: 0 | BD18: 0 | BE18: 0 | BF18: 0 | BG18: 0 | BH18: 0 | BI18: 0 | BJ18: 0 | BK18: 41967.456 | BL18: 0 | BM18: 0 | BN18: 0 | BO18: 17986.053 | BP18: 0 | BQ18: 0 | BR18: 0 | BS18: 0 | BT18: 18618.266 | BU18: 22547.772 | BV18: 24512.525 | BW18: 18618.266 | BX18: 18618.266 | BY18: 103618.36 | BZ18: 103618.36 | CA18: 103618.36 | CB18: 103618.36 | CC18: 103618.36 | CD18: 104206.6 | CE18: 103618.36 | CF18: 103618.36 | CG18: 103618.36 | CH18: 103618.36 | CI18: 103618.36 | CJ18: 108030.16 | CK18: 108030.16 | CL18: 414473.45 | CM18: 108030.16 | CN18: 108030.16 | CO18: 315266.89 | CP18: 233172.86 | CQ18: 172833.96 | CR18: 185936.69 | CS18: 469384.66 | CT18: 322752.41 | CU18: 320138.81 | CV18: 131607.19 | CW18: 103618.36 | CX18: 19500.626 | CY18: 19500.626 | CZ18: 19500.626 | DA18: 19500.626 | DB18: 19500.626 | DC18: 19500.626 | DD18: 19500.626 | DE18: 19500.626 | DF18: 19500.626 | DG18: 19500.626 | DH18: 22547.772 | DI18: 24512.525 | DJ18: 18618.266 | DK18: 18618.266 | DL18: 0 | DM18: 0 | DN18: 0 | DO18: 0 | DP18: 0 | DQ18: 0 | DR18: 0 | DS18: 0 | DT18: 0 | DU18: 0 | DV18: 0 | DW18: 0 | DX18: 0 | DY18: 0 | DZ18: 0 | EA18: 0 | EB18: 0 | EC18: 0 | ED18: 0 | EE18: 0 | EF18: 0 | EG18: 0 | EH18: 0 | EI18: 0 | EJ18: 0 | EK18: 0 | EL18: 0 | EM18: 0 | EN18: 0 | EO18: 0 | EP18: 0 | EQ18: 0 | ER18: 0 | ES18: 0 | ET18: 0 | EU18: 0 | EV18: 0 | EW18: 0 | EX18: 0 | EY18: 0 | EZ18: 0 | FA18: 0 | FB18: 0 | FC18: 0 | FD18: 0 | FE18: 0 | FF18: 0 | FG18: 0 | FH18: 0 | FI18: 0 | FJ18: 0 | FK18: 0 | FL18: 0 | FM18: 0 | FN18: 0 | FO18: 0 | FP18: 0 | FQ18: 0 | FR18: 0 | FS18: 0 | FT18: 0 | FU18: 0 | FV18: 0 | FW18: 0 | FX18: 0 | FY18: 0 | FZ18: 0 | GA18: 0 | GB18: 0 | GC18: 0 | GD18: 0 | GE18: 0 | GF18: 0 | GG18: 0 | GH18: 0 | GI18: 0 | GJ18: 0 | GK18: 0 | GL18: 0 | GM18: 0 | GN18: 0 | GO18: 0 | GP18: 0 | GQ18: 0 | GR18: 0 | GS18: 0 | GT18: 0 | GU18: 0 | GV18: 0 | GW18: 0 | GX18: 0 | GY18: 0 | GZ18: 0 | HA18: 0 | HB18: 0 | HC18: 0 | HD18: 0 | HE18: 0 | HF18: 0 | HG18: 0 | HH18: 0 | HI18: 0 | HJ18: 0 | HK18: 0 | HL18: 0 | HM18: 0 | HN18: 0 | HO18: 0 | HP18: 0 | HQ18: 0 | HR18: 0 | HS18: 0 | HT18: 0 | HU18: 0 | HV18: 0 | HW18: 0 | HX18: 0 | HY18: 0 | HZ18: 0 | IA18: 0 | IB18: 0 | IC18: 0 | ID18: 0 | IE18: 0 | IF18: 0 | IG18: 0 | IH18: 0 | II18: 0 | IJ18: 0 | IK18: 0 | IL18: 0 | IM18: 0 | IN18: 0 | IO18: 0 | IP18: 0
A19: 4.7 | B19: CAPEX | C19: Design | D19: 100 | E19: 102 | F19: 0 | G19: 0 | H19: 0 | I19: 0 | J19: 0 | K19: 35305.763 | L19: 19737.993 | M19: 8908.5233 | N19: 4103.0356 | O19: 5340.9925 | P19: 5297.3915 | Q19: 34847.361 | R19: 3329.8923 | S19: 4410.7433 | T19: 52390.383 | U19: 1783.3333 | V19: 4543.9533 | W19: 84152.816 | X19: 3471.2833 | Y19: 31169.279 | Z19: 2688.21 | AA19: 2717.21 | AB19: 2142.96 | AC19: 1783.33 | AD19: 1783.33 | AE19: 1974.75 | AF19: 28895.51 | AG19: 1783.33 | AH19: 15010.236 | AI19: 1783.33 | AJ19: 1783.33 | AK19: 19816.896 | AL19: 1783.33 | AM19: 4506.4987 | AN19: 6096.5486 | AO19: 2879.0595 | AP19: 3243.7376 | AQ19: 7737.4962 | AR19: 3414.942 | AS19: 504 | AT19: 0 | AU19: 0 | AV19: 0 | AW19: 3009.4434 | AX19: 38813.98 | AY19: 4748.7936 | AZ19: 130.74033 | BA19: 0 | BB19: 0 | BC19: 16003.148 | BD19: 26146.951 | BE19: 0 | BF19: 0 | BG19: 0 | BH19: 0 | BI19: 10143.803 | BJ19: 0 | BK19: 0 | BL19: 0 | BM19: 0 | BN19: 0 | BO19: 0 | BP19: 0 | BQ19: 0 | BR19: 0 | BS19: 0 | BT19: 0 | BU19: 0 | BV19: 0 | BW19: 0 | BX19: 0 | BY19: 0 | BZ19: 0 | CA19: 0 | CB19: 0 | CC19: 0 | CD19: 0 | CE19: 0 | CF19: 0 | CG19: 0 | CH19: 0 | CI19: 0 | CJ19: 0 | CK19: 0 | CL19: 0 | CM19: 0 | CN19: 0 | CO19: 0 | CP19: 0 | CQ19: 0 | CR19: 0 | CS19: 0 | CT19: 0 | CU19: 0 | CV19: 0 | CW19: 0 | CX19: 0 | CY19: 0 | CZ19: 0 | DA19: 0 | DB19: 0 | DC19: 0 | DD19: 0 | DE19: 0 | DF19: 0 | DG19: 0 | DH19: 0 | DI19: 0 | DJ19: 0 | DK19: 0 | DL19: 0 | DM19: 0 | DN19: 0 | DO19: 0 | DP19: 0 | DQ19: 0 | DR19: 0 | DS19: 0 | DT19: 0 | DU19: 0 | DV19: 0 | DW19: 0 | DX19: 0 | DY19: 0 | DZ19: 0 | EA19: 0 | EB19: 0 | EC19: 0 | ED19: 0 | EE19: 0 | EF19: 0 | EG19: 0 | EH19: 0 | EI19: 0 | EJ19: 0 | EK19: 0 | EL19: 0 | EM19: 0 | EN19: 0 | EO19: 0 | EP19: 0 | EQ19: 0 | ER19: 0 | ES19: 0 | ET19: 0 | EU19: 0 | EV19: 0 | EW19: 0 | EX19: 0 | EY19: 0 | EZ19: 0 | FA19: 0 | FB19: 0 | FC19: 0 | FD19: 0 | FE19: 0 | FF19: 0 | FG19: 0 | FH19: 0 | FI19: 0 | FJ19: 0 | FK19: 0 | FL19: 0 | FM19: 0 | FN19: 0 | FO19: 0 | FP19: 0 | FQ19: 0 | FR19: 0 | FS19: 0 | FT19: 0 | FU19: 0 | FV19: 0 | FW19: 0 | FX19: 0 | FY19: 0 | FZ19: 0 | GA19: 0 | GB19: 0 | GC19: 0 | GD19: 0 | GE19: 0 | GF19: 0 | GG19: 0 | GH19: 0 | GI19: 0 | GJ19: 0 | GK19: 0 | GL19: 0 | GM19: 0 | GN19: 0 | GO19: 0 | GP19: 0 | GQ19: 0 | GR19: 0 | GS19: 0 | GT19: 0 | GU19: 0 | GV19: 0 | GW19: 0 | GX19: 0 | GY19: 0 | GZ19: 0 | HA19: 0 | HB19: 0 | HC19: 0 | HD19: 0 | HE19: 0 | HF19: 0 | HG19: 0 | HH19: 0 | HI19: 0 | HJ19: 0 | HK19: 0 | HL19: 0 | HM19: 0 | HN19: 0 | HO19: 0 | HP19: 0 | HQ19: 0 | HR19: 0 | HS19: 0 | HT19: 0 | HU19: 0 | HV19: 0 | HW19: 0 | HX19: 0 | HY19: 0 | HZ19: 0 | IA19: 0 | IB19: 0 | IC19: 0 | ID19: 0 | IE19: 0 | IF19: 0 | IG19: 0 | IH19: 0 | II19: 0 | IJ19: 0 | IK19: 0 | IL19: 0 | IM19: 0 | IN19: 0 | IO19: 0 | IP19: 0
A20: 4.8 | B20: CAPEX | C20: ITS + Tags + Toll Systems | D20: 100 | E20: 103 | F20: 0 | G20: 0 | H20: 0 | I20: 25210 | J20: 0 | K20: 0 | L20: 0 | M20: 0 | N20: 0 | O20: 0 | P20: 0 | Q20: 0 | R20: 0 | S20: 0 | T20: 0 | U20: 0 | V20: 0 | W20: 0 | X20: 0 | Y20: 38091.371 | Z20: 76100.522 | AA20: 0 | AB20: 0 | AC20: 0 | AD20: 0 | AE20: 0 | AF20: 0 | AG20: 0 | AH20: 0 | AI20: 0 | AJ20: 0 | AK20: 0 | AL20: 0 | AM20: 144514.39 | AN20: 0 | AO20: 0 | AP20: 0 | AQ20: 0 | AR20: 0 | AS20: 0 | AT20: 0 | AU20: 0 | AV20: 0 | AW20: 0 | AX20: 0 | AY20: 0 | AZ20: 0 | BA20: 0 | BB20: 0 | BC20: 0 | BD20: 0 | BE20: 0 | BF20: 0 | BG20: 0 | BH20: 2878.0128 | BI20: 2878.0128 | BJ20: 2878.0128 | BK20: 2878.0128 | BL20: 2878.0128 | BM20: 2878.0128 | BN20: 2878.0128 | BO20: 5653.1565 | BP20: 8261.0603 | BQ20: 8261.0603 | BR20: 8261.0603 | BS20: 8261.0603 | BT20: 8261.0603 | BU20: 8261.0603 | BV20: 8261.0603 | BW20: 5485.9166 | BX20: 0 | BY20: 0 | BZ20: 0 | CA20: 0 | CB20: 0 | CC20: 0 | CD20: 0 | CE20: 0 | CF20: 0 | CG20: 0 | CH20: 0 | CI20: 0 | CJ20: 0 | CK20: 0 | CL20: 0 | CM20: 0 | CN20: 0 | CO20: 0 | CP20: 0 | CQ20: 0 | CR20: 0 | CS20: 0 | CT20: 0 | CU20: 0 | CV20: 0 | CW20: 0 | CX20: 0 | CY20: 0 | CZ20: 5539.3528 | DA20: 8539.3528 | DB20: 10539.353 | DC20: 10539.353 | DD20: 10039.353 | DE20: 6039.3528 | DF20: 0 | DG20: 0 | DH20: 0 | DI20: 0 | DJ20: 0 | DK20: 0 | DL20: 0 | DM20: 0 | DN20: 0 | DO20: 0 | DP20: 0 | DQ20: 0 | DR20: 0 | DS20: 0 | DT20: 0 | DU20: 0 | DV20: 0 | DW20: 0 | DX20: 0 | DY20: 0 | DZ20: 0 | EA20: 0 | EB20: 0 | EC20: 0 | ED20: 0 | EE20: 0 | EF20: 0 | EG20: 0 | EH20: 0 | EI20: 0 | EJ20: 0 | EK20: 0 | EL20: 0 | EM20: 0 | EN20: 0 | EO20: 0 | EP20: 0 | EQ20: 0 | ER20: 0 | ES20: 0 | ET20: 0 | EU20: 0 | EV20: 0 | EW20: 0 | EX20: 0 | EY20: 0 | EZ20: 0 | FA20: 0 | FB20: 0 | FC20: 0 | FD20: 0 | FE20: 0 | FF20: 0 | FG20: 0 | FH20: 0 | FI20: 0 | FJ20: 0 | FK20: 0 | FL20: 0 | FM20: 0 | FN20: 0 | FO20: 0 | FP20: 0 | FQ20: 0 | FR20: 0 | FS20: 0 | FT20: 0 | FU20: 0 | FV20: 0 | FW20: 0 | FX20: 0 | FY20: 0 | FZ20: 0 | GA20: 0 | GB20: 0 | GC20: 0 | GD20: 0 | GE20: 0 | GF20: 0 | GG20: 0 | GH20: 0 | GI20: 0 | GJ20: 0 | GK20: 0 | GL20: 0 | GM20: 0 | GN20: 0 | GO20: 0 | GP20: 0 | GQ20: 0 | GR20: 0 | GS20: 0 | GT20: 0 | GU20: 0 | GV20: 0 | GW20: 0 | GX20: 0 | GY20: 0 | GZ20: 0 | HA20: 0 | HB20: 0 | HC20: 0 | HD20: 0 | HE20: 0 | HF20: 0 | HG20: 0 | HH20: 0 | HI20: 0 | HJ20: 0 | HK20: 0 | HL20: 0 | HM20: 0 | HN20: 0 | HO20: 0 | HP20: 0 | HQ20: 0 | HR20: 0 | HS20: 0 | HT20: 0 | HU20: 0 | HV20: 0 | HW20: 0 | HX20: 0 | HY20: 0 | HZ20: 0 | IA20: 0 | IB20: 0 | IC20: 0 | ID20: 0 | IE20: 0 | IF20: 0 | IG20: 0 | IH20: 0 | II20: 0 | IJ20: 0 | IK20: 0 | IL20: 0 | IM20: 0 | IN20: 0 | IO20: 0 | IP20: 0
A21: 4.9 | B21: CAPEX | C21: Toll Plaza Construction | D21: 100 | E21: 104 | F21: 0 | G21: 0 | H21: 0 | I21: 0 | J21: 0 | K21: 0 | L21: 0 | M21: 0 | N21: 0 | O21: 0 | P21: 0 | Q21: 0 | R21: 0 | S21: 0 | T21: 0 | U21: 0 | V21: 0 | W21: 0 | X21: 0 | Y21: 0 | Z21: 0 | AA21: 0 | AB21: 0 | AC21: 0 | AD21: 0 | AE21: 0 | AF21: 0 | AG21: 0 | AH21: 0 | AI21: 0 | AJ21: 0 | AK21: 0 | AL21: 0 | AM21: 0 | AN21: 0 | AO21: 0 | AP21: 0 | AQ21: 0 | AR21: 0 | AS21: 0 | AT21: 0 | AU21: 0 | AV21: 0 | AW21: 0 | AX21: 0 | AY21: 0 | AZ21: 0 | BA21: 0 | BB21: 0 | BC21: 0 | BD21: 0 | BE21: 0 | BF21: 0 | BG21: 0 | BH21: 0 | BI21: 0 | BJ21: 0 | BK21: 0 | BL21: 0 | BM21: 0 | BN21: 0 | BO21: 0 | BP21: 0 | BQ21: 0 | BR21: 0 | BS21: 0 | BT21: 63029.569 | BU21: 0 | BV21: 49530.83 | BW21: 0 | BX21: 0 | BY21: 0 | BZ21: 0 | CA21: 165042.42 | CB21: 0 | CC21: 0 | CD21: 0 | CE21: 57326.332 | CF21: 0 | CG21: 0 | CH21: 0 | CI21: 0 | CJ21: 0 | CK21: 0 | CL21: 0 | CM21: 0 | CN21: 0 | CO21: 0 | CP21: 0 | CQ21: 0 | CR21: 0 | CS21: 0 | CT21: 0 | CU21: 0 | CV21: 0 | CW21: 0 | CX21: 0 | CY21: 0 | CZ21: 0 | DA21: 0 | DB21: 0 | DC21: 0 | DD21: 0 | DE21: 0 | DF21: 0 | DG21: 0 | DH21: 0 | DI21: 0 | DJ21: 0 | DK21: 0 | DL21: 0 | DM21: 0 | DN21: 0 | DO21: 0 | DP21: 0 | DQ21: 0 | DR21: 0 | DS21: 0 | DT21: 0 | DU21: 0 | DV21: 0 | DW21: 0 | DX21: 0 | DY21: 0 | DZ21: 0 | EA21: 0 | EB21: 0 | EC21: 0 | ED21: 0 | EE21: 0 | EF21: 0 | EG21: 0 | EH21: 0 | EI21: 0 | EJ21: 0 | EK21: 0 | EL21: 0 | EM21: 0 | EN21: 0 | EO21: 0 | EP21: 0 | EQ21: 0 | ER21: 0 | ES21: 0 | ET21: 0 | EU21: 0 | EV21: 0 | EW21: 0 | EX21: 0 | EY21: 0 | EZ21: 0 | FA21: 0 | FB21: 0 | FC21: 0 | FD21: 0 | FE21: 0 | FF21: 0 | FG21: 0 | FH21: 0 | FI21: 0 | FJ21: 0 | FK21: 0 | FL21: 0 | FM21: 0 | FN21: 0 | FO21: 0 | FP21: 0 | FQ21: 0 | FR21: 0 | FS21: 0 | FT21: 0 | FU21: 0 | FV21: 0 | FW21: 0 | FX21: 0 | FY21: 0 | FZ21: 0 | GA21: 0 | GB21: 0 | GC21: 0 | GD21: 0 | GE21: 0 | GF21: 0 | GG21: 0 | GH21: 0 | GI21: 0 | GJ21: 0 | GK21: 0 | GL21: 0 | GM21: 0 | GN21: 0 | GO21: 0 | GP21: 0 | GQ21: 0 | GR21: 0 | GS21: 0 | GT21: 0 | GU21: 0 | GV21: 0 | GW21: 0 | GX21: 0 | GY21: 0 | GZ21: 0 | HA21: 0 | HB21: 0 | HC21: 0 | HD21: 0 | HE21: 0 | HF21: 0 | HG21: 0 | HH21: 0 | HI21: 0 | HJ21: 0 | HK21: 0 | HL21: 0 | HM21: 0 | HN21: 0 | HO21: 0 | HP21: 0 | HQ21: 0 | HR21: 0 | HS21: 0 | HT21: 0 | HU21: 0 | HV21: 0 | HW21: 0 | HX21: 0 | HY21: 0 | HZ21: 0 | IA21: 0 | IB21: 0 | IC21: 0 | ID21: 0 | IE21: 0 | IF21: 0 | IG21: 0 | IH21: 0 | II21: 0 | IJ21: 0 | IK21: 0 | IL21: 0 | IM21: 0 | IN21: 0 | IO21: 0 | IP21: 0
A22: 4.10 | B22: CAPEX | C22: Expropiation + UR + RCA + Payment to the State | D22: 100 | E22: 106-107 | F22: 0 | G22: 0 | H22: 30000 | I22: 0 | J22: 0 | K22: 0 | L22: 0 | M22: 0 | N22: 0 | O22: 0 | P22: 30000 | Q22: 0 | R22: 0 | S22: 0 | T22: 0 | U22: 0 | V22: 0 | W22: 0 | X22: 0 | Y22: 0 | Z22: 0 | AA22: 0 | AB22: 30000 | AC22: 0 | AD22: 243000 | AE22: 0 | AF22: 0 | AG22: 0 | AH22: 50.807463 | AI22: 719.15393 | AJ22: 777.33569 | AK22: 1692.1079 | AL22: 3853.0752 | AM22: 4076.4301 | AN22: 34390.731 | AO22: 6961.4899 | AP22: 251312.65 | AQ22: 8799.3494 | AR22: 10190.837 | AS22: 9542.1713 | AT22: 9760.509 | AU22: 10498.894 | AV22: 11836.384 | AW22: 15283.135 | AX22: 14914.955 | AY22: 15046.647 | AZ22: 48038.417 | BA22: 263484.91 | BB22: 20013.195 | BC22: 21250.076 | BD22: 19175.491 | BE22: 20858.566 | BF22: 19798.912 | BG22: 21064.33 | BH22: 20983.503 | BI22: 18887.018 | BJ22: 20792.283 | BK22: 21056.126 | BL22: 48830.637 | BM22: 14475.237 | BN22: 85691.828 | BO22: 11171.575 | BP22: 9885.5236 | BQ22: 9972.5938 | BR22: 183935.04 | BS22: 6147.7348 | BT22: 6999.4696 | BU22: 5429.2609 | BV22: 3725.8033 | BW22: 3452.5067 | BX22: 31373.717 | BY22: 520.93487 | BZ22: 278.6552 | CA22: 0 | CB22: 0 | CC22: 0 | CD22: 0 | CE22: 0 | CF22: 0 | CG22: 0 | CH22: 0 | CI22: 0 | CJ22: 0 | CK22: 0 | CL22: 0 | CM22: 0 | CN22: 0 | CO22: 0 | CP22: 0 | CQ22: 0 | CR22: 0 | CS22: 0 | CT22: 0 | CU22: 0 | CV22: 0 | CW22: 0 | CX22: 0 | CY22: 0 | CZ22: 0 | DA22: 0 | DB22: 0 | DC22: 0 | DD22: 0 | DE22: 0 | DF22: 0 | DG22: 0 | DH22: 0 | DI22: 0 | DJ22: 0 | DK22: 0 | DL22: 0 | DM22: 0 | DN22: 0 | DO22: 0 | DP22: 0 | DQ22: 0 | DR22: 0 | DS22: 0 | DT22: 0 | DU22: 0 | DV22: 0 | DW22: 0 | DX22: 0 | DY22: 0 | DZ22: 0 | EA22: 0 | EB22: 0 | EC22: 0 | ED22: 0 | EE22: 0 | EF22: 0 | EG22: 0 | EH22: 0 | EI22: 0 | EJ22: 0 | EK22: 0 | EL22: 0 | EM22: 0 | EN22: 0 | EO22: 0 | EP22: 0 | EQ22: 0 | ER22: 0 | ES22: 0 | ET22: 0 | EU22: 0 | EV22: 0 | EW22: 0 | EX22: 0 | EY22: 0 | EZ22: 0 | FA22: 0 | FB22: 0 | FC22: 0 | FD22: 0 | FE22: 0 | FF22: 0 | FG22: 0 | FH22: 0 | FI22: 0 | FJ22: 0 | FK22: 0 | FL22: 0 | FM22: 0 | FN22: 0 | FO22: 0 | FP22: 0 | FQ22: 0 | FR22: 0 | FS22: 0 | FT22: 0 | FU22: 0 | FV22: 0 | FW22: 0 | FX22: 0 | FY22: 0 | FZ22: 0 | GA22: 0 | GB22: 0 | GC22: 0 | GD22: 0 | GE22: 0 | GF22: 0 | GG22: 0 | GH22: 0 | GI22: 0 | GJ22: 0 | GK22: 0 | GL22: 0 | GM22: 0 | GN22: 0 | GO22: 0 | GP22: 0 | GQ22: 0 | GR22: 0 | GS22: 0 | GT22: 0 | GU22: 0 | GV22: 0 | GW22: 0 | GX22: 0 | GY22: 0 | GZ22: 0 | HA22: 0 | HB22: 0 | HC22: 0 | HD22: 0 | HE22: 0 | HF22: 0 | HG22: 0 | HH22: 0 | HI22: 0 | HJ22: 0 | HK22: 0 | HL22: 0 | HM22: 0 | HN22: 0 | HO22: 0 | HP22: 0 | HQ22: 0 | HR22: 0 | HS22: 0 | HT22: 0 | HU22: 0 | HV22: 0 | HW22: 0 | HX22: 0 | HY22: 0 | HZ22: 0 | IA22: 0 | IB22: 0 | IC22: 0 | ID22: 0 | IE22: 0 | IF22: 0 | IG22: 0 | IH22: 0 | II22: 0 | IJ22: 0 | IK22: 0 | IL22: 0 | IM22: 0 | IN22: 0 | IO22: 0 | IP22: 0
A23: 1.1 | B23: OPEX | C23: Major Maintenance（up to Feb 2032 ) (Mes 1 a Mes 131) | D23: 200 | E23: 202 | F23: 0 | G23: 0 | H23: 0 | I23: 0 | J23: 0 | K23: 0 | L23: 0 | M23: 0 | N23: 0 | O23: 0 | P23: 0 | Q23: 0 | R23: 0 | S23: 0 | T23: 0 | U23: 0 | V23: 570.08342 | W23: 271.27318 | X23: 0 | Y23: 0 | Z23: 30314.041 | AA23: 15131.712 | AB23: 11904.813 | AC23: 0 | AD23: 0 | AE23: 37714.435 | AF23: 0 | AG23: 31909.397 | AH23: 0 | AI23: 0 | AJ23: 22709.663 | AK23: 69387.091 | AL23: 13561.699 | AM23: 42706.419 | AN23: 50249.179 | AO23: 92186.647 | AP23: 27800.643 | AQ23: 13789.104 | AR23: 5975.3888 | AS23: 16019.595 | AT23: 6255.7402 | AU23: 18450.906 | AV23: 6155.6493 | AW23: 39531.198 | AX23: 81042.49 | AY23: 32628.36 | AZ23: 6516.9 | BA23: 10043 | BB23: 10188 | BC23: 18452 | BD23: 49662 | BE23: 0 | BF23: 0 | BG23: 0 | BH23: 47796 | BI23: 0 | BJ23: 49005 | BK23: 48922 | BL23: 0 | BM23: 0 | BN23: 43370 | BO23: 0 | BP23: 0 | BQ23: 14106 | BR23: 0 | BS23: 20507 | BT23: 11000 | BU23: 25000 | BV23: 31338.333 | BW23: 23000 | BX23: 9781 | BY23: 20000 | BZ23: 31000 | CA23: 0 | CB23: 0 | CC23: 0 | CD23: 0 | CE23: 0 | CF23: 5000 | CG23: 45000 | CH23: 34000 | CI23: 20000 | CJ23: 0 | CK23: 0 | CL23: 0 | CR23: 5000 | CS23: 40333.333 | CT23: 25333.333 | CU23: 20000 | CV23: 10000 | CW23: 10000 | CX23: 0 | CY23: 0 | CZ23: 0 | DA23: 0 | DB23: 0 | DC23: 0 | DD23: 5000 | DE23: 40333.333 | DF23: 25333.333 | DG23: 0 | DH23: 10000 | DI23: 25333.333 | DJ23: 5333.3333 | DK23: 0 | DL23: 0 | DM23: 0 | DN23: 0 | DO23: 0 | DP23: 6000 | DQ23: 20000 | DR23: 20000 | DS23: 20000 | DT23: 25333.333 | DU23: 6090 | DV23: 0 | DW23: 6000 | DX23: 0 | DY23: 0 | DZ23: 0 | EA23: 0 | EB23: 5000 | EC23: 20000 | ED23: 20000 | EE23: 0 | EF23: 15333.333 | EG23: 15333.333
A24: 1.1 | B24: OPEX | C24: Major Maintenance（up to Feb 2035 ) (Mes 132 a Mes 167) | D24: 200 | E24: 202 | CM24: 0 | CN24: 0 | CO24: 0 | CP24: 0 | CQ24: 0 | EI24: 0 | EJ24: 0 | EK24: 0 | EL24: 0 | EM24: 0 | EN24: 5000 | EO24: 20000 | EP24: 0 | EQ24: 15963 | ER24: 10000 | ES24: 10000 | ET24: 0 | EU24: 0 | EV24: 0 | EW24: 0 | EX24: 0 | EY24: 0 | EZ24: 5000 | FA24: 10000 | FB24: 13108 | FC24: 0 | FD24: 3000 | FE24: 8614.74 | FF24: 10000 | FG24: 15000 | FH24: 20000 | FI24: 9000 | FJ24: 0 | FK24: 0 | FL24: 1500 | FM24: 1500 | FN24: 1500 | FO24: 12000 | FP24: 12000 | FQ24: 8000
A25: 1.1 | B25: OPEX | C25: Major Maintenance（up to March 2045 ) (Mes 168 a Mes 289) | D25: 200 | E25: 202 | FR25: 10000 | FS25: 15000 | FT25: 20000 | FU25: 9000 | FV25: 0 | FW25: 0 | FX25: 1500 | FY25: 11500 | FZ25: 11500 | GA25: 32000 | GB25: 12000 | GC25: 8000 | GD25: 10000 | GE25: 15000 | GF25: 20000 | GG25: 9000 | GH25: 0 | GI25: 0 | GJ25: 1500 | GK25: 11500 | GL25: 11500 | GM25: 32000 | GN25: 12000 | GO25: 8000 | GP25: 10000 | GQ25: 15000 | GR25: 20000 | GS25: 9000 | GT25: 0 | GU25: 0 | GV25: 1500 | GW25: 11500 | GX25: 11500 | GY25: 32000 | GZ25: 12000 | HA25: 8000 | HB25: 10000 | HC25: 15000 | HD25: 20000 | HE25: 9000 | HF25: 0 | HG25: 0 | HH25: 1500 | HI25: 11500 | HJ25: 11500 | HK25: 32000 | HL25: 12000 | HM25: 8000 | HN25: 10000 | HO25: 15000 | HP25: 20000 | HQ25: 9000 | HR25: 0 | HS25: 0 | HT25: 1500 | HU25: 11500 | HV25: 11500 | HW25: 32000 | HX25: 12000 | HY25: 8000 | HZ25: 10000 | IA25: 15000 | IB25: 20000 | IC25: 9000 | ID25: 0 | IE25: 0 | IF25: 1500 | IG25: 11500 | IH25: 11500 | II25: 32000 | IJ25: 12000 | IK25: 8000 | IL25: 10000 | IM25: 15000 | IN25: 20000 | IO25: 9000 | IP25: 0 | IQ25: 0 | IR25: 1500 | IS25: 11500 | IT25: 11500 | IU25: 32000 | IV25: 12000 | IW25: 8000 | IX25: 10000 | IY25: 15000 | IZ25: 20000 | JA25: 9000 | JB25: 0 | JC25: 0 | JD25: 1500 | JE25: 11500 | JF25: 11500 | JG25: 32000 | JH25: 12000 | JI25: 8000 | JJ25: 10000 | JK25: 15000 | JL25: 20000 | JM25: 9000 | JN25: 0 | JO25: 0 | JP25: 1500 | JQ25: 11500 | JR25: 11500 | JS25: 32000 | JT25: 12000 | JU25: 8000 | JV25: 10000 | JW25: 15000 | JX25: 20000 | JY25: 9000 | JZ25: 0 | KA25: 0 | KB25: 1500 | KC25: 11500 | KD25: 11500 | KE25: 32000 | KF25: 12000 | KG25: 8000 | KH25: 10000
A26: 1.4.2 | B26: OPEX | C26: Major Maintenance of Toll Plazas and Service Areas（Jan 2025 to Mar 2034） | D26: 200 | E26: 206 | BH26: 4000 | BI26: 4000 | BJ26: 4000 | BK26: 4000 | BL26: 4000 | BM26: 4000 | BN26: 4000 | BT26: 4000 | BU26: 4000 | BV26: 4000 | BW26: 4000 | BX26: 4000 | BY26: 4000 | BZ26: 4000 | CF26: 4000 | CG26: 4000 | CH26: 4000 | CI26: 4000 | CJ26: 4000 | CK26: 4000 | CL26: 4000 | CR26: 3000 | CS26: 3000 | CT26: 3000 | CU26: 3000 | CV26: 3000 | CW26: 3000 | DD26: 3000 | DE26: 3000 | DF26: 3000 | DG26: 3000 | DH26: 3000 | DI26: 3000 | DP26: 3000 | DQ26: 3000 | DR26: 3000 | DS26: 3000 | DT26: 3000 | DU26: 3000 | EB26: 3000 | EC26: 3000 | ED26: 3000 | EE26: 3000 | EO26: 3000 | EP26: 570.45
A27: 1.5 | B27: OPEX | C27: Major Maintenance costs to achieve the road's residual value（Final Payment） | D27: 200 | E27: 202 | ES27: 23664 | ET27: 23664 | EU27: 23664 | FA27: 23664 | FB27: 23664 | FC27: 23664 | FE27: 23664 | FF27: 28283
A28: 1.4.3 | B28: OPEX | C28: Emergencies (up to March 2045) | D28: 200 | E28: 205 | F28: 0 | G28: 0 | H28: 0 | I28: 0 | K28: 0 | L28: 0 | M28: 0 | N28: 0 | AB28: 0 | AC28: 2200 | AK28: 0 | AM28: 0 | AN28: 0 | AR28: 0 | AT28: 0 | AV28: 0 | AW28: 16000 | AX28: 5000 | BJ28: 5000 | BV28: 5000 | CH28: 5000 | CT28: 5000 | DF28: 5000 | ED28: 5000 | EP28: 5000 | FB28: 5000 | FN28: 5000 | FZ28: 5000 | GL28: 5000 | GX28: 5000 | HJ28: 5000 | HV28: 5000 | IH28: 5000 | IT28: 5000 | JF28: 5000 | JR28: 5000 | KD28: 5000
A29: 1.2 | B29: OPEX | C29: Routine Maintenance（up to March 2028) (Mes 1 a Mes 85) | D29: 200 | E29: 201 | G29: 8500 | H29: 8500 | I29: 8500 | J29: 8500 | K29: 8500 | L29: 8500 | M29: 8500 | N29: 8500 | O29: 8500 | P29: 8500 | Q29: 8500 | R29: 8500 | S29: 8500 | T29: 8500 | U29: 8500 | V29: 8500 | W29: 8500 | X29: 8500 | Y29: 8500 | Z29: 8500 | AA29: 8500 | AB29: 8500 | AC29: 8500 | AD29: 8500 | AE29: 8500 | AF29: 8500 | AG29: 8500 | AH29: 8500 | AI29: 8500 | AJ29: 8500 | AK29: 8500 | AL29: 8500 | AM29: 8500 | AN29: 8500 | AO29: 8500 | AP29: 8500 | AQ29: 8500 | AR29: 8500 | AS29: 8500 | AT29: 8500 | AU29: 8500 | AV29: 8500 | AW29: 8500 | AX29: 8500 | AY29: 8500 | AZ29: 8500 | BA29: 8500 | BB29: 8500 | BC29: 8500 | BD29: 8500 | BE29: 8500 | BF29: 8500 | BG29: 8500 | BH29: 8500 | BI29: 8500 | BJ29: 8500 | BK29: 8500 | BL29: 8500 | BM29: 8500 | BN29: 8500 | BO29: 8500 | BP29: 8500 | BQ29: 8500 | BR29: 8500 | BS29: 8500 | BT29: 8500 | BU29: 8500 | BV29: 8500 | BW29: 8500 | BX29: 8500 | BY29: 8500 | BZ29: 8500 | CA29: 7430 | CB29: 7430 | CC29: 7430 | CD29: 7430 | CE29: 7430 | CF29: 7430 | CG29: 7430 | CH29: 7430 | CI29: 7430 | CJ29: 7430 | CK29: 7430 | CL29: 7430
A30: 1.2 | B30: OPEX | C30: Routine Maintenance（April 2028 up to March 2034) (Mes 86 a Mes 157) | D30: 200 | E30: 201 | CM30: 10000 | CN30: 10000 | CO30: 10000 | CP30: 10000 | CQ30: 10000 | CR30: 10000 | CS30: 10000 | CT30: 10000 | CU30: 10000 | CV30: 10000 | CW30: 10000 | CX30: 10000 | CY30: 10000 | CZ30: 10000 | DA30: 10000 | DB30: 10000 | DC30: 10000 | DD30: 10000 | DE30: 10000 | DF30: 10000 | DG30: 10000 | DH30: 10000 | DI30: 10000 | DJ30: 10000 | DK30: 10000 | DL30: 10000 | DM30: 10000 | DN30: 10000 | DO30: 10000 | DP30: 10000 | DQ30: 10000 | DR30: 10000 | DS30: 10000 | DT30: 10000 | DU30: 10000 | DV30: 10000 | DW30: 10000 | DX30: 10000 | DY30: 10000 | DZ30: 10000 | EA30: 10000 | EB30: 10000 | EC30: 10000 | ED30: 10000 | EE30: 10000 | EF30: 10000 | EG30: 10000 | EH30: 10000 | EI30: 10000 | EJ30: 10000 | EK30: 10000 | EL30: 10000 | EM30: 10000 | EN30: 10000 | EO30: 10000 | EP30: 10000 | EQ30: 10000 | ER30: 10000 | ES30: 10000 | ET30: 10000 | EU30: 10000 | EV30: 10000 | EW30: 10000 | EX30: 10000 | EY30: 10000 | EZ30: 10000 | FA30: 10000 | FB30: 10000 | FC30: 10000 | FD30: 10000 | FE30: 10000 | FF30: 10000
A31: 1.2 | B31: OPEX | C31: Routine Maintenance（April 2034up to March 2045) (Mes 158 a Mes 289) | D31: 200 | E31: 201 | FG31: 10000 | FH31: 10000 | FI31: 10000 | FJ31: 10000 | FK31: 10000 | FL31: 10000 | FM31: 10000 | FN31: 10000 | FO31: 10000 | FP31: 10000 | FQ31: 10000 | FR31: 10000 | FS31: 10000 | FT31: 10000 | FU31: 10000 | FV31: 10000 | FW31: 10000 | FX31: 10000 | FY31: 10000 | FZ31: 10000 | GA31: 10000 | GB31: 10000 | GC31: 10000 | GD31: 10000 | GE31: 10000 | GF31: 10000 | GG31: 10000 | GH31: 10000 | GI31: 10000 | GJ31: 10000 | GK31: 10000 | GL31: 10000 | GM31: 10000 | GN31: 10000 | GO31: 10000 | GP31: 10000 | GQ31: 10000 | GR31: 10000 | GS31: 10000 | GT31: 10000 | GU31: 10000 | GV31: 10000 | GW31: 10000 | GX31: 10000 | GY31: 10000 | GZ31: 10000 | HA31: 10000 | HB31: 10000 | HC31: 10000 | HD31: 10000 | HE31: 10000 | HF31: 10000 | HG31: 10000 | HH31: 10000 | HI31: 10000 | HJ31: 10000 | HK31: 10000 | HL31: 10000 | HM31: 10000 | HN31: 10000 | HO31: 10000 | HP31: 10000 | HQ31: 10000 | HR31: 10000 | HS31: 10000 | HT31: 10000 | HU31: 10000 | HV31: 10000 | HW31: 10000 | HX31: 10000 | HY31: 10000 | HZ31: 10000 | IA31: 10000 | IB31: 10000 | IC31: 10000 | ID31: 10000 | IE31: 10000 | IF31: 10000 | IG31: 10000 | IH31: 10000 | II31: 10000 | IJ31: 10000 | IK31: 10000 | IL31: 10000 | IM31: 10000 | IN31: 10000 | IO31: 10000 | IP31: 10000 | IQ31: 10000 | IR31: 10000 | IS31: 10000 | IT31: 10000 | IU31: 10000 | IV31: 10000 | IW31: 10000 | IX31: 10000 | IY31: 10000 | IZ31: 10000 | JA31: 10000 | JB31: 10000 | JC31: 10000 | JD31: 10000 | JE31: 10000 | JF31: 10000 | JG31: 10000 | JH31: 10000 | JI31: 10000 | JJ31: 10000 | JK31: 10000 | JL31: 10000 | JM31: 10000 | JN31: 10000 | JO31: 10000 | JP31: 10000 | JQ31: 10000 | JR31: 10000 | JS31: 10000 | JT31: 10000 | JU31: 10000 | JV31: 10000 | JW31: 10000 | JX31: 10000 | JY31: 10000 | JZ31: 10000 | KA31: 10000 | KB31: 10000 | KC31: 10000 | KD31: 10000 | KE31: 10000 | KF31: 10000 | KG31: 10000 | KH31: 10000
A32: 1.3 | B32: OPEX | C32: Additional Routine Maintenance (up to March 2034) | D32: 200 | E32: 205 | K32: 1144.8999 | P32: 2436.9758 | Q32: 101.37006 | R32: 276.00733 | S32: 26.035515 | T32: 326.172 | U32: 1265.54 | V32: 358.54387 | W32: 2328.6759 | X32: 1096.4971 | Y32: 31.82169 | Z32: 64.3281 | AA32: 1202.4411 | AB32: 945.0935 | AD32: 1527.7327 | AE32: 2015.2047 | AF32: 3007.7093 | AG32: 1768.2333 | AH32: 1603.6789 | AK32: 2635.431
A33: 1.4.1 | B33: OPEX | C33: Routine Maintenance of Toll Plazas and Service Areas（Jan 2025 to Mar 2034） | D33: 200 | E33: 206 | BA33: 1600 | BB33: 1600 | BC33: 1600 | BD33: 1600 | BE33: 1600 | BF33: 1600 | BG33: 1500 | BH33: 1500 | BI33: 1500 | BJ33: 1500 | BK33: 1500 | BL33: 1500 | BM33: 1500 | BN33: 1500 | BO33: 1500 | BP33: 1500 | BQ33: 1500 | BR33: 1500 | BS33: 1500 | BT33: 1500 | BU33: 1500 | BV33: 1500 | BW33: 1500 | BX33: 1500 | BY33: 1500 | BZ33: 1500 | CA33: 1500 | CB33: 1500 | CC33: 1500 | CD33: 1500 | CE33: 1500 | CF33: 1500 | CG33: 1500 | CH33: 1500 | CI33: 1500 | CJ33: 1500 | CK33: 1500 | CL33: 1500 | CM33: 1500 | CN33: 1500 | CO33: 1500 | CP33: 1500 | CQ33: 1500 | CR33: 1500 | CS33: 1500 | CT33: 1500 | CU33: 1500 | CV33: 1500 | CW33: 1500 | CX33: 1500 | CY33: 1500 | CZ33: 1500 | DA33: 1500 | DB33: 1500 | DC33: 1500 | DD33: 1500 | DE33: 1500 | DF33: 1500 | DG33: 1500 | DH33: 1500 | DI33: 1500 | DJ33: 1500 | DK33: 1500 | DL33: 1500 | DM33: 1500 | DN33: 1500 | DO33: 1500 | DP33: 1500 | DQ33: 1500 | DR33: 1500 | DS33: 1500 | DT33: 1500 | DU33: 1500 | DV33: 1500 | DW33: 1500 | DX33: 1500 | DY33: 1500 | DZ33: 1500 | EA33: 1500 | EB33: 1500 | EC33: 1500 | ED33: 1500 | EE33: 1500 | EF33: 1500 | EG33: 1500 | EH33: 1500 | EI33: 1500 | EJ33: 1500 | EK33: 1500 | EL33: 1500 | EM33: 1500 | EN33: 1500 | EO33: 1500 | EP33: 1500 | EQ33: 1500 | ER33: 1500 | ES33: 1500 | ET33: 1500 | EU33: 1500 | EV33: 1500 | EW33: 1500 | EX33: 1500 | EY33: 1500 | EZ33: 1500 | FA33: 1500 | FB33: 1500 | FC33: 1500 | FD33: 1500 | FE33: 1500 | FF33: 1500
A34: 1.4.4 | B34: OPEX | C34: Testing advisor SPV cost (up to March 2045) | D34: 200 | E34: 204 | F34: 0 | G34: 0 | H34: 0 | I34: 0 | J34: 0 | K34: 1106.2639 | L34: 0 | M34: 0 | N34: 0 | O34: 1505.8896 | P34: 1590 | Q34: 0 | R34: 1429 | S34: 208 | T34: 0 | U34: 0 | V34: 0 | W34: 0 | X34: 0 | Y34: 1869 | Z34: 1869 | AA34: 190 | AB34: 0 | AC34: 0 | AD34: 0 | AE34: 0 | AF34: 0 | AG34: 0 | AH34: 0 | AI34: 0 | AJ34: 3738 | AK34: 0 | AL34: 0 | AM34: 0 | AN34: 0 | AO34: 0 | AP34: 0 | AQ34: 0 | AR34: 0 | AS34: 0 | AT34: 0 | AU34: 0 | AV34: 0 | AW34: 0 | AX34: 0 | AZ34: 2874 | BA34: 708 | BJ34: 3738 | BV34: 3738 | CH34: 3738 | CT34: 3738 | DF34: 3738 | DR34: 3738 | ED34: 3738 | EP34: 3738 | FB34: 3738 | FN34: 3738 | FZ34: 3738 | GL34: 3738 | GX34: 3738 | HJ34: 3738 | HV34: 3738 | IH34: 3738 | IT34: 3738 | JF34: 3738 | JR34: 3738 | KD34: 3738
A35: 2.3.1 | B35: OPEX | C35: Routine Maintenance of Toll Plazas and Service Areas (Including ITS Maintenance) | D35: 300 | E35: 301 | F35: 2301.1395 | G35: 3026.102 | H35: 3249.1984 | I35: 4056.5199 | J35: 8196.9562 | K35: 4233.2066 | L35: 3318.2639 | M35: 3133.8369 | N35: 3257.4388 | O35: 3332.0656 | P35: 5841.7708 | Q35: 6929.743 | R35: 5393.5846 | S35: 4195.0764 | T35: 4192.2145 | U35: 4133.1579 | V35: 4817.737 | W35: 4290.7267 | X35: 5660.5802 | Y35: 4486.49 | Z35: 3981.5162 | AA35: 3921.9664 | AB35: 4566.8425 | AC35: 5147.6907 | AD35: 4244.9031 | AE35: 5058.0704 | AF35: 5504.2831 | AG35: 6456.8717 | AH35: 6613.6794 | AI35: 5745.2522 | AJ35: 4602.6879 | AK35: 6850.4972 | AL35: 5149.2335 | AM35: 3787.3943 | AN35: 5160.4009 | AO35: 4290.328 | AP35: 4776.8851 | AQ35: 4121.1151 | AR35: 4027.7734 | AS35: 3223.5451 | AT35: 3646.6951 | AU35: 3967.9051 | AV35: 3678.2651 | AW35: 4055.51 | AX35: 4055.51 | AY35: 5017.19 | AZ35: 3417 | BA35: 3417.19 | BB35: 3417.19 | BC35: 3417.19 | BD35: 3417.19 | BE35: 3417.19 | BF35: 3417.19 | BG35: 3000 | BH35: 3000 | BI35: 3000 | BJ35: 3000 | BK35: 3000 | BL35: 3000 | BM35: 3000 | BN35: 3000 | BO35: 3000 | BP35: 3000 | BQ35: 3000 | BR35: 3000 | BS35: 2500 | BT35: 2500 | BU35: 2500 | BV35: 2500 | BW35: 2500 | BX35: 2500 | BY35: 2500 | BZ35: 2500 | CA35: 2500 | CB35: 2500 | CC35: 2500 | CD35: 2500 | CE35: 2500 | CF35: 2500 | CG35: 2500 | CH35: 2500 | CI35: 2500 | CJ35: 2500 | CK35: 2500 | CL35: 2500 | CM35: 2500 | CN35: 2500 | CO35: 2500 | CP35: 2500 | CQ35: 2500 | CR35: 2500 | CS35: 2500 | CT35: 2500 | CU35: 2500 | CV35: 2500 | CW35: 2500 | CX35: 2500 | CY35: 2500 | CZ35: 2500 | DA35: 2500 | DB35: 2500 | DC35: 2500 | DD35: 2500 | DE35: 2500 | DF35: 2500 | DG35: 2500 | DH35: 2500 | DI35: 2500 | DJ35: 3000 | DK35: 3000 | DL35: 3000 | DM35: 3000 | DN35: 3000 | DO35: 3000 | DP35: 3000 | DQ35: 3000 | DR35: 3000 | DS35: 3000 | DT35: 3000 | DU35: 3000 | DV35: 3000 | DW35: 3000 | DX35: 3000 | DY35: 3000 | DZ35: 3000 | EA35: 3000 | EB35: 3000 | EC35: 3000 | ED35: 3000 | EE35: 3000 | EF35: 3000 | EG35: 3000 | EH35: 3000 | EI35: 3000 | EJ35: 3000 | EK35: 3000 | EL35: 3000 | EM35: 3000 | EN35: 3000 | EO35: 3000 | EP35: 3000 | EQ35: 3000 | ER35: 3000 | ES35: 3000 | ET35: 3000 | EU35: 3000 | EV35: 3000 | EW35: 3000 | EX35: 3000 | EY35: 3000 | EZ35: 3000 | FA35: 3000 | FB35: 3000 | FC35: 3000 | FD35: 3000 | FE35: 3000 | FF35: 3000 | FG35: 3000 | FH35: 4100 | FI35: 4100 | FJ35: 4100 | FK35: 4100 | FL35: 4100 | FM35: 4100 | FN35: 4100 | FO35: 4100 | FP35: 4255 | FQ35: 4255 | FR35: 4255 | FS35: 4255 | FT35: 4255 | FU35: 4255 | FV35: 4255 | FW35: 4255 | FX35: 4255 | FY35: 4755.35 | FZ35: 4755.35 | GA35: 4755.35 | GB35: 4755.35 | GC35: 4755.35 | GD35: 4755.35 | GE35: 4755.35 | GF35: 4755.35 | GG35: 4755.35 | GH35: 4755.35 | GI35: 4755.35 | GJ35: 4755.35 | GK35: 4755.35 | GL35: 4755.35 | GM35: 4755.35 | GN35: 4755.35 | GO35: 4755.35 | GP35: 4755.35 | GQ35: 4755.35 | GR35: 4755.35 | GS35: 4755.35 | GT35: 4755.35 | GU35: 4755.35 | GV35: 4755.35 | GW35: 4755.35 | GX35: 4755.35 | GY35: 4755.35 | GZ35: 4755.35 | HA35: 4755.35 | HB35: 4755.35 | HC35: 4755.35 | HD35: 4755.35 | HE35: 4755.35 | HF35: 4755.35 | HG35: 4755.35 | HH35: 4755.35 | HI35: 4755.35 | HJ35: 4755.35 | HK35: 4755.35 | HL35: 4755.35 | HM35: 4755.35 | HN35: 4755.35 | HO35: 4755.35 | HP35: 4755.35 | HQ35: 4755.35 | HR35: 4755.35 | HS35: 4755.35 | HT35: 4755.35 | HU35: 4755.35 | HV35: 4755.35 | HW35: 4755.35 | HX35: 4755.35 | HY35: 4755.35 | HZ35: 4755.35 | IA35: 4755.35 | IB35: 4755.35 | IC35: 4755.35 | ID35: 4755.35 | IE35: 4755.35 | IF35: 4755.35 | IG35: 4755.35 | IH35: 4755.35 | II35: 4755.35 | IJ35: 4755.35 | IK35: 4755.35 | IL35: 4755.35 | IM35: 4755.35 | IN35: 4755.35 | IO35: 4755.35 | IP35: 4755.35 | IQ35: 4755.35 | IR35: 4755.35 | IS35: 4755.35 | IT35: 4755.35 | IU35: 4755.35 | IV35: 4755.35 | IW35: 4755.35 | IX35: 4755.35 | IY35: 4755.35 | IZ35: 4755.35 | JA35: 4755.35 | JB35: 4755.35 | JC35: 4755.35 | JD35: 4755.35 | JE35: 4755.35 | JF35: 4755.35 | JG35: 4755.35 | JH35: 4755.35 | JI35: 4755.35 | JJ35: 4755.35 | JK35: 4755.35 | JL35: 4755.35 | JM35: 4755.35 | JN35: 4755.35 | JO35: 4755.35 | JP35: 4755.35 | JQ35: 4755.35 | JR35: 4755.35 | JS35: 4755.35 | JT35: 4755.35 | JU35: 4755.35 | JV35: 4755.35 | JW35: 4755.35 | JX35: 4755.35 | JY35: 4755.35 | JZ35: 4755.35 | KA35: 4755.35 | KB35: 4755.35 | KC35: 4755.35 | KD35: 4755.35 | KE35: 4755.35 | KF35: 4755.35 | KG35: 4755.35 | KH35: 4755.35
A36: 2.1 | B36: OPEX | C36: Operation ( up to March,2045) | D36: 300 | E36: 301
A37: 2.1.1 | B37: OPEX | C37: Manual Toll Collection + Roadside Assistance + Traffic Management + Cash Transport + Security Services, etc. | D37: 300 | E37: 301 | F37: 47139 | G37: 16525.25 | H37: 16525.25 | I37: 16525.25 | J37: 16525.25 | K37: 16525.25 | L37: 16525.25 | M37: 16525.25 | N37: 21525.25 | O37: 16573.567 | P37: 16573.567 | Q37: 16573.567 | R37: 17072.745 | S37: 17072.745 | T37: 17072.745 | U37: 17072.745 | V37: 17072.744 | W37: 17072.744 | X37: 17072.745 | Y37: 17032.745 | Z37: 17072.745 | AA37: 15794.916 | AB37: 17072.74 | AC37: 17072.74 | AD37: 17092.02 | AE37: 17092.02 | AF37: 17092.02 | AG37: 17092.02 | AH37: 17092.02 | AI37: 17092.02 | AJ37: 17092.02 | AK37: 17092.02 | AL37: 17092.02 | AM37: 17092.02 | AN37: 17600.57 | AO37: 17991.6 | AP37: 18303.44 | AQ37: 18303.44 | AR37: 18303.44 | AS37: 18303.44 | AT37: 18303.44 | AU37: 18303.44 | AV37: 18303.44 | AW37: 18303.44 | AX37: 18303.44 | AY37: 18303.44 | AZ37: 18955 | BA37: 18955 | BB37: 18955 | BC37: 18955 | BD37: 18955 | BE37: 18955 | BF37: 18955 | BG37: 18955 | BH37: 16917 | BI37: 16917 | BJ37: 16917 | BK37: 16917 | BL37: 16917 | BM37: 16917 | BN37: 16917 | BO37: 16917 | BP37: 16917 | BQ37: 16917 | BR37: 15000 | BS37: 15000 | BT37: 15000 | BU37: 15000 | BV37: 15000 | BW37: 15000 | BX37: 15000 | BY37: 15000 | BZ37: 15000 | CA37: 15000 | CB37: 15000 | CC37: 15000 | CD37: 15000 | CE37: 15000 | CF37: 15000 | CG37: 15000 | CH37: 15000 | CI37: 15000 | CJ37: 15000 | CK37: 15000 | CL37: 15000 | CM37: 15000 | CN37: 15000 | CO37: 15000 | CP37: 15000 | CQ37: 15000 | CR37: 15000 | CS37: 15000 | CT37: 15000 | CU37: 15000 | CV37: 15000 | CW37: 15000 | CX37: 15000 | CY37: 15000 | CZ37: 15000 | DA37: 15000 | DB37: 15000 | DC37: 15000 | DD37: 15000 | DE37: 15000 | DF37: 15000 | DG37: 15000 | DH37: 15000 | DI37: 15000 | DJ37: 10998 | DK37: 10998 | DL37: 11058 | DM37: 11058 | DN37: 11058 | DO37: 11058 | DP37: 11058 | DQ37: 11058 | DR37: 11058 | DS37: 11058 | DT37: 11058 | DU37: 11058 | DV37: 11058 | DW37: 11058 | DX37: 11058 | DY37: 11058 | DZ37: 11058 | EA37: 11058 | EB37: 11058 | EC37: 11058 | ED37: 11058 | EE37: 11058 | EF37: 11058 | EG37: 11058 | EH37: 11058 | EI37: 11058 | EJ37: 11058 | EK37: 11058 | EL37: 11058 | EM37: 11058 | EN37: 11058 | EO37: 11058 | EP37: 11058 | EQ37: 11058 | ER37: 11058 | ES37: 11058 | ET37: 11058 | EU37: 11058 | EV37: 11058 | EW37: 11058 | EX37: 11058 | EY37: 11058 | EZ37: 11058 | FA37: 11058 | FB37: 11058 | FC37: 11058 | FD37: 11058 | FE37: 11058 | FF37: 11058 | FG37: 11058 | FH37: 11058 | FI37: 11058 | FJ37: 11058 | FK37: 11058 | FL37: 11058 | FM37: 11058 | FN37: 11058 | FO37: 11058 | FP37: 11058 | FQ37: 11058 | FR37: 11058 | FS37: 11058 | FT37: 11058 | FU37: 11058 | FV37: 11058 | FW37: 11058 | FX37: 11058 | FY37: 11058 | FZ37: 11058 | GA37: 11058 | GB37: 11058 | GC37: 11058 | GD37: 11058 | GE37: 11058 | GF37: 11058 | GG37: 11058 | GH37: 11058 | GI37: 11058 | GJ37: 11058 | GK37: 11058 | GL37: 11058 | GM37: 11058 | GN37: 11058 | GO37: 11058 | GP37: 11058 | GQ37: 11058 | GR37: 11058 | GS37: 11058 | GT37: 11058 | GU37: 11058 | GV37: 11058 | GW37: 11058 | GX37: 11058 | GY37: 11058 | GZ37: 11058 | HA37: 11058 | HB37: 11058 | HC37: 11058 | HD37: 11058 | HE37: 11058 | HF37: 11058 | HG37: 11058 | HH37: 11058 | HI37: 11058 | HJ37: 11058 | HK37: 11058 | HL37: 11058 | HM37: 11058 | HN37: 11058 | HO37: 11058 | HP37: 11058 | HQ37: 11058 | HR37: 11058 | HS37: 11058 | HT37: 11058 | HU37: 11058 | HV37: 11058 | HW37: 11058 | HX37: 11058 | HY37: 11058 | HZ37: 11058 | IA37: 11058 | IB37: 11058 | IC37: 11058 | ID37: 11058 | IE37: 11058 | IF37: 11058 | IG37: 11058 | IH37: 11058 | II37: 11058 | IJ37: 11058 | IK37: 11058 | IL37: 11058 | IM37: 11058 | IN37: 11058 | IO37: 11058 | IP37: 11058 | IQ37: 11058 | IR37: 11058 | IS37: 11058 | IT37: 11058 | IU37: 11058 | IV37: 11058 | IW37: 11058 | IX37: 11058 | IY37: 11058 | IZ37: 11058 | JA37: 11058 | JB37: 11058 | JC37: 11058 | JD37: 11058 | JE37: 11058 | JF37: 11058 | JG37: 11058 | JH37: 11058 | JI37: 11058 | JJ37: 11058 | JK37: 11058 | JL37: 11058 | JM37: 11058 | JN37: 11058 | JO37: 11058 | JP37: 11058 | JQ37: 11058 | JR37: 11058 | JS37: 11058 | JT37: 11058 | JU37: 11058 | JV37: 11058 | JW37: 11058 | JX37: 11058 | JY37: 11058 | JZ37: 11058 | KA37: 11058 | KB37: 11058 | KC37: 11058 | KD37: 11058 | KE37: 11058 | KF37: 11058 | KG37: 11058 | KH37: 11058
A38: 2.1.2 | B38: OPEX | C38: ITS and Other Communication Services + Utility Bills (Water and Electricity) + Road Debris Clearance | D38: 300 | E38: 301 | F38: 0 | G38: 644.17194 | H38: 1365.4606 | I38: 212.68886 | J38: 3344.2777 | K38: 1704.9787 | L38: 5634.6651 | M38: 1037.0401 | N38: 1207.2127 | O38: 2071.7801 | P38: 874.91719 | Q38: 1327.9017 | R38: 1356.4192 | S38: 946.33173 | T38: 3562.85 | U38: 8981.0394 | V38: 1529.0229 | W38: 4023.9765 | X38: 1389.8375 | Y38: 944.13405 | Z38: 727.59655 | AA38: 1796.7919 | AB38: 962.80416 | AC38: 1519.7459 | AD38: 2139.6392 | AE38: 1152.3192 | AF38: 742.37937 | AG38: 1486.4034 | AH38: 1793.5891 | AI38: 2001.5424 | AJ38: 2716.6045 | AK38: 1119.0733 | AL38: 1085.0096 | AM38: 921.49037 | AN38: 1407.8865 | AO38: 1315.7379 | AP38: 1795.1573 | AQ38: 1840.5378 | AR38: 1514.798 | AS38: 2096.4331 | AT38: 1340.8819 | AU38: 1724.1572 | AV38: 2065.3932 | AW38: 1720.5357 | AX38: 334.558 | AY38: 1587.6032 | AZ38: 1588 | BA38: 1588 | BB38: 1588 | BC38: 1588 | BD38: 1588 | BE38: 1588 | BF38: 1588 | BG38: 1588 | BH38: 1588 | BI38: 1588 | BJ38: 1588 | BK38: 1588 | BL38: 1588 | BM38: 1588 | BN38: 1588 | BO38: 1588 | BP38: 1588 | BQ38: 1588 | BR38: 1588 | BS38: 1588 | BT38: 1588 | BU38: 1588 | BV38: 1588 | BW38: 1588 | BX38: 1588 | BY38: 1588 | BZ38: 1588 | CA38: 1588 | CB38: 1588 | CC38: 1588 | CD38: 1588 | CE38: 1588 | CF38: 1588 | CG38: 1588 | CH38: 1588 | CI38: 1588 | CJ38: 1588 | CK38: 1588 | CL38: 1588 | CM38: 1588 | CN38: 1588 | CO38: 1588 | CP38: 1588 | CQ38: 1588 | CR38: 1588 | CS38: 1588 | CT38: 1588 | CU38: 1588 | CV38: 1588 | CW38: 1588 | CX38: 1588 | CY38: 1588 | CZ38: 1588 | DA38: 1588 | DB38: 1588 | DC38: 1588 | DD38: 1588 | DE38: 1588 | DF38: 1588 | DG38: 1588 | DH38: 1588 | DI38: 1588 | DJ38: 1588 | DK38: 1588 | DL38: 1748 | DM38: 1748 | DN38: 1748 | DO38: 1748 | DP38: 1748 | DQ38: 1748 | DR38: 1748 | DS38: 1748 | DT38: 1748 | DU38: 1748 | DV38: 1748 | DW38: 1748 | DX38: 1748 | DY38: 1748 | DZ38: 1748 | EA38: 1748 | EB38: 1748 | EC38: 1748 | ED38: 1748 | EE38: 1748 | EF38: 1748 | EG38: 1748 | EH38: 1748 | EI38: 1748 | EJ38: 1748 | EK38: 1748 | EL38: 1748 | EM38: 1748 | EN38: 1748 | EO38: 1748 | EP38: 1748 | EQ38: 1748 | ER38: 1748 | ES38: 1748 | ET38: 1748 | EU38: 1748 | EV38: 1748 | EW38: 1748 | EX38: 1748 | EY38: 1748 | EZ38: 1748 | FA38: 1748 | FB38: 1748 | FC38: 1748 | FD38: 1748 | FE38: 1748 | FF38: 1748 | FG38: 1748 | FH38: 1748 | FI38: 1748 | FJ38: 1748 | FK38: 1748 | FL38: 1748 | FM38: 1748 | FN38: 1748 | FO38: 1748 | FP38: 1748 | FQ38: 1748 | FR38: 1748 | FS38: 1748 | FT38: 1748 | FU38: 1748 | FV38: 1748 | FW38: 1748 | FX38: 1748 | FY38: 1748 | FZ38: 1748 | GA38: 1748 | GB38: 1748 | GC38: 1748 | GD38: 1748 | GE38: 1748 | GF38: 1748 | GG38: 1748 | GH38: 1748 | GI38: 1748 | GJ38: 1748 | GK38: 1748 | GL38: 1748 | GM38: 1748 | GN38: 1748 | GO38: 1748 | GP38: 1748 | GQ38: 1748 | GR38: 1748 | GS38: 1748 | GT38: 1748 | GU38: 1748 | GV38: 1748 | GW38: 1748 | GX38: 1748 | GY38: 1748 | GZ38: 1748 | HA38: 1748 | HB38: 1748 | HC38: 1748 | HD38: 1748 | HE38: 1748 | HF38: 1748 | HG38: 1748 | HH38: 1748 | HI38: 1748 | HJ38: 1748 | HK38: 1748 | HL38: 1748 | HM38: 1748 | HN38: 1748 | HO38: 1748 | HP38: 1748 | HQ38: 1748 | HR38: 1748 | HS38: 1748 | HT38: 1748 | HU38: 1748 | HV38: 1748 | HW38: 1748 | HX38: 1748 | HY38: 1748 | HZ38: 1748 | IA38: 1748 | IB38: 1748 | IC38: 1748 | ID38: 1748 | IE38: 1748 | IF38: 1748 | IG38: 1748 | IH38: 1748 | II38: 1748 | IJ38: 1748 | IK38: 1748 | IL38: 1748 | IM38: 1748 | IN38: 1748 | IO38: 1748 | IP38: 1748 | IQ38: 1748 | IR38: 1748 | IS38: 1748 | IT38: 1748 | IU38: 1748 | IV38: 1748 | IW38: 1748 | IX38: 1748 | IY38: 1748 | IZ38: 1748 | JA38: 1748 | JB38: 1748 | JC38: 1748 | JD38: 1748 | JE38: 1748 | JF38: 1748 | JG38: 1748 | JH38: 1748 | JI38: 1748 | JJ38: 1748 | JK38: 1748 | JL38: 1748 | JM38: 1748 | JN38: 1748 | JO38: 1748 | JP38: 1748 | JQ38: 1748 | JR38: 1748 | JS38: 1748 | JT38: 1748 | JU38: 1748 | JV38: 1748 | JW38: 1748 | JX38: 1748 | JY38: 1748 | JZ38: 1748 | KA38: 1748 | KB38: 1748 | KC38: 1748 | KD38: 1748 | KE38: 1748 | KF38: 1748 | KG38: 1748 | KH38: 1748
A39: 2.2 | B39: OPEX | C39: Backoffice ( up to March,2045) | D39: 300 | E39: 302
A40: 2.2.1 | B40: OPEX | C40: Backoffice operation service | D40: 300 | E40: 302 | X40: 3736.3193 | Y40: 3736.3236 | Z40: 3736.2876 | AA40: 3736.2496 | AB40: 3736.3063 | AC40: 3736.3438 | AD40: 3736.2688 | AE40: 3371.2527 | AF40: 1416.94 | AG40: 1416.94 | AH40: 1416.94 | AI40: 1432.63 | AJ40: 1459.74 | AK40: 1459.74 | AL40: 1459.74 | AM40: 1459.74 | AN40: 1459.74 | AO40: 1459.74 | AP40: 2719.74 | AQ40: 2719.74 | AR40: 2719.74 | AS40: 2719.74 | AT40: 2719.74 | AU40: 2719.74 | AV40: 2719.74 | AW40: 2719.74 | AX40: 2719.74 | AY40: 2719.74 | AZ40: 2719.74 | BA40: 2719.74 | BB40: 2719.74 | BC40: 2606.09 | BD40: 2606.09 | BE40: 2606.09 | BF40: 3606.09 | BG40: 2429.66 | BH40: 1692.14 | BI40: 1692.14 | BJ40: 1692.14 | BK40: 1692.14 | BL40: 1939.23 | BM40: 1939.23 | BN40: 1939.23 | BO40: 1939.23 | BP40: 1939.23 | BQ40: 1939.23 | BR40: 1939.23 | BS40: 1939.23 | BT40: 1939.23 | BU40: 1939.23 | BV40: 1939.23 | BW40: 1939.23 | BX40: 1939.23 | BY40: 1939.23 | BZ40: 1939.23 | CA40: 1939.23 | CB40: 1939.23 | CC40: 1939.23 | CD40: 1939.23 | CE40: 1939.23 | CF40: 1939.23 | CG40: 1939.23 | CH40: 1939.23 | CI40: 1939.23 | CJ40: 1939.23 | CK40: 1939.23 | CL40: 1939.23 | CM40: 1939.23 | CN40: 1939.23 | CO40: 1939.23 | CP40: 1939.23 | CQ40: 1939.23 | CR40: 1939.23 | CS40: 1939.23 | CT40: 1939.23 | CU40: 1939.23 | CV40: 1939.23 | CW40: 1939.23 | CX40: 1939.23 | CY40: 1939.23 | CZ40: 1939.23 | DA40: 1939.23 | DB40: 1939.23 | DC40: 1939.23 | DD40: 1939.23 | DE40: 1939.23 | DF40: 1939.23 | DG40: 1939.23 | DH40: 1939.23 | DI40: 1939.23 | DJ40: 1939.23 | DK40: 1939.23 | DL40: 1939.23 | DM40: 1939.23 | DN40: 1939.23 | DO40: 1939.23 | DP40: 1939.23 | DQ40: 1939.23 | DR40: 1939.23 | DS40: 1939.23 | DT40: 1939.23 | DU40: 1939.23 | DV40: 1939.23 | DW40: 1939.23 | DX40: 1939.23 | DY40: 1939.23 | DZ40: 1939.23 | EA40: 1939.23 | EB40: 1939.23 | EC40: 1939.23 | ED40: 1939.23 | EE40: 1939.23 | EF40: 1939.23 | EG40: 1939.23 | EH40: 1939.23 | EI40: 1939.23 | EJ40: 1939.23 | EK40: 1939.23 | EL40: 1939.23 | EM40: 1939.23 | EN40: 1939.23 | EO40: 1939.23 | EP40: 1939.23 | EQ40: 1939.23 | ER40: 1939.23 | ES40: 1939.23 | ET40: 1939.23 | EU40: 1939.23 | EV40: 1939.23 | EW40: 1939.23 | EX40: 1939.23 | EY40: 1939.23 | EZ40: 1939.23 | FA40: 1939.23 | FB40: 1939.23 | FC40: 1939.23 | FD40: 1939.23 | FE40: 1939.23 | FF40: 1939.23 | FG40: 1939.23 | FH40: 1939.23 | FI40: 1939.23 | FJ40: 1939.23 | FK40: 1939.23 | FL40: 1939.23 | FM40: 1939.23 | FN40: 1939.23 | FO40: 1939.23 | FP40: 1939.23 | FQ40: 1939.23 | FR40: 1939.23 | FS40: 1939.23 | FT40: 1939.23 | FU40: 1939.23 | FV40: 1939.23 | FW40: 1939.23 | FX40: 1939.23 | FY40: 1939.23 | FZ40: 1939.23 | GA40: 1939.23 | GB40: 1939.23 | GC40: 1939.23 | GD40: 1939.23 | GE40: 1939.23 | GF40: 1939.23 | GG40: 1939.23 | GH40: 1939.23 | GI40: 1939.23 | GJ40: 1939.23 | GK40: 1939.23 | GL40: 1939.23 | GM40: 1939.23 | GN40: 1939.23 | GO40: 1939.23 | GP40: 1939.23 | GQ40: 1939.23 | GR40: 1939.23 | GS40: 1939.23 | GT40: 1939.23 | GU40: 1939.23 | GV40: 1939.23 | GW40: 1939.23 | GX40: 1939.23 | GY40: 1939.23 | GZ40: 1939.23 | HA40: 1939.23 | HB40: 1939.23 | HC40: 1939.23 | HD40: 1939.23 | HE40: 1939.23 | HF40: 1939.23 | HG40: 1939.23 | HH40: 1939.23 | HI40: 1939.23 | HJ40: 1939.23 | HK40: 1939.23 | HL40: 1939.23 | HM40: 1939.23 | HN40: 1939.23 | HO40: 1939.23 | HP40: 1939.23 | HQ40: 1939.23 | HR40: 1939.23 | HS40: 1939.23 | HT40: 1939.23 | HU40: 1939.23 | HV40: 1939.23 | HW40: 1939.23 | HX40: 1939.23 | HY40: 1939.23 | HZ40: 1939.23 | IA40: 1939.23 | IB40: 1939.23 | IC40: 1939.23 | ID40: 1939.23 | IE40: 1939.23 | IF40: 1939.23 | IG40: 1939.23 | IH40: 1939.23 | II40: 1939.23 | IJ40: 1939.23 | IK40: 1939.23 | IL40: 1939.23 | IM40: 1939.23 | IN40: 1939.23 | IO40: 1939.23 | IP40: 1939.23 | IQ40: 1939.23 | IR40: 1939.23 | IS40: 1939.23 | IT40: 1939.23 | IU40: 1939.23 | IV40: 1939.23 | IW40: 1939.23 | IX40: 1939.23 | IY40: 1939.23 | IZ40: 1939.23 | JA40: 1939.23 | JB40: 1939.23 | JC40: 1939.23 | JD40: 1939.23 | JE40: 1939.23 | JF40: 1939.23 | JG40: 1939.23 | JH40: 1939.23 | JI40: 1939.23 | JJ40: 1939.23 | JK40: 1939.23 | JL40: 1939.23 | JM40: 1939.23 | JN40: 1939.23 | JO40: 1939.23 | JP40: 1939.23 | JQ40: 1939.23 | JR40: 1939.23 | JS40: 1939.23 | JT40: 1939.23 | JU40: 1939.23 | JV40: 1939.23 | JW40: 1939.23 | JX40: 1939.23 | JY40: 1939.23 | JZ40: 1939.23 | KA40: 1939.23 | KB40: 1939.23 | KC40: 1939.23 | KD40: 1939.23 | KE40: 1939.23 | KF40: 1939.23 | KG40: 1939.23 | KH40: 1939.23
A41: 2.2.2 | B41: OPEX | C41: Backoffice system Maintenance | D41: 300 | E41: 302 | K41: 1778.7976 | L41: 1778.7976 | M41: 1778.7976 | N41: 1778.7976 | O41: 1778.7976 | P41: 1778.7976 | Q41: 1778.7976 | R41: 1778.7976 | S41: 1778.7976 | T41: 1778.7976 | U41: 1778.7976 | V41: 1778.7976 | W41: 1778.7976 | X41: 1778.7976 | Y41: 1778.7976 | Z41: 1778.7976 | AA41: 1778.7976 | AB41: 1778.7976 | AC41: 1778.7976 | AD41: 1778.7976 | AE41: 1778.7976 | AF41: 1778.7976 | AG41: 1778.7976 | AH41: 1778.7976 | AI41: 1778.7976 | AJ41: 1778.7976 | AK41: 1778.7976 | AL41: 1778.7976 | AM41: 1778.7976 | AN41: 1778.7976 | AO41: 1778.7976 | AP41: 1778.7976 | AQ41: 1778.7976 | AR41: 1778.7976 | AS41: 1778.7976 | AT41: 1778.7976 | AU41: 1778.7976 | AV41: 1778.7976 | AW41: 1793.5576 | AX41: 1793.5576 | AY41: 1793.5576 | AZ41: 1793.5576 | BA41: 1793.5576 | BB41: 1793.5576 | BC41: 1514.76 | BD41: 1514.76 | BE41: 1514.76 | BF41: 2588.97 | BG41: 588.97 | BH41: 588.97 | BI41: 588.97 | BJ41: 588.97 | BK41: 588.97 | BL41: 588.97 | BM41: 588.97 | BN41: 588.97 | BO41: 588.97 | BP41: 588.97 | BQ41: 588.97 | BR41: 588.97 | BS41: 588.97 | BT41: 588.97 | BU41: 588.97 | BV41: 588.97 | BW41: 588.97 | BX41: 588.97 | BY41: 588.97 | BZ41: 588.97 | CA41: 588.97 | CB41: 588.97 | CC41: 588.97 | CD41: 588.97 | CE41: 588.97 | CF41: 588.97 | CG41: 588.97 | CH41: 588.97 | CI41: 588.97 | CJ41: 588.97 | CK41: 588.97 | CL41: 588.97 | CM41: 588.97 | CN41: 588.97 | CO41: 588.97 | CP41: 588.97 | CQ41: 588.97 | CR41: 588.97 | CS41: 588.97 | CT41: 588.97 | CU41: 588.97 | CV41: 588.97 | CW41: 588.97 | CX41: 588.97 | CY41: 588.97 | CZ41: 588.97 | DA41: 588.97 | DB41: 588.97 | DC41: 588.97 | DD41: 588.97 | DE41: 588.97 | DF41: 588.97 | DG41: 588.97 | DH41: 588.97 | DI41: 588.97 | DJ41: 620 | DK41: 620 | DL41: 620 | DM41: 620 | DN41: 620 | DO41: 620 | DP41: 620 | DQ41: 620 | DR41: 620 | DS41: 620 | DT41: 620 | DU41: 620 | DV41: 620 | DW41: 620 | DX41: 620 | DY41: 620 | DZ41: 620 | EA41: 620 | EB41: 620 | EC41: 620 | ED41: 620 | EE41: 620 | EF41: 620 | EG41: 620 | EH41: 620 | EI41: 620 | EJ41: 620 | EK41: 620 | EL41: 620 | EM41: 620 | EN41: 620 | EO41: 620 | EP41: 620 | EQ41: 620 | ER41: 620 | ES41: 620 | ET41: 620 | EU41: 620 | EV41: 620 | EW41: 620 | EX41: 620 | EY41: 620 | EZ41: 620 | FA41: 620 | FB41: 620 | FC41: 620 | FD41: 620 | FE41: 620 | FF41: 620 | FG41: 620 | FH41: 620 | FI41: 620 | FJ41: 620 | FK41: 620 | FL41: 620 | FM41: 620 | FN41: 620 | FO41: 620 | FP41: 620 | FQ41: 620 | FR41: 620 | FS41: 620 | FT41: 620 | FU41: 620 | FV41: 620 | FW41: 620 | FX41: 620 | FY41: 620 | FZ41: 620 | GA41: 620 | GB41: 620 | GC41: 620 | GD41: 620 | GE41: 620 | GF41: 620 | GG41: 620 | GH41: 620 | GI41: 620 | GJ41: 620 | GK41: 620 | GL41: 620 | GM41: 620 | GN41: 620 | GO41: 620 | GP41: 620 | GQ41: 620 | GR41: 620 | GS41: 620 | GT41: 620 | GU41: 620 | GV41: 620 | GW41: 620 | GX41: 620 | GY41: 620 | GZ41: 620 | HA41: 620 | HB41: 620 | HC41: 620 | HD41: 620 | HE41: 620 | HF41: 620 | HG41: 620 | HH41: 620 | HI41: 620 | HJ41: 620 | HK41: 620 | HL41: 620 | HM41: 620 | HN41: 620 | HO41: 620 | HP41: 620 | HQ41: 620 | HR41: 620 | HS41: 620 | HT41: 620 | HU41: 620 | HV41: 620 | HW41: 620 | HX41: 620 | HY41: 620 | HZ41: 620 | IA41: 620 | IB41: 620 | IC41: 620 | ID41: 620 | IE41: 620 | IF41: 620 | IG41: 620 | IH41: 620 | II41: 620 | IJ41: 620 | IK41: 620 | IL41: 620 | IM41: 620 | IN41: 620 | IO41: 620 | IP41: 620 | IQ41: 620 | IR41: 620 | IS41: 620 | IT41: 620 | IU41: 620 | IV41: 620 | IW41: 620 | IX41: 620 | IY41: 620 | IZ41: 620 | JA41: 620 | JB41: 620 | JC41: 620 | JD41: 620 | JE41: 620 | JF41: 620 | JG41: 620 | JH41: 620 | JI41: 620 | JJ41: 620 | JK41: 620 | JL41: 620 | JM41: 620 | JN41: 620 | JO41: 620 | JP41: 620 | JQ41: 620 | JR41: 620 | JS41: 620 | JT41: 620 | JU41: 620 | JV41: 620 | JW41: 620 | JX41: 620 | JY41: 620 | JZ41: 620 | KA41: 620 | KB41: 620 | KC41: 620 | KD41: 620 | KE41: 620 | KF41: 620 | KG41: 620 | KH41: 620
A42: 2.4 | B42: OPEX | C42: Payment Channels and Judicial Debt Recovery | D42: 300 | E42: 302 | AB42: 2215.9942 | AC42: 2215.9942 | AD42: 2526.3942 | AE42: 2514.1925 | AF42: 2471.4501 | AG42: 2361.8942 | AH42: 2355.6542 | AI42: 2368.6942 | AJ42: 2450.9542 | AK42: 2337.0542 | AL42: 2341.5742 | AM42: 2424.7016 | AN42: 4988.96 | AO42: 4085.15 | AP42: 5136.1295 | AQ42: 2208.35 | AR42: 2906.36 | AS42: 2452.64 | AT42: 2479.65 | AU42: 2381.98 | AV42: 2490.1218 | AW42: 2722.7 | AX42: 2330.3851 | AY42: 2371.13 | AZ42: 3070.475 | BA42: 2691.825 | BB42: 3380.735 | BC42: 2988.208 | BD42: 3230.7015 | BE42: 3942.0738 | BF42: 3836.7193 | BG42: 3986.2208 | BH42: 3733.4862 | BI42: 3915.5245 | BJ42: 4216.2732 | BK42: 4130.4458 | BL42: 3720 | BM42: 3720 | BN42: 3720 | BO42: 3720 | BP42: 3720 | BQ42: 3720 | BR42: 3720 | BS42: 3720 | BT42: 3720 | BU42: 3720 | BV42: 3720 | BW42: 3720 | BX42: 3607 | BY42: 3607 | BZ42: 3607 | CA42: 3607 | CB42: 3607 | CC42: 3607 | CD42: 3607 | CE42: 3607 | CF42: 3607 | CG42: 3607 | CH42: 3607 | CI42: 3607 | CJ42: 3546 | CK42: 3546 | CL42: 3546 | CM42: 3546 | CN42: 3546 | CO42: 3546 | CP42: 3546 | CQ42: 3546 | CR42: 3546 | CS42: 3546 | CT42: 3546 | CU42: 3546 | CV42: 3554 | CW42: 3554 | CX42: 3554 | CY42: 3554 | CZ42: 3554 | DA42: 3554 | DB42: 3554 | DC42: 3554 | DD42: 3554 | DE42: 3554 | DF42: 3554 | DG42: 3554 | DH42: 3639 | DI42: 3639 | DJ42: 3639 | DK42: 3639 | DL42: 3639 | DM42: 3639 | DN42: 3639 | DO42: 3639 | DP42: 3639 | DQ42: 3639 | DR42: 3639 | DS42: 3639 | DT42: 3734 | DU42: 3734 | DV42: 3734 | DW42: 3734 | DX42: 3734 | DY42: 3734 | DZ42: 3734 | EA42: 3734 | EB42: 3734 | EC42: 3734 | ED42: 3734 | EE42: 3734 | EF42: 3833 | EG42: 3833 | EH42: 3833 | EI42: 3833 | EJ42: 3833 | EK42: 3833 | EL42: 3833 | EM42: 3833 | EN42: 3833 | EO42: 3833 | EP42: 3833 | EQ42: 3833 | ER42: 3929 | ES42: 3929 | ET42: 3929 | EU42: 3929 | EV42: 3929 | EW42: 3929 | EX42: 3929 | EY42: 3929 | EZ42: 3929 | FA42: 3929 | FB42: 3929 | FC42: 3929 | FD42: 4032 | FE42: 4032 | FF42: 4032 | FG42: 4032 | FH42: 4032 | FI42: 4032 | FJ42: 4032 | FK42: 4032 | FL42: 4032 | FM42: 4032 | FN42: 4032 | FO42: 4032 | FP42: 4032 | FQ42: 4032 | FR42: 4032 | FS42: 4032 | FT42: 4032 | FU42: 4032 | FV42: 4032 | FW42: 4032 | FX42: 4032 | FY42: 4032 | FZ42: 4032 | GA42: 4032 | GB42: 4032 | GC42: 4032 | GD42: 4032 | GE42: 4032 | GF42: 4032 | GG42: 4032 | GH42: 4032 | GI42: 4032 | GJ42: 4032 | GK42: 4032 | GL42: 4032 | GM42: 4032 | GN42: 4032 | GO42: 4032 | GP42: 4032 | GQ42: 4032 | GR42: 4032 | GS42: 4032 | GT42: 4032 | GU42: 4032 | GV42: 4032 | GW42: 4032 | GX42: 4032 | GY42: 4032 | GZ42: 4032 | HA42: 4032 | HB42: 4032 | HC42: 4032 | HD42: 4032 | HE42: 4032 | HF42: 4032 | HG42: 4032 | HH42: 4032 | HI42: 4032 | HJ42: 4032 | HK42: 4032 | HL42: 4032 | HM42: 4032 | HN42: 4032 | HO42: 4032 | HP42: 4032 | HQ42: 4032 | HR42: 4032 | HS42: 4032 | HT42: 4032 | HU42: 4032 | HV42: 4032 | HW42: 4032 | HX42: 4032 | HY42: 4032 | HZ42: 4032 | IA42: 4032 | IB42: 4032 | IC42: 4032 | ID42: 4032 | IE42: 4032 | IF42: 4032 | IG42: 4032 | IH42: 4032 | II42: 4032 | IJ42: 4032 | IK42: 4032 | IL42: 4032 | IM42: 4032 | IN42: 4032 | IO42: 4032 | IP42: 4032 | IQ42: 4032 | IR42: 4032 | IS42: 4032 | IT42: 4032 | IU42: 4032 | IV42: 4032 | IW42: 4032 | IX42: 4032 | IY42: 4032 | IZ42: 4032 | JA42: 4032 | JB42: 4032 | JC42: 4032 | JD42: 4032 | JE42: 4032 | JF42: 4032 | JG42: 4032 | JH42: 4032 | JI42: 4032 | JJ42: 4032 | JK42: 4032 | JL42: 4032 | JM42: 4032 | JN42: 4032 | JO42: 4032 | JP42: 4032 | JQ42: 4032 | JR42: 4032 | JS42: 4032 | JT42: 4032 | JU42: 4032 | JV42: 4032 | JW42: 4032 | JX42: 4032 | JY42: 4032 | JZ42: 4032 | KA42: 4032 | KB42: 4032 | KC42: 4032 | KD42: 4032 | KE42: 4032 | KF42: 4032 | KG42: 4032 | KH42: 4032
A43: 4 | B43: SPV | C43: PMO services(up to March 2034) | D43: 400 | E43: 408 | J43: 16724.02 | K43: 4728.02 | L43: 4726.41 | M43: 5383.63 | N43: 4725.8 | O43: 3084.1 | P43: 5743.5 | Q43: 5438.5 | R43: 6707.76 | S43: 5950.26 | T43: 5437.26 | U43: 5437.26 | V43: 5437.26 | W43: 5437.26 | X43: 4887.01 | Y43: 4887.51 | Z43: 6287.41 | AA43: 5343.77 | AB43: 4908.57 | AC43: 5630.96 | AD43: 9088.83 | AE43: 4740.49 | AF43: 4091.02 | AG43: 4954.68 | AH43: 4150.64 | AI43: 4793.17 | AJ43: 4168.9 | AK43: 4762.8 | AL43: 6402.1 | AM43: 4770.17 | AN43: 4770.17 | AO43: 4928.99 | AP43: 4734.19 | AQ43: 4734.19 | AR43: 4734.19 | AS43: 4734.19 | AT43: 4734.19 | AU43: 4734.19 | AV43: 4734.19 | AW43: 4734.19 | AX43: 4734.19 | AY43: 4734.19 | AZ43: 4734.19 | BA43: 4734.19 | BB43: 4734.19 | BC43: 4734.19 | BD43: 3234.19 | BE43: 3234.19 | BF43: 3234.19 | BG43: 0 | BH43: 0 | BI43: 0 | BJ43: 0 | BK43: 0 | BL43: 0 | BM43: 0 | BN43: 0 | BO43: 0 | BP43: 0 | BQ43: 0 | BR43: 0 | BS43: 0 | BT43: 0 | BU43: 0 | BV43: 0 | BW43: 0 | BX43: 0 | BY43: 0 | BZ43: 0 | CA43: 0 | CB43: 0 | CC43: 0 | CD43: 0 | CE43: 0 | CF43: 0 | CG43: 0 | CH43: 0 | CI43: 0 | CJ43: 0 | CK43: 0 | CL43: 0 | CM43: 0 | CN43: 0 | CO43: 0 | CP43: 0 | CQ43: 0 | CR43: 0 | CS43: 0 | CT43: 0 | CU43: 0 | CV43: 0 | CW43: 0 | CX43: 0 | CY43: 0 | CZ43: 0 | DA43: 0 | DB43: 0 | DC43: 0 | DD43: 0 | DE43: 0 | DF43: 0 | DG43: 0 | DH43: 0 | DI43: 0 | DJ43: 0 | DK43: 0 | DL43: 0 | DM43: 0 | DN43: 0 | DO43: 0 | DP43: 0 | DQ43: 0 | DR43: 0 | DS43: 0 | DT43: 0 | DU43: 0 | DV43: 0 | DW43: 0 | DX43: 0 | DY43: 0 | DZ43: 0 | EA43: 0 | EB43: 0 | EC43: 0 | ED43: 0 | EE43: 0 | EF43: 0 | EG43: 0 | EH43: 0 | EI43: 0 | EJ43: 0 | EK43: 0 | EL43: 0 | EM43: 0 | EN43: 0 | EO43: 0 | EP43: 0 | EQ43: 0 | ER43: 0 | ES43: 0 | ET43: 0 | EU43: 0 | EV43: 0 | EW43: 0 | EX43: 0 | EY43: 0 | EZ43: 0 | FA43: 0 | FB43: 0 | FC43: 0 | FD43: 0 | FE43: 0
A44: 5.1 | B44: SPV | C44: Recursos Humanos | D44: 400 | E44: 404 | F44: 578.8 | G44: 1924.22 | H44: 1937.87 | I44: 1995.34 | J44: 4769.44 | K44: 2078.16 | L44: 2310.19 | M44: 2324.98 | N44: 3621.31 | O44: 2506.33 | P44: 2368.06 | Q44: 2299.67 | R44: 2468.1 | S44: 2257.39 | T44: 2175.15 | U44: 2253.88 | V44: 2874.39 | W44: 2425.83 | X44: 2903.14 | Y44: 7315.95 | Z44: 2493.01 | AA44: 2617.1 | AB44: 2876.91 | AC44: 3265.11 | AD44: 2502.21 | AE44: 3294.23 | AF44: 2509.4 | AG44: 2933.51 | AH44: 2241.97 | AI44: 3009.15 | AJ44: 3549.68 | AK44: 2703.83 | AL44: 7602.52 | AM44: 6542.1 | AN44: 4521.21 | AO44: 5323.91 | AP44: 11084.36 | AQ44: 5020.58 | AR44: 22831.48 | AS44: 3326.62 | AT44: 4232.78 | AU44: 5268.05 | AV44: 3953.55 | AW44: 5789.54 | AX44: 5510 | AY44: 3964.2447 | AZ44: 3964.2447 | BA44: 3964.2447 | BB44: 3964.2447 | BC44: 2835.0815 | BD44: 3312.9904 | BE44: 3312.9904 | BF44: 3312.9904 | BG44: 3312.9904 | BH44: 3312.9904 | BI44: 3312.9904 | BJ44: 3312.9904 | BK44: 3312.9904 | BL44: 3312.9904 | BM44: 3312.9904 | BN44: 3312.9904 | BO44: 3312.9904 | BP44: 3312.9904 | BQ44: 3312.9904 | BR44: 3312.9904 | BS44: 3312.9904 | BT44: 3312.9904 | BU44: 3312.9904 | BV44: 3312.9904 | BW44: 3312.9904 | BX44: 3312.9904 | BY44: 3312.9904 | BZ44: 3312.9904 | CA44: 3099.1856 | CB44: 3099.1856 | CC44: 3099.1856 | CD44: 3099.1856 | CE44: 3099.1856 | CF44: 3099.1856 | CG44: 3099.1856 | CH44: 3099.1856 | CI44: 3099.1856 | CJ44: 3099.1856 | CK44: 3099.1856 | CL44: 3099.1856 | CM44: 3099.1856 | CN44: 3099.1856 | CO44: 3099.1856 | CP44: 3099.1856 | CQ44: 3099.1856 | CR44: 3099.1856 | CS44: 3099.1856 | CT44: 3099.1856 | CU44: 3099.1856 | CV44: 3099.1856 | CW44: 3099.1856 | CX44: 3099.1856 | CY44: 3099.1856 | CZ44: 3099.1856 | DA44: 3099.1856 | DB44: 3099.1856 | DC44: 3099.1856 | DD44: 3099.1856 | DE44: 3099.1856 | DF44: 3099.1856 | DG44: 3099.1856 | DH44: 3099.1856 | DI44: 3099.1856 | DJ44: 3099.1856 | DK44: 3099.1856 | DL44: 3099.1856 | DM44: 3099.1856 | DN44: 3099.1856 | DO44: 3099.1856 | DP44: 3099.1856 | DQ44: 3099.1856 | DR44: 3099.1856 | DS44: 3099.1856 | DT44: 3099.1856 | DU44: 3099.1856 | DV44: 3099.1856 | DW44: 3099.1856 | DX44: 3099.1856 | DY44: 3099.1856 | DZ44: 3099.1856 | EA44: 3099.1856 | EB44: 3099.1856 | EC44: 3099.1856 | ED44: 3099.1856 | EE44: 3099.1856 | EF44: 3099.1856 | EG44: 3099.1856 | EH44: 3099.1856 | EI44: 3099.1856 | EJ44: 3099.1856 | EK44: 3099.1856 | EL44: 3099.1856 | EM44: 3099.1856 | EN44: 3099.1856 | EO44: 3099.1856 | EP44: 3099.1856 | EQ44: 3099.1856 | ER44: 3099.1856 | ES44: 3099.1856 | ET44: 3099.1856 | EU44: 3099.1856 | EV44: 3099.1856 | EW44: 3099.1856 | EX44: 3099.1856 | EY44: 3099.1856 | EZ44: 3099.1856 | FA44: 3099.1856 | FB44: 3099.1856 | FC44: 3099.1856 | FD44: 3099.1856 | FE44: 3099.1856 | FF44: 3053.9443 | FG44: 3053.9443 | FH44: 3053.9443 | FI44: 3053.9443 | FJ44: 3053.9443 | FK44: 3053.9443 | FL44: 3053.9443 | FM44: 3053.9443 | FN44: 3053.9443 | FO44: 3053.9443 | FP44: 3053.9443 | FQ44: 3053.9443 | FR44: 3053.9443 | FS44: 3053.9443 | FT44: 3053.9443 | FU44: 3053.9443 | FV44: 3053.9443 | FW44: 3053.9443 | FX44: 3053.9443 | FY44: 3053.9443 | FZ44: 3053.9443 | GA44: 3053.9443 | GB44: 3053.9443 | GC44: 3053.9443 | GD44: 3053.9443 | GE44: 3053.9443 | GF44: 3053.9443 | GG44: 3053.9443 | GH44: 3053.9443 | GI44: 3053.9443 | GJ44: 3053.9443 | GK44: 3053.9443 | GL44: 3053.9443 | GM44: 3053.9443 | GN44: 3053.9443 | GO44: 3053.9443 | GP44: 3053.9443 | GQ44: 3053.9443 | GR44: 3053.9443 | GS44: 3053.9443 | GT44: 3053.9443 | GU44: 3053.9443 | GV44: 3053.9443 | GW44: 3053.9443 | GX44: 3053.9443 | GY44: 3053.9443 | GZ44: 3053.9443 | HA44: 3053.9443 | HB44: 3053.9443 | HC44: 3053.9443 | HD44: 3053.9443 | HE44: 3053.9443 | HF44: 3053.9443 | HG44: 3053.9443 | HH44: 3053.9443 | HI44: 3053.9443 | HJ44: 3053.9443 | HK44: 3053.9443 | HL44: 3053.9443 | HM44: 3053.9443 | HN44: 3053.9443 | HO44: 3053.9443 | HP44: 3053.9443 | HQ44: 3053.9443 | HR44: 3053.9443 | HS44: 3053.9443 | HT44: 3053.9443 | HU44: 3053.9443 | HV44: 3053.9443 | HW44: 3053.9443 | HX44: 3053.9443 | HY44: 3053.9443 | HZ44: 3053.9443 | IA44: 3053.9443 | IB44: 3053.9443 | IC44: 3053.9443 | ID44: 3053.9443 | IE44: 3053.9443 | IF44: 3053.9443 | IG44: 3053.9443 | IH44: 3053.9443 | II44: 3053.9443 | IJ44: 3053.9443 | IK44: 3053.9443 | IL44: 3053.9443 | IM44: 3053.9443 | IN44: 3053.9443 | IO44: 3053.9443 | IP44: 3053.9443 | IQ44: 3053.9443 | IR44: 3053.9443 | IS44: 3053.9443 | IT44: 3053.9443 | IU44: 3053.9443 | IV44: 3053.9443 | IW44: 3053.9443 | IX44: 3053.9443 | IY44: 3053.9443 | IZ44: 3053.9443 | JA44: 3053.9443 | JB44: 3053.9443 | JC44: 3053.9443 | JD44: 3053.9443 | JE44: 3053.9443 | JF44: 3053.9443 | JG44: 3053.9443 | JH44: 3053.9443 | JI44: 3053.9443 | JJ44: 3053.9443 | JK44: 3053.9443 | JL44: 3053.9443 | JM44: 3053.9443 | JN44: 3053.9443 | JO44: 3053.9443 | JP44: 3053.9443 | JQ44: 3053.9443 | JR44: 3053.9443 | JS44: 3053.9443 | JT44: 3053.9443 | JU44: 3053.9443 | JV44: 3053.9443 | JW44: 3053.9443 | JX44: 3053.9443 | JY44: 3053.9443 | JZ44: 3053.9443 | KA44: 3053.9443 | KB44: 3053.9443 | KC44: 3053.9443 | KD44: 3053.9443 | KE44: 3053.9443 | KF44: 3053.9443 | KG44: 3053.9443
A45: 5.2 | B45: SPV | C45: Asesorías Externas | D45: 400 | E45: 403-405-406 | F45: 842.64 | G45: 239.93 | H45: 670.92 | I45: 243.18 | J45: 312.91 | K45: 216.27 | L45: 217.34 | M45: 1492.66 | N45: 216.81 | O45: 302.22 | P45: 678.43 | Q45: 361.61 | R45: 477.93 | S45: 302.59 | T45: 1186.89 | U45: 263.2 | V45: 743.85 | W45: 975.93 | X45: 343.22 | Y45: 290.52 | Z45: 2145.87 | AA45: 1214.17 | AB45: 275.51 | AC45: 920.49 | AD45: 357.78 | AE45: 576 | AF45: 1973.19 | AG45: 611.64 | AH45: 355.14 | AI45: 836.16 | AJ45: 628.66 | AK45: 355.54 | AL45: 863.6 | AM45: 1186.05 | AN45: 1212.18 | AO45: 1851.29 | AP45: 311.46 | AQ45: 769.57 | AR45: 2316.45 | AS45: 94.02 | AT45: 353.78 | AU45: 507.04 | AV45: 1129.94 | AW45: 1363.2 | AX45: 1696 | AY45: 761.86178 | AZ45: 761.86178 | BA45: 761.86178 | BB45: 1772.25 | BC45: 1938.5809 | BD45: 2328.3333 | BE45: 1568.3333 | BF45: 3478.3333 | BG45: 4205.3333 | BH45: 4078.3333 | BI45: 3518.3333 | BJ45: 4528.3333 | BK45: 3518.3333 | BL45: 10827.243 | BM45: 3518.3333 | BN45: 3388.3333 | BO45: 2948.3333 | BP45: 2888.3333 | BQ45: 678.33333 | BR45: 538.33333 | BS45: 678.33333 | BT45: 667.33333 | BU45: 807.65333 | BV45: 667.65333 | BW45: 807.65333 | BX45: 667.65333 | BY45: 807.65333 | BZ45: 667.65333 | CA45: 807.65333 | CB45: 667.65333 | CC45: 807.65333 | CD45: 667.65333 | CE45: 807.65333 | CF45: 667.65333 | CG45: 807.65333 | CH45: 667.65333 | CI45: 607.65333 | CJ45: 467.65333 | CK45: 607.65333 | CL45: 467.65333 | CM45: 607.65333 | CN45: 467.65333 | CO45: 507.65333 | CP45: 467.65333 | CQ45: 507.65333 | CR45: 467.65333 | CS45: 507.65333 | CT45: 467.65333 | CU45: 507.65333 | CV45: 467.65333 | CW45: 507.65333 | CX45: 467.65333 | CY45: 507.65333 | CZ45: 467.65333 | DA45: 507.65333 | DB45: 467.65333 | DC45: 507.65333 | DD45: 467.65333 | DE45: 507.65333 | DF45: 467.65333 | DG45: 507.65333 | DH45: 467.65333 | DI45: 507.65333 | DJ45: 467.65333 | DK45: 507.65333 | DL45: 561.01333 | DM45: 378.33333 | DN45: 338.33333 | DO45: 378.33333 | DP45: 338.33333 | DQ45: 378.33333 | DR45: 561.01333 | DS45: 378.33333 | DT45: 338.33333 | DU45: 378.33333 | DV45: 338.33333 | DW45: 378.33333 | DX45: 561.01333 | DY45: 378.33333 | DZ45: 338.33333 | EA45: 378.33333 | EB45: 338.33333 | EC45: 378.33333 | ED45: 561.01333 | EE45: 378.33333 | EF45: 338.33333 | EG45: 378.33333 | EH45: 338.33333 | EI45: 378.33333 | EJ45: 561.01333 | EK45: 378.33333 | EL45: 338.33333 | EM45: 378.33333 | EN45: 338.33333 | EO45: 378.33333 | EP45: 561.01333 | EQ45: 378.33333 | ER45: 338.33333 | ES45: 378.33333 | ET45: 338.33333 | EU45: 378.33333 | EV45: 561.01333 | EW45: 378.33333 | EX45: 338.33333 | EY45: 378.33333 | EZ45: 338.33333 | FA45: 378.33333 | FB45: 561.01333 | FC45: 378.33333 | FD45: 338.33333 | FE45: 378.33333 | FF45: 378.33333 | FG45: 378.33333 | FH45: 378.33333 | FI45: 378.33333 | FJ45: 378.33333 | FK45: 378.33333 | FL45: 378.33333 | FM45: 378.33333 | FN45: 378.33333 | FO45: 378.33333 | FP45: 378.33333 | FQ45: 378.33333 | FR45: 378.33333 | FS45: 378.33333 | FT45: 378.33333 | FU45: 378.33333 | FV45: 378.33333 | FW45: 378.33333 | FX45: 378.33333 | FY45: 378.33333 | FZ45: 378.33333 | GA45: 378.33333 | GB45: 378.33333 | GC45: 378.33333 | GD45: 378.33333 | GE45: 378.33333 | GF45: 378.33333 | GG45: 378.33333 | GH45: 378.33333 | GI45: 378.33333 | GJ45: 378.33333 | GK45: 378.33333 | GL45: 378.33333 | GM45: 378.33333 | GN45: 378.33333 | GO45: 378.33333 | GP45: 378.33333 | GQ45: 378.33333 | GR45: 378.33333 | GS45: 378.33333 | GT45: 378.33333 | GU45: 378.33333 | GV45: 378.33333 | GW45: 378.33333 | GX45: 378.33333 | GY45: 378.33333 | GZ45: 378.33333 | HA45: 378.33333 | HB45: 378.33333 | HC45: 378.33333 | HD45: 378.33333 | HE45: 378.33333 | HF45: 378.33333 | HG45: 378.33333 | HH45: 378.33333 | HI45: 378.33333 | HJ45: 378.33333 | HK45: 378.33333 | HL45: 378.33333 | HM45: 378.33333 | HN45: 378.33333 | HO45: 378.33333 | HP45: 378.33333 | HQ45: 378.33333 | HR45: 378.33333 | HS45: 378.33333 | HT45: 378.33333 | HU45: 378.33333 | HV45: 378.33333 | HW45: 378.33333 | HX45: 378.33333 | HY45: 378.33333 | HZ45: 378.33333 | IA45: 378.33333 | IB45: 378.33333 | IC45: 378.33333 | ID45: 378.33333 | IE45: 378.33333 | IF45: 378.33333 | IG45: 378.33333 | IH45: 378.33333 | II45: 378.33333 | IJ45: 378.33333 | IK45: 378.33333 | IL45: 378.33333 | IM45: 378.33333 | IN45: 378.33333 | IO45: 378.33333 | IP45: 378.33333 | IQ45: 378.33333 | IR45: 378.33333 | IS45: 378.33333 | IT45: 378.33333 | IU45: 378.33333 | IV45: 378.33333 | IW45: 378.33333 | IX45: 378.33333 | IY45: 378.33333 | IZ45: 378.33333 | JA45: 378.33333 | JB45: 378.33333 | JC45: 378.33333 | JD45: 378.33333 | JE45: 378.33333 | JF45: 378.33333 | JG45: 378.33333 | JH45: 378.33333 | JI45: 378.33333 | JJ45: 378.33333 | JK45: 378.33333 | JL45: 378.33333 | JM45: 378.33333 | JN45: 378.33333 | JO45: 378.33333 | JP45: 378.33333 | JQ45: 378.33333 | JR45: 378.33333 | JS45: 378.33333 | JT45: 378.33333 | JU45: 378.33333 | JV45: 378.33333 | JW45: 378.33333 | JX45: 378.33333 | JY45: 378.33333 | JZ45: 378.33333 | KA45: 378.33333 | KB45: 378.33333 | KC45: 378.33333 | KD45: 378.33333 | KE45: 378.33333 | KF45: 378.33333 | KG45: 378.33333
A46: 5.3 | B46: SPV | C46: Other addmistration cost | D46: 400 | E46: 401-402 | F46: 2218.5295 | G46: 3408.1495 | H46: 3125.1795 | I46: 2880.7695 | J46: 4275.5895 | K46: 2410.5095 | L46: 2705.5195 | M46: 1644.5295 | N46: 1571.6795 | O46: 2745.1495 | P46: 1962.6895 | Q46: 1910.8695 | R46: 2111.1995 | S46: 1776.9595 | T46: 2134.1895 | U46: 2558.9695 | V46: 6645.1195 | W46: 16084.77 | X46: 7825.0095 | Y46: 2683.7895 | Z46: 4907.4095 | AA46: 4579.8995 | AB46: 3339.0695 | AC46: 2694.6595 | AD46: 1988.8895 | AE46: 2960.3295 | AF46: 2465.2595 | AG46: 1741.8195 | AH46: 3110.6295 | AI46: 2457.5895 | AJ46: 3423.1395 | AK46: 2729.0895 | AL46: 3039.4295 | AM46: 2245.8395 | AN46: 3710.8595 | AO46: 2187.3695 | AP46: 2907.5895 | AQ46: 2517.4795 | AR46: 3425.2095 | AS46: 2330.4095 | AT46: 3879.0295 | AU46: 3258.3495 | AV46: 4054.2895 | AW46: 3519.1295 | AX46: 11325.75 | AY46: 2685.2447 | AZ46: 2685.2447 | BA46: 2685.2447 | BB46: 0 | BC46: 1522.9514 | BD46: 1352.9514 | BE46: 1352.9514 | BF46: 1352.9514 | BG46: 1352.9514 | BH46: 1352.9514 | BI46: 1264.1514 | BJ46: 1264.1514 | BK46: 1143.4113 | BL46: 1143.4113 | BM46: 1143.4113 | BN46: 1143.4113 | BO46: 1143.4113 | BP46: 1143.4113 | BQ46: 1143.4113 | BR46: 1143.4113 | BS46: 1143.4113 | BT46: 1143.4113 | BU46: 1054.6113 | BV46: 1204.6113 | BW46: 1145.4841 | BX46: 1145.4841 | BY46: 1145.4841 | BZ46: 1145.4841 | CA46: 1145.4841 | CB46: 1145.4841 | CC46: 1145.4841 | CD46: 1145.4841 | CE46: 1145.4841 | CF46: 1145.4841 | CG46: 1056.6841 | CH46: 1206.6841 | CI46: 1134.5441 | CJ46: 1134.5441 | CK46: 1134.5441 | CL46: 1134.5441 | CM46: 1134.5441 | CN46: 1134.5441 | CO46: 1134.5441 | CP46: 1134.5441 | CQ46: 1134.5441 | CR46: 1134.5441 | CS46: 1045.7441 | CT46: 1195.7441 | CU46: 1124.7557 | CV46: 1124.7557 | CW46: 1124.7557 | CX46: 1124.7557 | CY46: 1124.7557 | CZ46: 1124.7557 | DA46: 1124.7557 | DB46: 1124.7557 | DC46: 1124.7557 | DD46: 1124.7557 | DE46: 1035.9557 | DF46: 1185.9557 | DG46: 1117.8462 | DH46: 1117.8462 | DI46: 1117.8462 | DJ46: 1117.8462 | DK46: 1117.8462 | DL46: 1117.8462 | DM46: 1117.8462 | DN46: 1117.8462 | DO46: 1117.8462 | DP46: 1117.8462 | DQ46: 1029.0462 | DR46: 1179.0462 | DS46: 1117.8462 | DT46: 1117.8462 | DU46: 1117.8462 | DV46: 1117.8462 | DW46: 1117.8462 | DX46: 1117.8462 | DY46: 1117.8462 | DZ46: 1117.8462 | EA46: 1117.8462 | EB46: 1117.8462 | EC46: 1029.0462 | ED46: 1179.0462 | EE46: 1117.8462 | EF46: 1117.8462 | EG46: 1117.8462 | EH46: 1117.8462 | EI46: 1117.8462 | EJ46: 1117.8462 | EK46: 1117.8462 | EL46: 1117.8462 | EM46: 1117.8462 | EN46: 1117.8462 | EO46: 1029.0462 | EP46: 1179.0462 | EQ46: 1117.8462 | ER46: 1117.8462 | ES46: 1117.8462 | ET46: 1117.8462 | EU46: 1117.8462 | EV46: 1117.8462 | EW46: 1117.8462 | EX46: 1117.8462 | EY46: 1117.8462 | EZ46: 1117.8462 | FA46: 1029.0462 | FB46: 1179.0462 | FC46: 1117.8462 | FD46: 1117.8462 | FE46: 1117.8462 | FF46: 1113.8562 | FG46: 1113.8562 | FH46: 1113.8562 | FI46: 1113.8562 | FJ46: 1113.8562 | FK46: 1113.8562 | FL46: 1113.8562 | FM46: 1113.8562 | FN46: 1113.8562 | FO46: 1113.8562 | FP46: 1113.8562 | FQ46: 1113.8562 | FR46: 1113.8562 | FS46: 1113.8562 | FT46: 1113.8562 | FU46: 1113.8562 | FV46: 1113.8562 | FW46: 1113.8562 | FX46: 1113.8562 | FY46: 1113.8562 | FZ46: 1113.8562 | GA46: 1113.8562 | GB46: 1113.8562 | GC46: 1113.8562 | GD46: 1113.8562 | GE46: 1113.8562 | GF46: 1113.8562 | GG46: 1113.8562 | GH46: 1113.8562 | GI46: 1113.8562 | GJ46: 1113.8562 | GK46: 1113.8562 | GL46: 1113.8562 | GM46: 1113.8562 | GN46: 1113.8562 | GO46: 1113.8562 | GP46: 1113.8562 | GQ46: 1113.8562 | GR46: 1113.8562 | GS46: 1113.8562 | GT46: 1113.8562 | GU46: 1113.8562 | GV46: 1113.8562 | GW46: 1113.8562 | GX46: 1113.8562 | GY46: 1113.8562 | GZ46: 1113.8562 | HA46: 1113.8562 | HB46: 1113.8562 | HC46: 1113.8562 | HD46: 1113.8562 | HE46: 1113.8562 | HF46: 1113.8562 | HG46: 1113.8562 | HH46: 1113.8562 | HI46: 1113.8562 | HJ46: 1113.8562 | HK46: 1113.8562 | HL46: 1113.8562 | HM46: 1113.8562 | HN46: 1113.8562 | HO46: 1113.8562 | HP46: 1113.8562 | HQ46: 1113.8562 | HR46: 1113.8562 | HS46: 1113.8562 | HT46: 1113.8562 | HU46: 1113.8562 | HV46: 1113.8562 | HW46: 1113.8562 | HX46: 1113.8562 | HY46: 1113.8562 | HZ46: 1113.8562 | IA46: 1113.8562 | IB46: 1113.8562 | IC46: 1113.8562 | ID46: 1113.8562 | IE46: 1113.8562 | IF46: 1113.8562 | IG46: 1113.8562 | IH46: 1113.8562 | II46: 1113.8562 | IJ46: 1113.8562 | IK46: 1113.8562 | IL46: 1113.8562 | IM46: 1113.8562 | IN46: 1113.8562 | IO46: 1113.8562 | IP46: 1113.8562 | IQ46: 1113.8562 | IR46: 1113.8562 | IS46: 1113.8562 | IT46: 1113.8562 | IU46: 1113.8562 | IV46: 1113.8562 | IW46: 1113.8562 | IX46: 1113.8562 | IY46: 1113.8562 | IZ46: 1113.8562 | JA46: 1113.8562 | JB46: 1113.8562 | JC46: 1113.8562 | JD46: 1113.8562 | JE46: 1113.8562 | JF46: 1113.8562 | JG46: 1113.8562 | JH46: 1113.8562 | JI46: 1113.8562 | JJ46: 1113.8562 | JK46: 1113.8562 | JL46: 1113.8562 | JM46: 1113.8562 | JN46: 1113.8562 | JO46: 1113.8562 | JP46: 1113.8562 | JQ46: 1113.8562 | JR46: 1113.8562 | JS46: 1113.8562 | JT46: 1113.8562 | JU46: 1113.8562 | JV46: 1113.8562 | JW46: 1113.8562 | JX46: 1113.8562 | JY46: 1113.8562 | JZ46: 1113.8562 | KA46: 1113.8562 | KB46: 1113.8562 | KC46: 1113.8562 | KD46: 1113.8562 | KE46: 1113.8562 | KF46: 1113.8562 | KG46: 1113.8562
A47: 2.5.1 | B47: OPEX | C47: IGYC-Operation & Back Office | D47: 400 | E47: 408
A48: 2.5.2 | B48: OPEX | C48: Public Opinion Monitoring (up to March 2034) | D48: 400 | E48: 402 | F48: 0 | G48: 360 | H48: 360 | I48: 360 | J48: 363 | K48: 418.48 | L48: 225 | M48: 144 | N48: 0 | O48: 131 | P48: 240 | Q48: 0 | R48: 110.5 | S48: 124 | T48: 516 | U48: 328 | V48: 328 | W48: 328 | X48: 284 | Y48: 284 | Z48: 284 | AA48: 284 | AB48: 0 | AC48: 0 | AD48: 0 | AE48: 0 | AF48: 0 | AG48: 284 | AH48: 284 | AI48: 284 | AJ48: 284 | AK48: 0 | AL48: 0 | AM48: 83.9 | AN48: 0 | AO48: 0 | AP48: 0 | AQ48: 0 | AR48: 0 | AS48: 0 | AT48: 0 | AU48: 0 | AV48: 0 | AW48: 0 | AX48: 0 | AY48: 0 | AZ48: 0 | BA48: 0 | BB48: 0 | BC48: 0 | BD48: 0 | BE48: 0 | BF48: 0 | BG48: 0 | BH48: 0 | BI48: 0 | BJ48: 0 | BK48: 0 | BL48: 0 | BM48: 0 | BN48: 0 | BO48: 0 | BP48: 0 | BQ48: 0 | BR48: 0 | BS48: 0 | BT48: 0 | BU48: 0 | BV48: 0 | BW48: 0 | BX48: 0 | BY48: 0 | BZ48: 0 | CA48: 0 | CB48: 0 | CC48: 0 | CD48: 0 | CE48: 0 | CF48: 0 | CG48: 0 | CH48: 0 | CI48: 0 | CJ48: 0 | CK48: 0 | CL48: 0 | CM48: 0 | CN48: 0 | CO48: 0 | CP48: 0 | CQ48: 0 | CR48: 0 | CS48: 0 | CT48: 0 | CU48: 0 | CV48: 0 | CW48: 0 | CX48: 0 | CY48: 0 | CZ48: 0 | DA48: 0 | DB48: 0 | DC48: 0 | DD48: 0 | DE48: 0 | DF48: 0 | DG48: 0 | DH48: 0 | DI48: 0 | DJ48: 0 | DK48: 0 | DL48: 0 | DM48: 0 | DN48: 0 | DO48: 0 | DP48: 0 | DQ48: 0 | DR48: 0 | DS48: 0 | DT48: 0 | DU48: 0 | DV48: 0 | DW48: 0 | DX48: 0 | DY48: 0 | DZ48: 0 | EA48: 0 | EB48: 0 | EC48: 0 | ED48: 0 | EE48: 0 | EF48: 0 | EG48: 0 | EH48: 0 | EI48: 0 | EJ48: 0 | EK48: 0 | EL48: 0 | EM48: 0 | EN48: 0 | EO48: 0 | EP48: 0 | EQ48: 0 | ER48: 0 | ES48: 0 | ET48: 0 | EU48: 0 | EV48: 0 | EW48: 0 | EX48: 0 | EY48: 0 | EZ48: 0 | FA48: 0 | FB48: 0 | FC48: 0 | FD48: 0 | FE48: 0 | FF48: 0 | FG48: 0 | FH48: 0 | FI48: 0 | FJ48: 0 | FK48: 0 | FL48: 0 | FM48: 0 | FN48: 0 | FO48: 0 | FP48: 0 | FQ48: 0 | FR48: 0 | FS48: 0 | FT48: 0 | FU48: 0 | FV48: 0 | FW48: 0 | FX48: 0 | FY48: 0 | FZ48: 0 | GA48: 0 | GB48: 0 | GC48: 0 | GD48: 0 | GE48: 0 | GF48: 0 | GG48: 0 | GH48: 0 | GI48: 0 | GJ48: 0 | GK48: 0 | GL48: 0 | GM48: 0 | GN48: 0 | GO48: 0 | GP48: 0 | GQ48: 0 | GR48: 0 | GS48: 0 | GT48: 0 | GU48: 0 | GV48: 0 | GW48: 0 | GX48: 0 | GY48: 0 | GZ48: 0 | HA48: 0 | HB48: 0 | HC48: 0 | HD48: 0 | HE48: 0 | HF48: 0 | HG48: 0 | HH48: 0 | HI48: 0 | HJ48: 0 | HK48: 0 | HL48: 0 | HM48: 0 | HN48: 0 | HO48: 0 | HP48: 0 | HQ48: 0 | HR48: 0 | HS48: 0 | HT48: 0 | HU48: 0 | HV48: 0 | HW48: 0 | HX48: 0 | HY48: 0 | HZ48: 0 | IA48: 0 | IB48: 0 | IC48: 0 | ID48: 0 | IE48: 0 | IF48: 0 | IG48: 0 | IH48: 0 | II48: 0 | IJ48: 0 | IK48: 0 | IL48: 0 | IM48: 0 | IN48: 0 | IO48: 0 | IP48: 0 | IQ48: 0 | IR48: 0 | IS48: 0 | IT48: 0 | IU48: 0 | IV48: 0 | IW48: 0 | IX48: 0 | IY48: 0 | IZ48: 0 | JA48: 0 | JB48: 0 | JC48: 0 | JD48: 0 | JE48: 0 | JF48: 0 | JG48: 0 | JH48: 0 | JI48: 0 | JJ48: 0 | JK48: 0 | JL48: 0 | JM48: 0 | JN48: 0 | JO48: 0 | JP48: 0 | JQ48: 0 | JR48: 0 | JS48: 0 | JT48: 0 | JU48: 0 | JV48: 0 | JW48: 0 | JX48: 0 | JY48: 0 | JZ48: 0 | KA48: 0 | KB48: 0 | KC48: 0 | KD48: 0 | KE48: 0 | KF48: 0 | KG48: 0 | KH48: 0
A49: 6.1 | B49: SPV | C49: Insurance | D49: 700 | E49: 701 | F49: 2909.25 | G49: 2909.25 | H49: 2909.25 | I49: 2909.25 | J49: 2909.25 | K49: 2909.25 | L49: 2909.25 | M49: 2909.25 | N49: 2909.25 | O49: 2909.25 | P49: 2909.25 | Q49: 2909.25 | R49: 2619.5 | S49: 2619.5 | T49: 2619.5 | U49: 2619.5 | V49: 2619.5 | W49: 2619.5 | X49: 2619.5 | Y49: 2619.5 | Z49: 2619.5 | AA49: 2619.5 | AB49: 2619.5 | AC49: 2619.5 | AD49: 2598.6667 | AE49: 2598.6667 | AF49: 2598.6667 | AG49: 2598.6667 | AH49: 2598.6667 | AI49: 2598.6667 | AJ49: 2598.6667 | AK49: 2598.6667 | AL49: 2598.6667 | AM49: 2598.6667 | AN49: 2598.6667 | AO49: 2598.6667 | AP49: 2924.1808 | AQ49: 2924.1808 | AR49: 2924.1808 | AS49: 2924.1808 | AT49: 2924.1808 | AU49: 2924.1808 | AV49: 2924.1808 | AW49: 2924.1808 | AX49: 2924.1808 | AY49: 2924.1808 | AZ49: 2924.1808 | BA49: 2924.1808 | BB49: 2762.8994 | BC49: 0 | BD49: 0 | BE49: 0 | BF49: 0 | BG49: 0 | BH49: 0 | BI49: 0 | BJ49: 0 | BK49: 0 | BL49: 50380 | BM49: 0 | BN49: 0 | BO49: 0 | BP49: 0 | BQ49: 0 | BR49: 0 | BS49: 0 | BT49: 0 | BU49: 0 | BV49: 0 | BW49: 0 | BX49: 50380 | BY49: 0 | BZ49: 0 | CA49: 0 | CB49: 0 | CC49: 0 | CD49: 0 | CE49: 0 | CF49: 0 | CG49: 0 | CH49: 0 | CI49: 0 | CJ49: 50380 | CK49: 0 | CL49: 0 | CM49: 0 | CN49: 0 | CO49: 0 | CP49: 0 | CQ49: 0 | CR49: 0 | CS49: 0 | CT49: 0 | CU49: 0 | CV49: 50380 | CW49: 0 | CX49: 0 | CY49: 0 | CZ49: 0 | DA49: 0 | DB49: 0 | DC49: 0 | DD49: 0 | DE49: 0 | DF49: 0 | DG49: 0 | DH49: 50380 | DI49: 0 | DJ49: 0 | DK49: 0 | DL49: 0 | DM49: 0 | DN49: 0 | DO49: 0 | DP49: 0 | DQ49: 0 | DR49: 0 | DS49: 0 | DT49: 51800 | DU49: 0 | DV49: 0 | DW49: 0 | DX49: 0 | DY49: 0 | DZ49: 0 | EA49: 0 | EB49: 0 | EC49: 0 | ED49: 0 | EE49: 0 | EF49: 51800 | EG49: 0 | EH49: 0 | EI49: 0 | EJ49: 0 | EK49: 0 | EL49: 0 | EM49: 0 | EN49: 0 | EO49: 0 | EP49: 0 | EQ49: 0 | ER49: 51800 | ES49: 0 | ET49: 0 | EU49: 0 | EV49: 0 | EW49: 0 | EX49: 0 | EY49: 0 | EZ49: 0 | FA49: 0 | FB49: 0 | FC49: 0 | FD49: 51800 | FE49: 0
A50: 6.2 | B50: SPV | C50: Guarantee | D50: 700 | E50: 702 | F50: 333.33333 | G50: 333.33333 | H50: 333.33333 | I50: 333.33333 | J50: 333.33333 | K50: 333.33333 | L50: 333.33333 | M50: 333.33333 | N50: 333.33333 | O50: 333.33333 | P50: 333.33333 | Q50: 333.33333 | R50: 333.33333 | S50: 333.33333 | T50: 333.33333 | U50: 333.33333 | V50: 333.33333 | W50: 333.33333 | X50: 333.33333 | Y50: 333.33333 | Z50: 333.33333 | AA50: 333.33333 | AB50: 333.33333 | AC50: 333.33333 | AD50: 333.33333 | AE50: 333.33333 | AF50: 333.33333 | AG50: 333.33333 | AH50: 333.33333 | AI50: 333.33333 | AJ50: 333.33333 | AK50: 333.33333 | AL50: 333.33333 | AM50: 333.33333 | AN50: 333.33333 | AO50: 333.33333 | AP50: 333.33333 | AQ50: 333.33333 | AR50: 333.33333 | AS50: 333.33333 | AT50: 333.33333 | AU50: 333.33333 | AV50: 333.33333 | AW50: 333.33333 | AX50: 333.33333 | AY50: 479.16667 | AZ50: 479.16667 | BA50: 479.16667 | BB50: 479.16667 | BC50: 230.40525 | BD50: 230.40525 | BE50: 230.40525 | BF50: 230.40525 | BG50: 230.40525 | BH50: 230.40525 | BI50: 230.40525 | BJ50: 230.40525 | BK50: 230.40525 | BL50: 230.40525 | BM50: 230.40525 | BN50: 230.40525 | BO50: 230.40525 | BP50: 230.40525 | BQ50: 186.65525 | BR50: 186.65525 | BS50: 186.65525 | BT50: 186.65525 | BU50: 186.65525 | BV50: 157.48859 | BW50: 219.98859 | BX50: 219.98859 | BY50: 219.98859 | BZ50: 219.98859 | CA50: 176.23859 | CB50: 176.23859 | CC50: 176.23859 | CD50: 176.23859 | CE50: 176.23859 | CF50: 176.23859 | CG50: 176.23859 | CH50: 176.23859 | CI50: 176.23859 | CJ50: 176.23859 | CK50: 176.23859 | CL50: 176.23859 | CM50: 176.23859 | CN50: 230.40525 | CO50: 230.40525 | CP50: 230.40525 | CQ50: 230.40525 | CR50: 230.40525 | CS50: 230.40525 | CT50: 230.40525 | CU50: 230.40525 | CV50: 230.40525 | CW50: 230.40525 | CX50: 230.40525 | CY50: 230.40525 | CZ50: 230.40525 | DA50: 230.40525 | DB50: 230.40525 | DC50: 347.07192 | DD50: 230.40525 | DE50: 230.40525 | DF50: 230.40525 | DG50: 230.40525 | DH50: 230.40525 | DI50: 230.40525 | DJ50: 230.40525 | DK50: 230.40525 | DL50: 230.40525 | DM50: 230.40525 | DN50: 230.40525 | DO50: 230.40525 | DP50: 230.40525 | DQ50: 230.40525 | DR50: 230.40525 | DS50: 230.40525 | DT50: 230.40525 | DU50: 230.40525 | DV50: 230.40525 | DW50: 230.40525 | DX50: 230.40525 | DY50: 230.40525 | DZ50: 230.40525 | EA50: 230.40525 | EB50: 230.40525 | EC50: 230.40525 | ED50: 230.40525 | EE50: 230.40525 | EF50: 230.40525 | EG50: 230.40525 | EH50: 230.40525 | EI50: 230.40525 | EJ50: 230.40525 | EK50: 230.40525 | EL50: 230.40525 | EM50: 230.40525 | EN50: 230.40525 | EO50: 230.40525 | EP50: 230.40525 | EQ50: 230.40525 | ER50: 230.40525 | ES50: 230.40525 | ET50: 230.40525 | EU50: 230.40525 | EV50: 230.40525 | EW50: 230.40525 | EX50: 230.40525 | EY50: 230.40525 | EZ50: 230.40525 | FA50: 230.40525 | FB50: 230.40525 | FC50: 230.40525 | FD50: 230.40525 | FE50: 2405.4053
C51: MOP | D51: 500 | F51: 18947.456 | G51: 18947.456 | H51: 18947.456 | I51: 18947.456 | J51: 18947.456 | K51: 18947.456 | L51: 18947.456 | M51: 18947.456 | N51: 18947.456 | O51: 20043.007 | P51: 20043.007 | Q51: 1764043 | R51: 20043.007 | S51: 20043.007 | T51: 20043.007 | U51: 20043.007 | V51: 20043.007 | W51: 20043.007 | X51: 20043.007 | Y51: 20043.007 | Z51: 20043.007 | AA51: 21047.743 | AB51: 21047.743 | AC51: 21047.743 | AD51: 21047.743 | AE51: 21047.743 | AF51: 21047.743 | AG51: 21047.743 | AH51: 21047.743 | AI51: 21047.743 | AJ51: 1765047.7 | AK51: 21047.743 | AL51: 21047.743 | AM51: 22180.841 | AN51: 22180.841 | AO51: 22180.841 | AP51: 22180.841 | AQ51: 22180.841 | AR51: 22180.841 | AS51: 22180.841 | AT51: 22180.841 | AU51: 22180.841 | AV51: 1766180.8 | AW51: 22180.841 | AX51: 22180.841 | AY51: 23345.682 | AZ51: 23345.682 | BA51: 23345.682 | BB51: 23345.682 | BC51: 23345.682 | BD51: 23345.682 | BE51: 23345.682 | BF51: 23345.682 | BG51: 23345.682 | BH51: 1767345.7 | BI51: 23345.682 | BJ51: 23345.682 | BK51: 24540.772 | BL51: 24540.772 | BM51: 24540.772 | BN51: 24540.772 | BO51: 24540.772 | BP51: 24540.772 | BQ51: 24540.772 | BR51: 24540.772 | BS51: 24540.772 | BT51: 1108540.8 | BU51: 24540.772 | BV51: 24540.772 | BW51: 25668.34 | BX51: 25668.34 | BY51: 25668.34 | BZ51: 25668.34 | CA51: 25668.34 | CB51: 25668.34 | CC51: 25668.34 | CD51: 25668.34 | CE51: 25668.34 | CF51: 1109668.3 | CG51: 25668.34 | CH51: 25668.34 | CI51: 25655.367 | CJ51: 25655.367 | CK51: 25655.367 | CL51: 25655.367 | CM51: 25655.367 | CN51: 25655.367 | CO51: 25655.367 | CP51: 25655.367 | CQ51: 0 | CR51: 1084000 | CS51: 0 | CT51: 0 | CU51: 0 | CV51: 0 | CW51: 0 | CX51: 0 | CY51: 0 | CZ51: 0 | DA51: 0 | DB51: 0 | DC51: 0 | DD51: 1084000 | DE51: 0 | DF51: 0 | DG51: 0 | DH51: 0 | DI51: 0 | DJ51: 0 | DK51: 0 | DL51: 0 | DM51: 0 | DN51: 0 | DO51: 0 | DP51: 1084000 | DQ51: 0 | DR51: 0 | DS51: 0 | DT51: 0 | DU51: 0 | DV51: 0 | DW51: 0 | DX51: 0 | DY51: 0 | DZ51: 0 | EA51: 0 | EB51: 1084000 | EC51: 0 | ED51: 0 | EE51: 0 | EF51: 0 | EG51: 0 | EH51: 0 | EI51: 0 | EJ51: 0 | EK51: 0 | EL51: 0 | EM51: 0 | EN51: 1084000 | EO51: 0 | EP51: 0 | EQ51: 0 | ER51: 0 | ES51: 0 | ET51: 0 | EU51: 0 | EV51: 0 | EW51: 0 | EX51: 0 | EY51: 0 | EZ51: 1084000 | FA51: 0 | FB51: 3252000 | FC51: 0 | FD51: 0 | FE51: 0 | FF51: 0 | FG51: 0 | FH51: 0 | FI51: 0 | FJ51: 0 | FK51: 0 | FL51: 0 | FM51: 0 | FN51: 0 | FO51: 0 | FP51: 0 | FQ51: 0 | FR51: 0 | FS51: 0 | FT51: 0 | FU51: 0 | FV51: 0 | FW51: 0 | FX51: 0 | FY51: 0 | FZ51: 0
C52: TAX | D52: 800 | F52: 5981.9924 | G52: 0 | H52: 0 | I52: 0 | J52: 0 | K52: 0 | L52: 0 | M52: 0 | N52: 0 | O52: 0 | P52: 0 | Q52: 0 | R52: 8437.195 | S52: 0 | T52: 0 | U52: 0 | V52: 0 | W52: 0 | X52: 0 | Y52: 0 | Z52: 0 | AA52: 0 | AB52: 0 | AC52: 0 | AD52: 14269.371 | AE52: 0 | AF52: 0 | AG52: 0 | AH52: 0 | AI52: 0 | AJ52: 0 | AK52: 0 | AL52: 0 | AM52: 0 | AN52: 0 | AO52: 0 | AP52: 15551.015 | AQ52: 0 | AR52: 0 | AS52: 0 | AT52: 0 | AU52: 0 | AV52: 0 | AW52: 0 | AX52: 0 | AY52: 0 | AZ52: 0 | BA52: 0 | BB52: 38759.062 | BC52: 0 | BD52: 0 | BE52: 0 | BF52: 0 | BG52: 0 | BH52: 0 | BI52: 0 | BJ52: 0 | BK52: 0 | BL52: 0 | BM52: 0 | BN52: 46963.868 | BO52: 0 | BP52: 0 | BQ52: 0 | BR52: 0 | BS52: 0 | BT52: 0 | BU52: 0 | BV52: 0 | BW52: 0 | BX52: 0 | BY52: 0 | BZ52: 33163.445 | CA52: 0 | CB52: 0 | CC52: 0 | CD52: 0 | CE52: 0 | CF52: 0 | CG52: 0 | CH52: 0 | CI52: 0 | CJ52: 0 | CK52: 0 | CL52: 14144.506 | CM52: 0 | CN52: 0 | CO52: 0 | CP52: 0 | CQ52: 0 | CR52: 0 | CS52: 0 | CT52: 0 | CU52: 0 | CV52: 0 | CW52: 0 | CX52: 2 | CY52: 0 | CZ52: 0 | DA52: 0 | DB52: 0 | DC52: 0 | DD52: 0 | DE52: 0 | DF52: 0 | DG52: 0 | DH52: 0 | DI52: 0 | DJ52: 2 | DK52: 0 | DL52: 0 | DM52: 0 | DN52: 0 | DO52: 0 | DP52: 0 | DQ52: 0 | DR52: 0 | DS52: 0 | DT52: 0 | DU52: 0 | DV52: 2 | DW52: 0 | DX52: 0 | DY52: 0 | DZ52: 0 | EA52: 0 | EB52: 0 | EC52: 0 | ED52: 0 | EE52: 0 | EF52: 0 | EG52: 0 | EH52: 2 | EI52: 0 | EJ52: 0 | EK52: 0 | EL52: 0 | EM52: 0 | EN52: 0 | EO52: 0 | EP52: 0 | EQ52: 0 | ER52: 0 | ES52: 0 | ET52: 163.65344 | EU52: 0 | EV52: 0 | EW52: 0 | EX52: 0 | EY52: 0 | EZ52: 0 | FA52: 0 | FB52: 0 | FC52: 0 | FD52: 0 | FE52: 0.5 | FF52: 0 | FG52: 0 | FH52: 0 | FI52: 0 | FJ52: 0 | FK52: 0 | FL52: 0 | FM52: 0 | FN52: 0 | FO52: 0 | FP52: 0 | FQ52: 0 | FR52: 0 | FS52: 0 | FT52: 0 | FU52: 0 | FV52: 0 | FW52: 0 | FX52: 0 | FY52: 0
C53: Financing | D53: 600 | F53: 795.79316 | G53: 795.79316 | H53: 795.79316 | I53: 795.79316 | J53: 795.79316 | K53: 795.79316 | L53: 795.79316 | M53: 795.79316 | N53: 795.79316 | O53: 24139.485 | P53: 841.80628 | Q53: 841.80628 | R53: 841.80628 | S53: 841.80628 | T53: 841.80628 | U53: 841.80628 | V53: 841.80628 | W53: 841.80628 | X53: 841.80628 | Y53: 841.80628 | Z53: 841.80628 | AA53: 884.00521 | AB53: 884.00521 | AC53: 884.00521 | AD53: 884.00521 | AE53: 884.00521 | AF53: 884.00521 | AG53: 884.00521 | AH53: 884.00521 | AI53: 884.00521 | AJ53: 884.00521 | AK53: 884.00521 | AL53: 884.00521 | AM53: 931.59533 | AN53: 931.59533 | AO53: 931.59533 | AP53: 931.59533 | AQ53: 931.59533 | AR53: 931.59533 | AS53: 931.59533 | AT53: 931.59533 | AU53: 931.59533 | AV53: 931.59533 | AW53: 931.59533 | AX53: 931.59533 | AY53: 980.51866 | AZ53: 980.51866 | BA53: 980.51866 | BB53: 980.51866 | BC53: 980.51866 | BD53: 980.51866 | BE53: 980.51866 | BF53: 980.51866 | BG53: 980.51866 | BH53: 980.51866 | BI53: 980.51866 | BJ53: 980.51866 | BK53: 1030.7124 | BL53: 1030.7124 | BM53: 1030.7124 | BN53: 1030.7124 | BO53: 1030.7124 | BP53: 1030.7124 | BQ53: 1030.7124 | BR53: 1030.7124 | BS53: 1030.7124 | BT53: 1030.7124 | BU53: 1030.7124 | BV53: 1030.7124 | BW53: 1078.0703 | BX53: 1078.0703 | BY53: 1078.0703 | BZ53: 1078.0703 | CA53: 1078.0703 | CB53: 1078.0703 | CC53: 1078.0703 | CD53: 1078.0703 | CE53: 1078.0703 | CF53: 1078.0703 | CG53: 1078.0703 | CH53: 1078.0703 | CI53: 1077.5254 | CJ53: 1077.5254 | CK53: 1077.5254 | CL53: 1077.5254 | CM53: 1077.5254 | CN53: 1077.5254 | CO53: 1077.5254 | CP53: 1077.5254 | CQ53: 1077.5254 | CR53: 1077.5254 | CS53: 1077.5254 | CT53: 1077.5254 | CU53: 1089.9097 | CV53: 1089.9097 | CW53: 1089.9097 | CX53: 1089.9097 | CY53: 1089.9097 | CZ53: 1089.9097 | DA53: 1089.9097 | DB53: 1089.9097 | DC53: 1089.9097 | DD53: 1089.9097 | DE53: 1089.9097 | DF53: 1089.9097 | DG53: 1145.9444 | DH53: 1145.9444 | DI53: 1145.9444 | DJ53: 1145.9444 | DK53: 1145.9444 | DL53: 1145.9444 | DM53: 1145.9444 | DN53: 1145.9444 | DO53: 1145.9444 | DP53: 1145.9444 | DQ53: 1145.9444 | DR53: 1145.9444 | DS53: 1201.7378 | DT53: 1201.7378 | DU53: 1201.7378 | DV53: 1201.7378 | DW53: 1201.7378 | DX53: 1201.7378 | DY53: 1201.7378 | DZ53: 1201.7378 | EA53: 1201.7378 | EB53: 1201.7378 | EC53: 1201.7378 | ED53: 1201.7378 | EE53: 1260.2877 | EF53: 1260.2877 | EG53: 1260.2877 | EH53: 1260.2877 | EI53: 1260.2877 | EJ53: 1260.2877 | EK53: 1260.2877 | EL53: 1260.2877 | EM53: 1260.2877 | EN53: 1260.2877 | EO53: 1260.2877 | EP53: 1260.2877 | EQ53: 1321.7316 | ER53: 1321.7316 | ES53: 1321.7316 | ET53: 1321.7316 | EU53: 1321.7316 | EV53: 1321.7316 | EW53: 1321.7316 | EX53: 1321.7316 | EY53: 1321.7316 | EZ53: 1321.7316 | FA53: 1321.7316 | FB53: 1321.7316 | FC53: 1386.2138 | FD53: 1386.2138 | FE53: 1386.2138 | FF53: 0 | FG53: 0 | FH53: 0 | FI53: 0 | FJ53: 0 | FK53: 0 | FL53: 0 | FM53: 0 | FN53: 0 | FO53: 0 | FP53: 0 | FQ53: 0 | FR53: 0 | FS53: 0 | FT53: 0 | FU53: 0 | FV53: 0 | FW53: 0 | FX53: 0 | FY53: 0

Sheet Cost Until 07-26
C1: CategoryName | D1: SubcategoryName | E1: Tipo | F1: TOTAL | G1: 2021-04 | H1: 2021-05 | I1: 2021-06 | J1: 2021-07 | K1: 2021-08 | L1: 2021-09 | M1: 2021-10 | N1: 2021-11 | O1: 2021-12 | P1: 2022-01 | Q1: 2022-02 | R1: 2022-03 | S1: 2022-04 | T1: 2022-05 | U1: 2022-06 | V1: 2022-07 | W1: 2022-08 | X1: 2022-09 | Y1: 2022-10 | Z1: 2022-11 | AA1: 2022-12 | AB1: 2023-01 | AC1: 2023-02 | AD1: 2023-03 | AE1: 2023-04 | AF1: 2023-05 | AG1: 2023-06 | AH1: 2023-07 | AI1: 2023-08 | AJ1: 2023-09 | AK1: 2023-10 | AL1: 2023-11 | AM1: 2023-12 | AN1: 2024-01 | AO1: 2024-02 | AP1: 2024-03 | AQ1: 2024-04 | AR1: 2024-05 | AS1: 2024-06 | AT1: 2024-07 | AU1: 2024-08 | AV1: 2024-09 | AW1: 2024-10 | AX1: 2024-11 | AY1: 2024-12 | AZ1: 2025-01 | BA1: 2025-02 | BB1: 2025-03 | BC1: 2025-04 | BD1: 2025-05 | BE1: 2025-06 | BF1: 2025-07 | BG1: 2025-08 | BH1: 2025-09 | BI1: 2025-10 | BJ1: 2025-11 | BK1: 2025-12 | BL1: 2026-01 | BM1: 2026-02 | BN1: 2026-03 | BO1: 2026-04 | BP1: 2026-05 | BQ1: 2026-06 | BR1: 2026-07
C2: EPC (100) | D2: EPC (100) | E2: COST-REAL | F2: =SUM(G2:BR2) -> 2397665.5 | G2: =SUM(G3:G30) -> 0 | H2: =SUM(H3:H30) -> 34620 | I2: =SUM(I3:I30) -> 1801 | J2: =SUM(J3:J30) -> 10517 | K2: =SUM(K3:K30) -> 27584 | L2: =SUM(L3:L30) -> 19328 | M2: =SUM(M3:M30) -> 8626 | N2: =SUM(N3:N30) -> 6523 | ... BR2: =SUM(BR3:BR30) -> 978
C3: EPC (100) | D3: Advance Payment (101) | E3: → CHINA RAILWAY CONSTRUCCION CORPORATION (INTERNATIONAL) LIMITED | F3: =SUM(G3:BR3) -> 500000 | G3: 0 | H3: 0 | I3: 0 | J3: 0 | K3: 0 | L3: 0 | M3: 0 | N3: 0 | O3: 0 | P3: 0 | Q3: 0 | R3: 0 | S3: 0 | T3: 0 | U3: 0 | V3: 0 | W3: 0 | X3: 0 | Y3: 0 | Z3: 0 | AA3: 0 | AB3: 0 | AC3: 0 | AD3: 0 | AE3: 0 | AF3: 0 | AG3: 0 | AH3: 0 | AI3: 0 | AJ3: 0 | AK3: 0 | AL3: 0 | AM3: 0 | AN3: 0 | AO3: 0 | AP3: 0 | AQ3: 300000 | AR3: 0 | AS3: 0 | AT3: 0 | AU3: 0 | AV3: 0 | AW3: 0 | AX3: 0 | AY3: 0 | AZ3: 0 | BA3: 0 | BB3: 0 | BC3: 0 | BD3: 0 | BE3: 0 | BF3: 200000 | BG3: 0 | BH3: 0 | BI3: 0 | BJ3: 0 | BK3: 0 | BL3: 0 | BM3: 0 | BN3: 0 | BO3: 0 | BP3: 0 | BQ3: 0 | BR3: 0
C4: EPC (100) | D4: PID (102) | E4: → ALPHA INGENIEROS CONSULTORES SPA | F4: =SUM(G4:BR4) -> 9356.93 | G4: 0 | H4: 0 | I4: 0 | J4: 0 | K4: 0 | L4: 0 | M4: 0 | N4: 0 | O4: 0 | P4: 0 | Q4: 0 | R4: 0 | S4: 0 | T4: 0 | U4: 0 | V4: 0 | W4: 0 | X4: 0 | Y4: 0 | Z4: 0 | AA4: 0 | AB4: 0 | AC4: 0 | AD4: 0 | AE4: 0 | AF4: 0 | AG4: 0 | AH4: 0 | AI4: 0 | AJ4: 0 | AK4: 0 | AL4: 0 | AM4: 0 | AN4: 995 | AO4: 497 | AP4: 0 | AQ4: 1989 | AR4: 0 | AS4: 995 | AT4: 995 | AU4: 0 | AV4: 504 | AW4: 0 | AX4: 1053 | AY4: 0 | AZ4: 0 | BA4: 0 | BB4: 0 | BC4: 540 | BD4: 0 | BE4: 0 | BF4: 0 | BG4: 495 | BH4: 0 | BI4: 828 | BJ4: 0 | BK4: 0 | BL4: 0 | BM4: 465.93 | BN4: 0 | BO4: 0 | BP4: 0 | BQ4: 0 | BR4: 0
C5: EPC (100) | D5: PID (102) | E5: → CHINA RAILWAY CONSTRUCCION CORPORATION (INTERNATIONAL) LIMITED | F5: =SUM(G5:BR5) -> 80196 | G5: 0 | H5: 0 | I5: 0 | J5: 0 | K5: 26750 | L5: 0 | M5: 0 | N5: 5350 | O5: 1783 | P5: 1782 | Q5: 1781 | R5: 1781 | S5: 0 | T5: 1758 | U5: 3545 | V5: 1784 | W5: 1783 | X5: 0 | Y5: 3570 | Z5: 1783 | AA5: 0 | AB5: 0 | AC5: 5350 | AD5: 1783 | AE5: 1783 | AF5: 1783 | AG5: 1783 | AH5: 1783 | AI5: 1783 | AJ5: 1783 | AK5: 1783 | AL5: 1783 | AM5: 1783 | AN5: 1783 | AO5: 1783 | AP5: 0 | AQ5: 0 | AR5: 0 | AS5: 0 | AT5: 0 | AU5: 0 | AV5: 0 | AW5: 0 | AX5: 0 | AY5: 0 | AZ5: 0 | BA5: 0 | BB5: 0 | BC5: 0 | BD5: 0 | BE5: 0 | BF5: 0 | BG5: 0 | BH5: 0 | BI5: 0 | BJ5: 0 | BK5: 0 | BL5: 0 | BM5: 0 | BN5: 0 | BO5: 0 | BP5: 0 | BQ5: 0 | BR5: 0
C6: EPC (100) | D6: PID (102) | E6: → HILDEBRANDT Y ASOCIADOS ARQUITECTOS INGENIEROS CONSULTORES LIMITADA | F6: =SUM(G6:BR6) -> 19174 | G6: 0 | H6: 0 | I6: 0 | J6: 0 | K6: 0 | L6: 0 | M6: 0 | N6: 0 | O6: 0 | P6: 0 | Q6: 3551 | R6: 0 | S6: 2698 | T6: 0 | U6: 2586 | V6: 2255 | W6: 2743 | X6: 0 | Y6: 1674 | Z6: 1095 | AA6: 902 | AB6: 0 | AC6: 930 | AD6: 0 | AE6: 358 | AF6: 191 | AG6: 191 | AH6: 0 | AI6: 0 | AJ6: 0 | AK6: 0 | AL6: 0 | AM6: 0 | AN6: 0 | AO6: 0 | AP6: 0 | AQ6: 0 | AR6: 0 | AS6: 0 | AT6: 0 | AU6: 0 | AV6: 0 | AW6: 0 | AX6: 0 | AY6: 0 | AZ6: 0 | BA6: 0 | BB6: 0 | BC6: 0 | BD6: 0 | BE6: 0 | BF6: 0 | BG6: 0 | BH6: 0 | BI6: 0 | BJ6: 0 | BK6: 0 | BL6: 0 | BM6: 0 | BN6: 0 | BO6: 0 | BP6: 0 | BQ6: 0 | BR6: 0
C7: EPC (100) | D7: PID (102) | E7: → INGELOG CONSULTORES DE INGENIERIA Y SISTEMAS S.A. | F7: =SUM(G7:BR7) -> 347149 | G7: 0 | H7: 0 | I7: 0 | J7: 6772 | K7: 176 | L7: 17955 | M7: 7125 | N7: 0 | O7: 2356 | P7: 3605 | Q7: 0 | R7: 31891 | S7: 0 | T7: 0 | U7: 48322 | V7: 0 | W7: 0 | X7: 82369 | Y7: 0 | Z7: 1472 | AA7: 28289 | AB7: 0 | AC7: 0 | AD7: 0 | AE7: 0 | AF7: 28832 | AG7: 0 | AH7: 0 | AI7: 13227 | AJ7: 0 | AK7: 0 | AL7: 18034 | AM7: 0 | AN7: 0 | AO7: 0 | AP7: 0 | AQ7: 0 | AR7: 0 | AS7: 0 | AT7: 0 | AU7: 0 | AV7: 38575 | AW7: 0 | AX7: 0 | AY7: 0 | AZ7: 0 | BA7: 0 | BB7: 0 | BC7: 0 | BD7: 7560 | BE7: 0 | BF7: 0 | BG7: 0 | BH7: 0 | BI7: 0 | BJ7: 0 | BK7: 0 | BL7: 10589 | BM7: 0 | BN7: 0 | BO7: 0 | BP7: 0 | BQ7: 0 | BR7: 0
C8: EPC (100) | D8: PID (102) | E8: → INGENIERIA CALCULO Y CONSTRUCCION JLS INGENIERIA LIMITADA | F8: =SUM(G8:BR8) -> 17379.44 | G8: 0 | H8: 0 | I8: 0 | J8: 0 | K8: 0 | L8: 0 | M8: 0 | N8: 0 | O8: 0 | P8: 0 | Q8: 0 | R8: 0 | S8: 0 | T8: 0 | U8: 0 | V8: 0 | W8: 0 | X8: 0 | Y8: 0 | Z8: 0 | AA8: 0 | AB8: 0 | AC8: 0 | AD8: 0 | AE8: 0 | AF8: 0 | AG8: 0 | AH8: 0 | AI8: 0 | AJ8: 0 | AK8: 0 | AL8: 0 | AM8: 0 | AN8: 0 | AO8: 1728 | AP8: 0 | AQ8: 559 | AR8: 0 | AS8: 0 | AT8: 890 | AU8: 1272 | AV8: 0 | AW8: 1380 | AX8: 1048 | AY8: 0 | AZ8: 0 | BA8: 0 | BB8: 871 | BC8: 125 | BD8: 555 | BE8: 0 | BF8: 4276 | BG8: 0 | BH8: 0 | BI8: 0 | BJ8: 3684 | BK8: 0 | BL8: 0 | BM8: 991.44 | BN8: 0 | BO8: 0 | BP8: 0 | BQ8: 0 | BR8: 0
C9: EPC (100) | D9: PID (102) | E9: → LEN Y ASOCIADOS LTDA INGENIEROS CONSULTO | F9: =SUM(G9:BR9) -> 11828.23 | G9: 0 | H9: 0 | I9: 0 | J9: 0 | K9: 0 | L9: 0 | M9: 0 | N9: 0 | O9: 0 | P9: 0 | Q9: 0 | R9: 0 | S9: 0 | T9: 0 | U9: 0 | V9: 0 | W9: 0 | X9: 0 | Y9: 0 | Z9: 0 | AA9: 0 | AB9: 0 | AC9: 0 | AD9: 0 | AE9: 0 | AF9: 0 | AG9: 0 | AH9: 0 | AI9: 0 | AJ9: 0 | AK9: 0 | AL9: 0 | AM9: 0 | AN9: 0 | AO9: 0 | AP9: 0 | AQ9: 0 | AR9: 5279 | AS9: 0 | AT9: 0 | AU9: 2420 | AV9: 0 | AW9: 2641 | AX9: 184 | AY9: 0 | AZ9: 0 | BA9: 248 | BB9: 0 | BC9: 0 | BD9: 0 | BE9: 0 | BF9: 107 | BG9: 0 | BH9: 0 | BI9: 0 | BJ9: 0 | BK9: 0 | BL9: 381.6 | BM9: 0 | BN9: 0 | BO9: 0 | BP9: 0 | BQ9: 567.63 | BR9: 0
C10: EPC (100) | D10: PID (102) | E10: → O P H INGENIEROS CONSULTORES LIMITADA | F10: =SUM(G10:BR10) -> 14290 | G10: 0 | H10: 0 | I10: 0 | J10: 0 | K10: 0 | L10: 0 | M10: 0 | N10: 0 | O10: 0 | P10: 0 | Q10: 0 | R10: 0 | S10: 0 | T10: 0 | U10: 0 | V10: 0 | W10: 0 | X10: 0 | Y10: 0 | Z10: 0 | AA10: 0 | AB10: 0 | AC10: 0 | AD10: 0 | AE10: 0 | AF10: 0 | AG10: 0 | AH10: 0 | AI10: 0 | AJ10: 0 | AK10: 0 | AL10: 0 | AM10: 0 | AN10: 0 | AO10: 0 | AP10: 0 | AQ10: 3186 | AR10: 0 | AS10: 1929 | AT10: 1464 | AU10: 0 | AV10: 0 | AW10: 0 | AX10: 0 | AY10: 3929 | AZ10: 0 | BA10: 0 | BB10: 0 | BC10: 921 | BD10: 0 | BE10: 0 | BF10: 0 | BG10: 0 | BH10: 2162 | BI10: 0 | BJ10: 699 | BK10: 0 | BL10: 0 | BM10: 0 | BN10: 0 | BO10: 0 | BP10: 0 | BQ10: 0 | BR10: 0
C11: EPC (100) | D11: Construction Toll Plaza (104) | E11: → CHINA RAILWAY CONSTRUCCION CORPORATION (INTERNATIONAL) LIMITED | F11: =SUM(G11:BR11) -> 357758 | G11: 0 | H11: 0 | I11: 0 | J11: 0 | K11: 0 | L11: 0 | M11: 0 | N11: 0 | O11: 0 | P11: 68981 | Q11: 0 | R11: 50424 | S11: 39288 | T11: 0 | U11: 0 | V11: 0 | W11: 130782 | X11: 0 | Y11: 0 | Z11: 4427 | AA11: 53980 | AB11: 0 | AC11: 0 | AD11: 0 | AE11: 0 | AF11: 338 | AG11: 0 | AH11: 0 | AI11: 0 | AJ11: 0 | AK11: 2045 | AL11: 7493 | AM11: 0 | AN11: 0 | AO11: 0 | AP11: 0 | AQ11: 0 | AR11: 0 | AS11: 0 | AT11: 0 | AU11: 0 | AV11: 0 | AW11: 0 | AX11: 0 | AY11: 0 | AZ11: 0 | BA11: 0 | BB11: 0 | BC11: 0 | BD11: 0 | BE11: 0 | BF11: 0 | BG11: 0 | BH11: 0 | BI11: 0 | BJ11: 0 | BK11: 0 | BL11: 0 | BM11: 0 | BN11: 0 | BO11: 0 | BP11: 0 | BQ11: 0 | BR11: 0
